Workbook

Sheet Pricing_model
A1: SKU | B1: Total_Cost | C1: Min_Price | D1: Target_Price | E1: Lowest_Competitor_Price | F1: Highest_Competitor_price | G1: Avg_Competitor_Price | H1: Days_of_Supply | I1: Weeks_of_Cover_t30 | J1: Avg_Acos14D | K1: Avg_Roas14D | L1: Conversion_Rate | M1: Base_Price | N1: After_Competitor_Price | O1: Inventory_Factory | P1: After_Inventory_Price | Q1: Demand_Factor | R1: After_Demand_Price | S1: Final_Recommended_Price | T1: Pricing_Reason | U1: Price_Increase_Potential | V1: Primary_Pricing_Driver
A2: MN-01 | B2: =IFERROR(INDEX(Pricing_Data[Total_Cost],MATCH(Pricing_model!A2,Pricing_Data[SKU],0)),"") -> 32.3 | C2: =INDEX(Pricing_Data[Min_Price],MATCH(A2,Pricing_Data[SKU],0)) -> 40.375 | D2: =INDEX(Pricing_Data[Target_Price],MATCH(Pricing_model!A2,Pricing_Data[SKU],0)) -> 49.692308 | E2: =INDEX(Competitor_Data[Lowest_Competitor_Price],MATCH(Pricing_model!A2,Competitor_Data[SKU],0)) -> 31.95 | F2: =INDEX(Competitor_Data[Highest_Competitor_Price],MATCH(Pricing_model!A2,Competitor_Data[SKU],0)) -> 44.9 | G2: =INDEX(Competitor_Data[Avg_Competitor_Price],MATCH(Pricing_model!A2,Competitor_Data[SKU],0)) -> 36.9 | H2: =INDEX(Inventory_Health__2[days-of-supply],MATCH(Pricing_model!A2,Inventory_Health__2[SKU],0)) -> 47 | I2: =INDEX(Inventory_Health__2[weeks-of-cover-t30],MATCH(Pricing_model!A2,Inventory_Health__2[SKU],0)) -> 6 | J2: =INDEX(Ads_Performance!AF12:AF61,MATCH(Pricing_model!A2,Ads_Performance!AE12:AE61,0)) -> 31.486923 | K2: =INDEX(Ads_Performance!AG12:AG61,MATCH(Pricing_model!A2,Ads_Performance!AE12:AE61,0)) -> 6.0015491 | L2: =INDEX(Historical_Sales!O8:O57,MATCH(Pricing_model!A2,Historical_Sales!L8:L57,0)) -> 0.30557002 | M2: =D2 -> 49.692308 | N2: =IF(AND(G2<>"", M2> G2),G2,M2) -> 36.9 | O2: =IF( H2=0, 1, IF( H2 < 45, 1.05, IF( H2 > 90, 0.95, IF( I2 > 10, 0.95, 1 ) ) ) ) -> 1 | P2: =N2*O2 -> 36.9 | Q2: =IF( AND(K2>=6, L2>=0.3, J2<=35), 1.03, IF(OR(J2>35, K2<3), 0.95, 1) ) -> 1.03 | R2: =P2*Q2 -> 38.007 | S2: =MAX(R2,C2) -> 40.375 | T2: =_xlfn.TEXTJOIN(", ", TRUE, IF(H2 < 15, "Low inventory", ""), IF(I2 > 8, "Overstock", ""), IF(G2<>"", "Competitor benchmark", ""), IF(K2 > 3, "Strong ads", ""), IF(J2 > 0.4, "High ad cost", "") ) -> Competitor benchmark, Strong ads, High ad cost | U2: =IF(Table3[[#This Row],[Final_Recommended_Price]]>Table3[[#This Row],[Min_Price]],"Yes","No") -> No | V2: =IF( S2=C2, "Minimum margin constraint", IF( G2<>"", "Competitor benchmark", IF( O2>1, "Low inventory", IF( O2<1, "Overstock", IF( Q2>1, "Strong demand / ads", IF(Q2<1, "High ad cost", "Neutral") ) ) ) ) ) -> Minimum margin constraint
A3: MN-02 | B3: =IFERROR(INDEX(Pricing_Data[Total_Cost],MATCH(Pricing_model!A3,Pricing_Data[SKU],0)),"") -> 26.6 | C3: =INDEX(Pricing_Data[Min_Price],MATCH(A3,Pricing_Data[SKU],0)) -> 33.25 | D3: =INDEX(Pricing_Data[Target_Price],MATCH(Pricing_model!A3,Pricing_Data[SKU],0)) -> 40.923077 | E3: =INDEX(Competitor_Data[Lowest_Competitor_Price],MATCH(Pricing_model!A3,Competitor_Data[SKU],0)) -> 27.9 | F3: =INDEX(Competitor_Data[Highest_Competitor_Price],MATCH(Pricing_model!A3,Competitor_Data[SKU],0)) -> 39.95 | G3: =INDEX(Competitor_Data[Avg_Competitor_Price],MATCH(Pricing_model!A3,Competitor_Data[SKU],0)) -> 32.5 | H3: =INDEX(Inventory_Health__2[days-of-supply],MATCH(Pricing_model!A3,Inventory_Health__2[SKU],0)) -> 85 | I3: =INDEX(Inventory_Health__2[weeks-of-cover-t30],MATCH(Pricing_model!A3,Inventory_Health__2[SKU],0)) -> 7 | J3: =INDEX(Ads_Performance!AF13:AF62,MATCH(Pricing_model!A3,Ads_Performance!AE13:AE62,0)) -> 17.429955 | K3: =INDEX(Ads_Performance!AG13:AG62,MATCH(Pricing_model!A3,Ads_Performance!AE13:AE62,0)) -> 11.141498 | L3: =INDEX(Historical_Sales!O9:O58,MATCH(Pricing_model!A3,Historical_Sales!L9:L58,0)) -> 0.2339848 | M3: =D3 -> 40.923077 | N3: =IF(AND(G3<>"", M3> G3),G3,M3) -> 32.5 | O3: =IF( H3=0, 1, IF( H3 < 45, 1.05, IF( H3 > 90, 0.95, IF( I3 > 10, 0.95, 1 ) ) ) ) -> 1 | P3: =N3*O3 -> 32.5 | Q3: =IF( AND(K3>=6, L3>=0.3, J3<=35), 1.03, IF(OR(J3>35, K3<3), 0.95, 1) ) -> 1 | R3: =P3*Q3 -> 32.5 | S3: =MAX(R3,C3) -> 33.25 | T3: =_xlfn.TEXTJOIN(", ", TRUE, IF(H3 < 15, "Low inventory", ""), IF(I3 > 8, "Overstock", ""), IF(G3<>"", "Competitor benchmark", ""), IF(K3 > 3, "Strong ads", ""), IF(J3 > 0.4, "High ad cost", "") ) -> Competitor benchmark, Strong ads, High ad cost | U3: =IF(Table3[[#This Row],[Final_Recommended_Price]]>Table3[[#This Row],[Min_Price]],"Yes","No") -> No | V3: =IF( S3=C3, "Minimum margin constraint", IF( G3<>"", "Competitor benchmark", IF( O3>1, "Low inventory", IF( O3<1, "Overstock", IF( Q3>1, "Strong demand / ads", IF(Q3<1, "High ad cost", "Neutral") ) ) ) ) ) -> Minimum margin constraint
A4: MN-03 | B4: =IFERROR(INDEX(Pricing_Data[Total_Cost],MATCH(Pricing_model!A4,Pricing_Data[SKU],0)),"") -> 30.03 | C4: =INDEX(Pricing_Data[Min_Price],MATCH(A4,Pricing_Data[SKU],0)) -> 37.5375 | D4: =INDEX(Pricing_Data[Target_Price],MATCH(Pricing_model!A4,Pricing_Data[SKU],0)) -> 46.2 | E4: =INDEX(Competitor_Data[Lowest_Competitor_Price],MATCH(Pricing_model!A4,Competitor_Data[SKU],0)) -> 29.99 | F4: =INDEX(Competitor_Data[Highest_Competitor_Price],MATCH(Pricing_model!A4,Competitor_Data[SKU],0)) -> 42.5 | G4: =INDEX(Competitor_Data[Avg_Competitor_Price],MATCH(Pricing_model!A4,Competitor_Data[SKU],0)) -> 35.2 | H4: =INDEX(Inventory_Health__2[days-of-supply],MATCH(Pricing_model!A4,Inventory_Health__2[SKU],0)) -> 83 | I4: =INDEX(Inventory_Health__2[weeks-of-cover-t30],MATCH(Pricing_model!A4,Inventory_Health__2[SKU],0)) -> 8 | J4: =INDEX(Ads_Performance!AF14:AF63,MATCH(Pricing_model!A4,Ads_Performance!AE14:AE63,0)) -> 14.183546 | K4: =INDEX(Ads_Performance!AG14:AG63,MATCH(Pricing_model!A4,Ads_Performance!AE14:AE63,0)) -> 10.859895 | L4: =INDEX(Historical_Sales!O10:O59,MATCH(Pricing_model!A4,Historical_Sales!L10:L59,0)) -> 0.22817229 | M4: =D4 -> 46.2 | N4: =IF(AND(G4<>"", M4> G4),G4,M4) -> 35.2 | O4: =IF( H4=0, 1, IF( H4 < 45, 1.05, IF( H4 > 90, 0.95, IF( I4 > 10, 0.95, 1 ) ) ) ) -> 1 | P4: =N4*O4 -> 35.2 | Q4: =IF( AND(K4>=6, L4>=0.3, J4<=35), 1.03, IF(OR(J4>35, K4<3), 0.95, 1) ) -> 1 | R4: =P4*Q4 -> 35.2 | S4: =MAX(R4,C4) -> 37.5375 | T4: =_xlfn.TEXTJOIN(", ", TRUE, IF(H4 < 15, "Low inventory", ""), IF(I4 > 8, "Overstock", ""), IF(G4<>"", "Competitor benchmark", ""), IF(K4 > 3, "Strong ads", ""), IF(J4 > 0.4, "High ad cost", "") ) -> Competitor benchmark, Strong ads, High ad cost | U4: =IF(Table3[[#This Row],[Final_Recommended_Price]]>Table3[[#This Row],[Min_Price]],"Yes","No") -> No | V4: =IF( S4=C4, "Minimum margin constraint", IF( G4<>"", "Competitor benchmark", IF( O4>1, "Low inventory", IF( O4<1, "Overstock", IF( Q4>1, "Strong demand / ads", IF(Q4<1, "High ad cost", "Neutral") ) ) ) ) ) -> Minimum margin constraint
A5: MN-04 | B5: =IFERROR(INDEX(Pricing_Data[Total_Cost],MATCH(Pricing_model!A5,Pricing_Data[SKU],0)),"") -> 25.94 | C5: =INDEX(Pricing_Data[Min_Price],MATCH(A5,Pricing_Data[SKU],0)) -> 32.425 | D5: =INDEX(Pricing_Data[Target_Price],MATCH(Pricing_model!A5,Pricing_Data[SKU],0)) -> 39.907692 | E5: =INDEX(Competitor_Data[Lowest_Competitor_Price],MATCH(Pricing_model!A5,Competitor_Data[SKU],0)) -> 24.5 | F5: =INDEX(Competitor_Data[Highest_Competitor_Price],MATCH(Pricing_model!A5,Competitor_Data[SKU],0)) -> 35.9 | G5: =INDEX(Competitor_Data[Avg_Competitor_Price],MATCH(Pricing_model!A5,Competitor_Data[SKU],0)) -> 28.4 | H5: =INDEX(Inventory_Health__2[days-of-supply],MATCH(Pricing_model!A5,Inventory_Health__2[SKU],0)) -> 99 | I5: =INDEX(Inventory_Health__2[weeks-of-cover-t30],MATCH(Pricing_model!A5,Inventory_Health__2[SKU],0)) -> 8 | J5: =INDEX(Ads_Performance!AF15:AF64,MATCH(Pricing_model!A5,Ads_Performance!AE15:AE64,0)) -> 40.747658 | K5: =INDEX(Ads_Performance!AG15:AG64,MATCH(Pricing_model!A5,Ads_Performance!AE15:AE64,0)) -> 5.490357 | L5: =INDEX(Historical_Sales!O11:O60,MATCH(Pricing_model!A5,Historical_Sales!L11:L60,0)) -> 0.31622517 | M5: =D5 -> 39.907692 | N5: =IF(AND(G5<>"", M5> G5),G5,M5) -> 28.4 | O5: =IF( H5=0, 1, IF( H5 < 45, 1.05, IF( H5 > 90, 0.95, IF( I5 > 10, 0.95, 1 ) ) ) ) -> 0.95 | P5: =N5*O5 -> 26.98 | Q5: =IF( AND(K5>=6, L5>=0.3, J5<=35), 1.03, IF(OR(J5>35, K5<3), 0.95, 1) ) -> 0.95 | R5: =P5*Q5 -> 25.631 | S5: =MAX(R5,C5) -> 32.425 | T5: =_xlfn.TEXTJOIN(", ", TRUE, IF(H5 < 15, "Low inventory", ""), IF(I5 > 8, "Overstock", ""), IF(G5<>"", "Competitor benchmark", ""), IF(K5 > 3, "Strong ads", ""), IF(J5 > 0.4, "High ad cost", "") ) -> Competitor benchmark, Strong ads, High ad cost | U5: =IF(Table3[[#This Row],[Final_Recommended_Price]]>Table3[[#This Row],[Min_Price]],"Yes","No") -> No | V5: =IF( S5=C5, "Minimum margin constraint", IF( G5<>"", "Competitor benchmark", IF( O5>1, "Low inventory", IF( O5<1, "Overstock", IF( Q5>1, "Strong demand / ads", IF(Q5<1, "High ad cost", "Neutral") ) ) ) ) ) -> Minimum margin constraint
A6: MN-05 | B6: =IFERROR(INDEX(Pricing_Data[Total_Cost],MATCH(Pricing_model!A6,Pricing_Data[SKU],0)),"") -> 25.77 | C6: =INDEX(Pricing_Data[Min_Price],MATCH(A6,Pricing_Data[SKU],0)) -> 34.36 | D6: =INDEX(Pricing_Data[Target_Price],MATCH(Pricing_model!A6,Pricing_Data[SKU],0)) -> 46.854545 | E6: =INDEX(Competitor_Data[Lowest_Competitor_Price],MATCH(Pricing_model!A6,Competitor_Data[SKU],0)) -> 18.95 | F6: =INDEX(Competitor_Data[Highest_Competitor_Price],MATCH(Pricing_model!A6,Competitor_Data[SKU],0)) -> 0 | G6: =INDEX(Competitor_Data[Avg_Competitor_Price],MATCH(Pricing_model!A6,Competitor_Data[SKU],0)) -> 23.9 | H6: =INDEX(Inventory_Health__2[days-of-supply],MATCH(Pricing_model!A6,Inventory_Health__2[SKU],0)) -> 145 | I6: =INDEX(Inventory_Health__2[weeks-of-cover-t30],MATCH(Pricing_model!A6,Inventory_Health__2[SKU],0)) -> 0 | J6: =INDEX(Ads_Performance!AF16:AF65,MATCH(Pricing_model!A6,Ads_Performance!AE16:AE65,0)) -> 25.843374 | K6: =INDEX(Ads_Performance!AG16:AG65,MATCH(Pricing_model!A6,Ads_Performance!AE16:AE65,0)) -> 2.5731512 | L6: =INDEX(Historical_Sales!O12:O61,MATCH(Pricing_model!A6,Historical_Sales!L12:L61,0)) -> 0.17788211 | M6: =D6 -> 46.854545 | N6: =IF(AND(G6<>"", M6> G6),G6,M6) -> 23.9 | O6: =IF( H6=0, 1, IF( H6 < 45, 1.05, IF( H6 > 90, 0.95, IF( I6 > 10, 0.95, 1 ) ) ) ) -> 0.95 | P6: =N6*O6 -> 22.705 | Q6: =IF( AND(K6>=6, L6>=0.3, J6<=35), 1.03, IF(OR(J6>35, K6<3), 0.95, 1) ) -> 0.95 | R6: =P6*Q6 -> 21.56975 | S6: =MAX(R6,C6) -> 34.36 | T6: =_xlfn.TEXTJOIN(", ", TRUE, IF(H6 < 15, "Low inventory", ""), IF(I6 > 8, "Overstock", ""), IF(G6<>"", "Competitor benchmark", ""), IF(K6 > 3, "Strong ads", ""), IF(J6 > 0.4, "High ad cost", "") ) -> Competitor benchmark, High ad cost | U6: =IF(Table3[[#This Row],[Final_Recommended_Price]]>Table3[[#This Row],[Min_Price]],"Yes","No") -> No | V6: =IF( S6=C6, "Minimum margin constraint", IF( G6<>"", "Competitor benchmark", IF( O6>1, "Low inventory", IF( O6<1, "Overstock", IF( Q6>1, "Strong demand / ads", IF(Q6<1, "High ad cost", "Neutral") ) ) ) ) ) -> Minimum margin constraint
A7: MN-06 | B7: =IFERROR(INDEX(Pricing_Data[Total_Cost],MATCH(Pricing_model!A7,Pricing_Data[SKU],0)),"") -> 14.37 | C7: =INDEX(Pricing_Data[Min_Price],MATCH(A7,Pricing_Data[SKU],0)) -> 19.16 | D7: =INDEX(Pricing_Data[Target_Price],MATCH(Pricing_model!A7,Pricing_Data[SKU],0)) -> 26.127273 | E7: =INDEX(Competitor_Data[Lowest_Competitor_Price],MATCH(Pricing_model!A7,Competitor_Data[SKU],0)) -> 12.99 | F7: =INDEX(Competitor_Data[Highest_Competitor_Price],MATCH(Pricing_model!A7,Competitor_Data[SKU],0)) -> 21.5 | G7: =INDEX(Competitor_Data[Avg_Competitor_Price],MATCH(Pricing_model!A7,Competitor_Data[SKU],0)) -> 15.8 | H7: =INDEX(Inventory_Health__2[days-of-supply],MATCH(Pricing_model!A7,Inventory_Health__2[SKU],0)) -> 0 | I7: =INDEX(Inventory_Health__2[weeks-of-cover-t30],MATCH(Pricing_model!A7,Inventory_Health__2[SKU],0)) -> 0 | J7: =INDEX(Ads_Performance!AF17:AF66,MATCH(Pricing_model!A7,Ads_Performance!AE17:AE66,0)) -> 49.906491 | K7: =INDEX(Ads_Performance!AG17:AG66,MATCH(Pricing_model!A7,Ads_Performance!AE17:AE66,0)) -> 1.8697301 | L7: =INDEX(Historical_Sales!O13:O62,MATCH(Pricing_model!A7,Historical_Sales!L13:L62,0)) -> 0.22064057 | M7: =D7 -> 26.127273 | N7: =IF(AND(G7<>"", M7> G7),G7,M7) -> 15.8 | O7: =IF( H7=0, 1, IF( H7 < 45, 1.05, IF( H7 > 90, 0.95, IF( I7 > 10, 0.95, 1 ) ) ) ) -> 1 | P7: =N7*O7 -> 15.8 | Q7: =IF( AND(K7>=6, L7>=0.3, J7<=35), 1.03, IF(OR(J7>35, K7<3), 0.95, 1) ) -> 0.95 | R7: =P7*Q7 -> 15.01 | S7: =MAX(R7,C7) -> 19.16 | T7: =_xlfn.TEXTJOIN(", ", TRUE, IF(H7 < 15, "Low inventory", ""), IF(I7 > 8, "Overstock", ""), IF(G7<>"", "Competitor benchmark", ""), IF(K7 > 3, "Strong ads", ""), IF(J7 > 0.4, "High ad cost", "") ) -> Low inventory, Competitor benchmark, High ad cost | U7: =IF(Table3[[#This Row],[Final_Recommended_Price]]>Table3[[#This Row],[Min_Price]],"Yes","No") -> No | V7: =IF( S7=C7, "Minimum margin constraint", IF( G7<>"", "Competitor benchmark", IF( O7>1, "Low inventory", IF( O7<1, "Overstock", IF( Q7>1, "Strong demand / ads", IF(Q7<1, "High ad cost", "Neutral") ) ) ) ) ) -> Minimum margin constraint
A8: MN-07 | B8: =IFERROR(INDEX(Pricing_Data[Total_Cost],MATCH(Pricing_model!A8,Pricing_Data[SKU],0)),"") -> 71.46 | C8: =INDEX(Pricing_Data[Min_Price],MATCH(A8,Pricing_Data[SKU],0)) -> 89.325 | D8: =INDEX(Pricing_Data[Target_Price],MATCH(Pricing_model!A8,Pricing_Data[SKU],0)) -> 109.93846 | E8: =INDEX(Competitor_Data[Lowest_Competitor_Price],MATCH(Pricing_model!A8,Competitor_Data[SKU],0)) -> 28.9 | F8: =INDEX(Competitor_Data[Highest_Competitor_Price],MATCH(Pricing_model!A8,Competitor_Data[SKU],0)) -> 41.95 | G8: =INDEX(Competitor_Data[Avg_Competitor_Price],MATCH(Pricing_model!A8,Competitor_Data[SKU],0)) -> 33.5 | H8: =INDEX(Inventory_Health__2[days-of-supply],MATCH(Pricing_model!A8,Inventory_Health__2[SKU],0)) -> 59 | I8: =INDEX(Inventory_Health__2[weeks-of-cover-t30],MATCH(Pricing_model!A8,Inventory_Health__2[SKU],0)) -> 5 | J8: =INDEX(Ads_Performance!AF18:AF67,MATCH(Pricing_model!A8,Ads_Performance!AE18:AE67,0)) -> 10.698216 | K8: =INDEX(Ads_Performance!AG18:AG67,MATCH(Pricing_model!A8,Ads_Performance!AE18:AE67,0)) -> 8.6299209 | L8: =INDEX(Historical_Sales!O14:O63,MATCH(Pricing_model!A8,Historical_Sales!L14:L63,0)) -> 0.13002755 | M8: =D8 -> 109.93846 | N8: =IF(AND(G8<>"", M8> G8),G8,M8) -> 33.5 | O8: =IF( H8=0, 1, IF( H8 < 45, 1.05, IF( H8 > 90, 0.95, IF( I8 > 10, 0.95, 1 ) ) ) ) -> 1 | P8: =N8*O8 -> 33.5 | Q8: =IF( AND(K8>=6, L8>=0.3, J8<=35), 1.03, IF(OR(J8>35, K8<3), 0.95, 1) ) -> 1 | R8: =P8*Q8 -> 33.5 | S8: =MAX(R8,C8) -> 89.325 | T8: =_xlfn.TEXTJOIN(", ", TRUE, IF(H8 < 15, "Low inventory", ""), IF(I8 > 8, "Overstock", ""), IF(G8<>"", "Competitor benchmark", ""), IF(K8 > 3, "Strong ads", ""), IF(J8 > 0.4, "High ad cost", "") ) -> Competitor benchmark, Strong ads, High ad cost | U8: =IF(Table3[[#This Row],[Final_Recommended_Price]]>Table3[[#This Row],[Min_Price]],"Yes","No") -> No | V8: =IF( S8=C8, "Minimum margin constraint", IF( G8<>"", "Competitor benchmark", IF( O8>1, "Low inventory", IF( O8<1, "Overstock", IF( Q8>1, "Strong demand / ads", IF(Q8<1, "High ad cost", "Neutral") ) ) ) ) ) -> Minimum margin constraint
A9: MN-08 | B9: =IFERROR(INDEX(Pricing_Data[Total_Cost],MATCH(Pricing_model!A9,Pricing_Data[SKU],0)),"") -> 26.11 | C9: =INDEX(Pricing_Data[Min_Price],MATCH(A9,Pricing_Data[SKU],0)) -> 34.813333 | D9: =INDEX(Pricing_Data[Target_Price],MATCH(Pricing_model!A9,Pricing_Data[SKU],0)) -> 47.472727 | E9: =INDEX(Competitor_Data[Lowest_Competitor_Price],MATCH(Pricing_model!A9,Competitor_Data[SKU],0)) -> 25.95 | F9: =INDEX(Competitor_Data[Highest_Competitor_Price],MATCH(Pricing_model!A9,Competitor_Data[SKU],0)) -> 39.9 | G9: =INDEX(Competitor_Data[Avg_Competitor_Price],MATCH(Pricing_model!A9,Competitor_Data[SKU],0)) -> 31.2 | H9: =INDEX(Inventory_Health__2[days-of-supply],MATCH(Pricing_model!A9,Inventory_Health__2[SKU],0)) -> 103 | I9: =INDEX(Inventory_Health__2[weeks-of-cover-t30],MATCH(Pricing_model!A9,Inventory_Health__2[SKU],0)) -> 98 | J9: =INDEX(Ads_Performance!AF19:AF68,MATCH(Pricing_model!A9,Ads_Performance!AE19:AE68,0)) -> 4.6143725 | K9: =INDEX(Ads_Performance!AG19:AG68,MATCH(Pricing_model!A9,Ads_Performance!AE19:AE68,0)) -> 9.9317801 | L9: =INDEX(Historical_Sales!O15:O64,MATCH(Pricing_model!A9,Historical_Sales!L15:L64,0)) -> 0.25595238 | M9: =D9 -> 47.472727 | N9: =IF(AND(G9<>"", M9> G9),G9,M9) -> 31.2 | O9: =IF( H9=0, 1, IF( H9 < 45, 1.05, IF( H9 > 90, 0.95, IF( I9 > 10, 0.95, 1 ) ) ) ) -> 0.95 | P9: =N9*O9 -> 29.64 | Q9: =IF( AND(K9>=6, L9>=0.3, J9<=35), 1.03, IF(OR(J9>35, K9<3), 0.95, 1) ) -> 1 | R9: =P9*Q9 -> 29.64 | S9: =MAX(R9,C9) -> 34.813333 | T9: =_xlfn.TEXTJOIN(", ", TRUE, IF(H9 < 15, "Low inventory", ""), IF(I9 > 8, "Overstock", ""), IF(G9<>"", "Competitor benchmark", ""), IF(K9 > 3, "Strong ads", ""), IF(J9 > 0.4, "High ad cost", "") ) -> Overstock, Competitor benchmark, Strong ads, High ad cost | U9: =IF(Table3[[#This Row],[Final_Recommended_Price]]>Table3[[#This Row],[Min_Price]],"Yes","No") -> No | V9: =IF( S9=C9, "Minimum margin constraint", IF( G9<>"", "Competitor benchmark", IF( O9>1, "Low inventory", IF( O9<1, "Overstock", IF( Q9>1, "Strong demand / ads", IF(Q9<1, "High ad cost", "Neutral") ) ) ) ) ) -> Minimum margin constraint
A10: MN-09 | B10: =IFERROR(INDEX(Pricing_Data[Total_Cost],MATCH(Pricing_model!A10,Pricing_Data[SKU],0)),"") -> 14.92 | C10: =INDEX(Pricing_Data[Min_Price],MATCH(A10,Pricing_Data[SKU],0)) -> 19.893333 | D10: =INDEX(Pricing_Data[Target_Price],MATCH(Pricing_model!A10,Pricing_Data[SKU],0)) -> 27.127273 | E10: =INDEX(Competitor_Data[Lowest_Competitor_Price],MATCH(Pricing_model!A10,Competitor_Data[SKU],0)) -> 11.99 | F10: =INDEX(Competitor_Data[Highest_Competitor_Price],MATCH(Pricing_model!A10,Competitor_Data[SKU],0)) -> 22.9 | G10: =INDEX(Competitor_Data[Avg_Competitor_Price],MATCH(Pricing_model!A10,Competitor_Data[SKU],0)) -> 15.6 | H10: =INDEX(Inventory_Health__2[days-of-supply],MATCH(Pricing_model!A10,Inventory_Health__2[SKU],0)) -> 57 | I10: =INDEX(Inventory_Health__2[weeks-of-cover-t30],MATCH(Pricing_model!A10,Inventory_Health__2[SKU],0)) -> 43 | J10: =INDEX(Ads_Performance!AF20:AF69,MATCH(Pricing_model!A10,Ads_Performance!AE20:AE69,0)) -> 13.280875 | K10: =INDEX(Ads_Performance!AG20:AG69,MATCH(Pricing_model!A10,Ads_Performance!AE20:AE69,0)) -> 3.982438 | L10: =INDEX(Historical_Sales!O16:O65,MATCH(Pricing_model!A10,Historical_Sales!L16:L65,0)) -> 0.15728155 | M10: =D10 -> 27.127273 | N10: =IF(AND(G10<>"", M10> G10),G10,M10) -> 15.6 | O10: =IF( H10=0, 1, IF( H10 < 45, 1.05, IF( H10 > 90, 0.95, IF( I10 > 10, 0.95, 1 ) ) ) ) -> 0.95 | P10: =N10*O10 -> 14.82 | Q10: =IF( AND(K10>=6, L10>=0.3, J10<=35), 1.03, IF(OR(J10>35, K10<3), 0.95, 1) ) -> 1 | R10: =P10*Q10 -> 14.82 | S10: =MAX(R10,C10) -> 19.893333 | T10: =_xlfn.TEXTJOIN(", ", TRUE, IF(H10 < 15, "Low inventory", ""), IF(I10 > 8, "Overstock", ""), IF(G10<>"", "Competitor benchmark", ""), IF(K10 > 3, "Strong ads", ""), IF(J10 > 0.4, "High ad cost", "") ) -> Overstock, Competitor benchmark, Strong ads, High ad cost | U10: =IF(Table3[[#This Row],[Final_Recommended_Price]]>Table3[[#This Row],[Min_Price]],"Yes","No") -> No | V10: =IF( S10=C10, "Minimum margin constraint", IF( G10<>"", "Competitor benchmark", IF( O10>1, "Low inventory", IF( O10<1, "Overstock", IF( Q10>1, "Strong demand / ads", IF(Q10<1, "High ad cost", "Neutral") ) ) ) ) ) -> Minimum margin constraint
A11: MN-10 | B11: =IFERROR(INDEX(Pricing_Data[Total_Cost],MATCH(Pricing_model!A11,Pricing_Data[SKU],0)),"") -> 17.4 | C11: =INDEX(Pricing_Data[Min_Price],MATCH(A11,Pricing_Data[SKU],0)) -> 21.75 | D11: =INDEX(Pricing_Data[Target_Price],MATCH(Pricing_model!A11,Pricing_Data[SKU],0)) -> 26.769231 | E11: =INDEX(Competitor_Data[Lowest_Competitor_Price],MATCH(Pricing_model!A11,Competitor_Data[SKU],0)) -> 16.95 | F11: =INDEX(Competitor_Data[Highest_Competitor_Price],MATCH(Pricing_model!A11,Competitor_Data[SKU],0)) -> 26.9 | G11: =INDEX(Competitor_Data[Avg_Competitor_Price],MATCH(Pricing_model!A11,Competitor_Data[SKU],0)) -> 20.5 | H11: =INDEX(Inventory_Health__2[days-of-supply],MATCH(Pricing_model!A11,Inventory_Health__2[SKU],0)) -> 150 | I11: =INDEX(Inventory_Health__2[weeks-of-cover-t30],MATCH(Pricing_model!A11,Inventory_Health__2[SKU],0)) -> 10 | J11: =INDEX(Ads_Performance!AF21:AF70,MATCH(Pricing_model!A11,Ads_Performance!AE21:AE70,0)) -> 18.167006 | K11: =INDEX(Ads_Performance!AG21:AG70,MATCH(Pricing_model!A11,Ads_Performance!AE21:AE70,0)) -> 5.7078558 | L11: =INDEX(Historical_Sales!O17:O66,MATCH(Pricing_model!A11,Historical_Sales!L17:L66,0)) -> 0.17801858 | M11: =D11 -> 26.769231 | N11: =IF(AND(G11<>"", M11> G11),G11,M11) -> 20.5 | O11: =IF( H11=0, 1, IF( H11 < 45, 1.05, IF( H11 > 90, 0.95, IF( I11 > 10, 0.95, 1 ) ) ) ) -> 0.95 | P11: =N11*O11 -> 19.475 | Q11: =IF( AND(K11>=6, L11>=0.3, J11<=35), 1.03, IF(OR(J11>35, K11<3), 0.95, 1) ) -> 1 | R11: =P11*Q11 -> 19.475 | S11: =MAX(R11,C11) -> 21.75 | T11: =_xlfn.TEXTJOIN(", ", TRUE, IF(H11 < 15, "Low inventory", ""), IF(I11 > 8, "Overstock", ""), IF(G11<>"", "Competitor benchmark", ""), IF(K11 > 3, "Strong ads", ""), IF(J11 > 0.4, "High ad cost", "") ) -> Overstock, Competitor benchmark, Strong ads, High ad cost | U11: =IF(Table3[[#This Row],[Final_Recommended_Price]]>Table3[[#This Row],[Min_Price]],"Yes","No") -> No | V11: =IF( S11=C11, "Minimum margin constraint", IF( G11<>"", "Competitor benchmark", IF( O11>1, "Low inventory", IF( O11<1, "Overstock", IF( Q11>1, "Strong demand / ads", IF(Q11<1, "High ad cost", "Neutral") ) ) ) ) ) -> Minimum margin constraint
A12: MN-11 | B12: =IFERROR(INDEX(Pricing_Data[Total_Cost],MATCH(Pricing_model!A12,Pricing_Data[SKU],0)),"") -> 15.26 | C12: =INDEX(Pricing_Data[Min_Price],MATCH(A12,Pricing_Data[SKU],0)) -> 19.075 | D12: =INDEX(Pricing_Data[Target_Price],MATCH(Pricing_model!A12,Pricing_Data[SKU],0)) -> 23.476923 | E12: =INDEX(Competitor_Data[Lowest_Competitor_Price],MATCH(Pricing_model!A12,Competitor_Data[SKU],0)) -> 14.99 | F12: =INDEX(Competitor_Data[Highest_Competitor_Price],MATCH(Pricing_model!A12,Competitor_Data[SKU],0)) -> 23.5 | G12: =INDEX(Competitor_Data[Avg_Competitor_Price],MATCH(Pricing_model!A12,Competitor_Data[SKU],0)) -> 17.8 | H12: =INDEX(Inventory_Health__2[days-of-supply],MATCH(Pricing_model!A12,Inventory_Health__2[SKU],0)) -> 159 | I12: =INDEX(Inventory_Health__2[weeks-of-cover-t30],MATCH(Pricing_model!A12,Inventory_Health__2[SKU],0)) -> 8 | J12: =INDEX(Ads_Performance!AF22:AF71,MATCH(Pricing_model!A12,Ads_Performance!AE22:AE71,0)) -> 19.915199 | K12: =INDEX(Ads_Performance!AG22:AG71,MATCH(Pricing_model!A12,Ads_Performance!AE22:AE71,0)) -> 5.6579079 | L12: =INDEX(Historical_Sales!O18:O67,MATCH(Pricing_model!A12,Historical_Sales!L18:L67,0)) -> 0.13393871 | M12: =D12 -> 23.476923 | N12: =IF(AND(G12<>"", M12> G12),G12,M12) -> 17.8 | O12: =IF( H12=0, 1, IF( H12 < 45, 1.05, IF( H12 > 90, 0.95, IF( I12 > 10, 0.95, 1 ) ) ) ) -> 0.95 | P12: =N12*O12 -> 16.91 | Q12: =IF( AND(K12>=6, L12>=0.3, J12<=35), 1.03, IF(OR(J12>35, K12<3), 0.95, 1) ) -> 1 | R12: =P12*Q12 -> 16.91 | S12: =MAX(R12,C12) -> 19.075 | T12: =_xlfn.TEXTJOIN(", ", TRUE, IF(H12 < 15, "Low inventory", ""), IF(I12 > 8, "Overstock", ""), IF(G12<>"", "Competitor benchmark", ""), IF(K12 > 3, "Strong ads", ""), IF(J12 > 0.4, "High ad cost", "") ) -> Competitor benchmark, Strong ads, High ad cost | U12: =IF(Table3[[#This Row],[Final_Recommended_Price]]>Table3[[#This Row],[Min_Price]],"Yes","No") -> No | V12: =IF( S12=C12, "Minimum margin constraint", IF( G12<>"", "Competitor benchmark", IF( O12>1, "Low inventory", IF( O12<1, "Overstock", IF( Q12>1, "Strong demand / ads", IF(Q12<1, "High ad cost", "Neutral") ) ) ) ) ) -> Minimum margin constraint
A13: MN-12 | B13: =IFERROR(INDEX(Pricing_Data[Total_Cost],MATCH(Pricing_model!A13,Pricing_Data[SKU],0)),"") -> 17.87 | C13: =INDEX(Pricing_Data[Min_Price],MATCH(A13,Pricing_Data[SKU],0)) -> 22.3375 | D13: =INDEX(Pricing_Data[Target_Price],MATCH(Pricing_model!A13,Pricing_Data[SKU],0)) -> 27.492308 | E13: =INDEX(Competitor_Data[Lowest_Competitor_Price],MATCH(Pricing_model!A13,Competitor_Data[SKU],0)) -> 17.95 | F13: =INDEX(Competitor_Data[Highest_Competitor_Price],MATCH(Pricing_model!A13,Competitor_Data[SKU],0)) -> 27.9 | G13: =INDEX(Competitor_Data[Avg_Competitor_Price],MATCH(Pricing_model!A13,Competitor_Data[SKU],0)) -> 21.4 | H13: =INDEX(Inventory_Health__2[days-of-supply],MATCH(Pricing_model!A13,Inventory_Health__2[SKU],0)) -> 74 | I13: =INDEX(Inventory_Health__2[weeks-of-cover-t30],MATCH(Pricing_model!A13,Inventory_Health__2[SKU],0)) -> 3 | J13: =INDEX(Ads_Performance!AF23:AF72,MATCH(Pricing_model!A13,Ads_Performance!AE23:AE72,0)) -> 37.854601 | K13: =INDEX(Ads_Performance!AG23:AG72,MATCH(Pricing_model!A13,Ads_Performance!AE23:AE72,0)) -> 3.7928957 | L13: =INDEX(Historical_Sales!O19:O68,MATCH(Pricing_model!A13,Historical_Sales!L19:L68,0)) -> 0.17254902 | M13: =D13 -> 27.492308 | N13: =IF(AND(G13<>"", M13> G13),G13,M13) -> 21.4 | O13: =IF( H13=0, 1, IF( H13 < 45, 1.05, IF( H13 > 90, 0.95, IF( I13 > 10, 0.95, 1 ) ) ) ) -> 1 | P13: =N13*O13 -> 21.4 | Q13: =IF( AND(K13>=6, L13>=0.3, J13<=35), 1.03, IF(OR(J13>35, K13<3), 0.95, 1) ) -> 0.95 | R13: =P13*Q13 -> 20.33 | S13: =MAX(R13,C13) -> 22.3375 | T13: =_xlfn.TEXTJOIN(", ", TRUE, IF(H13 < 15, "Low inventory", ""), IF(I13 > 8, "Overstock", ""), IF(G13<>"", "Competitor benchmark", ""), IF(K13 > 3, "Strong ads", ""), IF(J13 > 0.4, "High ad cost", "") ) -> Competitor benchmark, Strong ads, High ad cost | U13: =IF(Table3[[#This Row],[Final_Recommended_Price]]>Table3[[#This Row],[Min_Price]],"Yes","No") -> No | V13: =IF( S13=C13, "Minimum margin constraint", IF( G13<>"", "Competitor benchmark", IF( O13>1, "Low inventory", IF( O13<1, "Overstock", IF( Q13>1, "Strong demand / ads", IF(Q13<1, "High ad cost", "Neutral") ) ) ) ) ) -> Minimum margin constraint
... A51: MN-50 | B51: =IFERROR(INDEX(Pricing_Data[Total_Cost],MATCH(Pricing_model!A51,Pricing_Data[SKU],0)),"") -> 27.6 | C51: =INDEX(Pricing_Data[Min_Price],MATCH(A51,Pricing_Data[SKU],0)) -> 34.5 | D51: =INDEX(Pricing_Data[Target_Price],MATCH(Pricing_model!A51,Pricing_Data[SKU],0)) -> 42.461538 | E51: =INDEX(Competitor_Data[Lowest_Competitor_Price],MATCH(Pricing_model!A51,Competitor_Data[SKU],0)) -> 24.95 | F51: =INDEX(Competitor_Data[Highest_Competitor_Price],MATCH(Pricing_model!A51,Competitor_Data[SKU],0)) -> 38.9 | G51: =INDEX(Competitor_Data[Avg_Competitor_Price],MATCH(Pricing_model!A51,Competitor_Data[SKU],0)) -> 30.2 | H51: =INDEX(Inventory_Health__2[days-of-supply],MATCH(Pricing_model!A51,Inventory_Health__2[SKU],0)) -> 49 | I51: =INDEX(Inventory_Health__2[weeks-of-cover-t30],MATCH(Pricing_model!A51,Inventory_Health__2[SKU],0)) -> 3 | J51: =INDEX(Ads_Performance!AF61:AF110,MATCH(Pricing_model!A51,Ads_Performance!AE61:AE110,0)) -> 12.42124 | K51: =INDEX(Ads_Performance!AG61:AG110,MATCH(Pricing_model!A51,Ads_Performance!AE61:AE110,0)) -> 6.89907 | L51: =INDEX(Historical_Sales!O57:O106,MATCH(Pricing_model!A51,Historical_Sales!L57:L106,0)) -> 0.20022185 | M51: =D51 -> 42.461538 | N51: =IF(AND(G51<>"", M51> G51),G51,M51) -> 30.2 | O51: =IF( H51=0, 1, IF( H51 < 45, 1.05, IF( H51 > 90, 0.95, IF( I51 > 10, 0.95, 1 ) ) ) ) -> 1 | P51: =N51*O51 -> 30.2 | Q51: =IF( AND(K51>=6, L51>=0.3, J51<=35), 1.03, IF(OR(J51>35, K51<3), 0.95, 1) ) -> 1 | R51: =P51*Q51 -> 30.2 | S51: =MAX(R51,C51) -> 34.5 | T51: =_xlfn.TEXTJOIN(", ", TRUE, IF(H51 < 15, "Low inventory", ""), IF(I51 > 8, "Overstock", ""), IF(G51<>"", "Competitor benchmark", ""), IF(K51 > 3, "Strong ads", ""), IF(J51 > 0.4, "High ad cost", "") ) -> Competitor benchmark, Strong ads, High ad cost | U51: =IF(Table3[[#This Row],[Final_Recommended_Price]]>Table3[[#This Row],[Min_Price]],"Yes","No") -> No | V51: =IF( S51=C51, "Minimum margin constraint", IF( G51<>"", "Competitor benchmark", IF( O51>1, "Low inventory", IF( O51<1, "Overstock", IF( Q51>1, "Strong demand / ads", IF(Q51<1, "High ad cost", "Neutral") ) ) ) ) ) -> Minimum margin constraint

Sheet Pricing_Action_View
A1: SKU | B1: Current_Price | C1: Final_Recommended_Price | D1: Price_Change_on_CurrentPrice | E1: Min_Price | F1: Price_Increase_Potential | G1: Primary_Pricing_Driver | H1: Action_Recommended | I1: Return_Risk
A2: =Pricing_Data[[#This Row],[SKU]] -> MN-01 | B2: =Pricing_Data[[#This Row],[Current_Price]] -> 38.9 | C2: =Table3[[#This Row],[Final_Recommended_Price]] -> 40.375 | D2: =C2-B2 -> 1.475 | E2: =Pricing_Data[[#This Row],[Min_Price]] -> 40.375 | F2: =Table3[[#This Row],[Price_Increase_Potential]] -> No | G2: =Table3[[#This Row],[Primary_Pricing_Driver]] -> Minimum margin constraint | H2: =IF( G2="Minimum margin constraint", "Hold price (margin floor)", IF( C2 > B2, "Increase price", IF( C2 < B2, "Decrease price", "Hold price" ) ) ) -> Hold price (margin floor) | I2: =INDEX(Returns_Data[Return_Risk],MATCH(Table8[[#This Row],[SKU]],Returns_Data[SKU],0)) -> Low Risk
A3: =Pricing_Data[[#This Row],[SKU]] -> MN-02 | B3: =Pricing_Data[[#This Row],[Current_Price]] -> 33.9 | C3: =Table3[[#This Row],[Final_Recommended_Price]] -> 33.25 | D3: =C3-B3 -> -0.65 | E3: =Pricing_Data[[#This Row],[Min_Price]] -> 33.25 | F3: =Table3[[#This Row],[Price_Increase_Potential]] -> No | G3: =Table3[[#This Row],[Primary_Pricing_Driver]] -> Minimum margin constraint | H3: =IF( G3="Minimum margin constraint", "Hold price (margin floor)", IF( C3 > B3, "Increase price", IF( C3 < B3, "Decrease price", "Hold price" ) ) ) -> Hold price (margin floor) | I3: =INDEX(Returns_Data[Return_Risk],MATCH(Table8[[#This Row],[SKU]],Returns_Data[SKU],0)) -> Low Risk
A4: =Pricing_Data[[#This Row],[SKU]] -> MN-03 | B4: =Pricing_Data[[#This Row],[Current_Price]] -> 34.9 | C4: =Table3[[#This Row],[Final_Recommended_Price]] -> 37.5375 | D4: =C4-B4 -> 2.6375 | E4: =Pricing_Data[[#This Row],[Min_Price]] -> 37.5375 | F4: =Table3[[#This Row],[Price_Increase_Potential]] -> No | G4: =Table3[[#This Row],[Primary_Pricing_Driver]] -> Minimum margin constraint | H4: =IF( G4="Minimum margin constraint", "Hold price (margin floor)", IF( C4 > B4, "Increase price", IF( C4 < B4, "Decrease price", "Hold price" ) ) ) -> Hold price (margin floor) | I4: =INDEX(Returns_Data[Return_Risk],MATCH(Table8[[#This Row],[SKU]],Returns_Data[SKU],0)) -> Low Risk
A5: =Pricing_Data[[#This Row],[SKU]] -> MN-04 | B5: =Pricing_Data[[#This Row],[Current_Price]] -> 29.9 | C5: =Table3[[#This Row],[Final_Recommended_Price]] -> 32.425 | D5: =C5-B5 -> 2.525 | E5: =Pricing_Data[[#This Row],[Min_Price]] -> 32.425 | F5: =Table3[[#This Row],[Price_Increase_Potential]] -> No | G5: =Table3[[#This Row],[Primary_Pricing_Driver]] -> Minimum margin constraint | H5: =IF( G5="Minimum margin constraint", "Hold price (margin floor)", IF( C5 > B5, "Increase price", IF( C5 < B5, "Decrease price", "Hold price" ) ) ) -> Hold price (margin floor) | I5: =INDEX(Returns_Data[Return_Risk],MATCH(Table8[[#This Row],[SKU]],Returns_Data[SKU],0)) -> Low Risk
A6: =Pricing_Data[[#This Row],[SKU]] -> MN-05 | B6: =Pricing_Data[[#This Row],[Current_Price]] -> 21.9 | C6: =Table3[[#This Row],[Final_Recommended_Price]] -> 34.36 | D6: =C6-B6 -> 12.46 | E6: =Pricing_Data[[#This Row],[Min_Price]] -> 34.36 | F6: =Table3[[#This Row],[Price_Increase_Potential]] -> No | G6: =Table3[[#This Row],[Primary_Pricing_Driver]] -> Minimum margin constraint | H6: =IF( G6="Minimum margin constraint", "Hold price (margin floor)", IF( C6 > B6, "Increase price", IF( C6 < B6, "Decrease price", "Hold price" ) ) ) -> Hold price (margin floor) | I6: =INDEX(Returns_Data[Return_Risk],MATCH(Table8[[#This Row],[SKU]],Returns_Data[SKU],0)) -> Low Risk
A7: =Pricing_Data[[#This Row],[SKU]] -> MN-06 | B7: =Pricing_Data[[#This Row],[Current_Price]] -> 14.95 | C7: =Table3[[#This Row],[Final_Recommended_Price]] -> 19.16 | D7: =C7-B7 -> 4.21 | E7: =Pricing_Data[[#This Row],[Min_Price]] -> 19.16 | F7: =Table3[[#This Row],[Price_Increase_Potential]] -> No | G7: =Table3[[#This Row],[Primary_Pricing_Driver]] -> Minimum margin constraint | H7: =IF( G7="Minimum margin constraint", "Hold price (margin floor)", IF( C7 > B7, "Increase price", IF( C7 < B7, "Decrease price", "Hold price" ) ) ) -> Hold price (margin floor) | I7: =INDEX(Returns_Data[Return_Risk],MATCH(Table8[[#This Row],[SKU]],Returns_Data[SKU],0)) -> Low Risk
A8: =Pricing_Data[[#This Row],[SKU]] -> MN-07 | B8: =Pricing_Data[[#This Row],[Current_Price]] -> 17.89 | C8: =Table3[[#This Row],[Final_Recommended_Price]] -> 89.325 | D8: =C8-B8 -> 71.435 | E8: =Pricing_Data[[#This Row],[Min_Price]] -> 89.325 | F8: =Table3[[#This Row],[Price_Increase_Potential]] -> No | G8: =Table3[[#This Row],[Primary_Pricing_Driver]] -> Minimum margin constraint | H8: =IF( G8="Minimum margin constraint", "Hold price (margin floor)", IF( C8 > B8, "Increase price", IF( C8 < B8, "Decrease price", "Hold price" ) ) ) -> Hold price (margin floor) | I8: =INDEX(Returns_Data[Return_Risk],MATCH(Table8[[#This Row],[SKU]],Returns_Data[SKU],0)) -> Low Risk
A9: =Pricing_Data[[#This Row],[SKU]] -> MN-08 | B9: =Pricing_Data[[#This Row],[Current_Price]] -> 29.9 | C9: =Table3[[#This Row],[Final_Recommended_Price]] -> 34.813333 | D9: =C9-B9 -> 4.9133333 | E9: =Pricing_Data[[#This Row],[Min_Price]] -> 34.813333 | F9: =Table3[[#This Row],[Price_Increase_Potential]] -> No | G9: =Table3[[#This Row],[Primary_Pricing_Driver]] -> Minimum margin constraint | H9: =IF( G9="Minimum margin constraint", "Hold price (margin floor)", IF( C9 > B9, "Increase price", IF( C9 < B9, "Decrease price", "Hold price" ) ) ) -> Hold price (margin floor) | I9: =INDEX(Returns_Data[Return_Risk],MATCH(Table8[[#This Row],[SKU]],Returns_Data[SKU],0)) -> Low Risk
A10: =Pricing_Data[[#This Row],[SKU]] -> MN-09 | B10: =Pricing_Data[[#This Row],[Current_Price]] -> 14.9 | C10: =Table3[[#This Row],[Final_Recommended_Price]] -> 19.893333 | D10: =C10-B10 -> 4.9933333 | E10: =Pricing_Data[[#This Row],[Min_Price]] -> 19.893333 | F10: =Table3[[#This Row],[Price_Increase_Potential]] -> No | G10: =Table3[[#This Row],[Primary_Pricing_Driver]] -> Minimum margin constraint | H10: =IF( G10="Minimum margin constraint", "Hold price (margin floor)", IF( C10 > B10, "Increase price", IF( C10 < B10, "Decrease price", "Hold price" ) ) ) -> Hold price (margin floor) | I10: =INDEX(Returns_Data[Return_Risk],MATCH(Table8[[#This Row],[SKU]],Returns_Data[SKU],0)) -> Low Risk
A11: =Pricing_Data[[#This Row],[SKU]] -> MN-10 | B11: =Pricing_Data[[#This Row],[Current_Price]] -> 19.9 | C11: =Table3[[#This Row],[Final_Recommended_Price]] -> 21.75 | D11: =C11-B11 -> 1.85 | E11: =Pricing_Data[[#This Row],[Min_Price]] -> 21.75 | F11: =Table3[[#This Row],[Price_Increase_Potential]] -> No | G11: =Table3[[#This Row],[Primary_Pricing_Driver]] -> Minimum margin constraint | H11: =IF( G11="Minimum margin constraint", "Hold price (margin floor)", IF( C11 > B11, "Increase price", IF( C11 < B11, "Decrease price", "Hold price" ) ) ) -> Hold price (margin floor) | I11: =INDEX(Returns_Data[Return_Risk],MATCH(Table8[[#This Row],[SKU]],Returns_Data[SKU],0)) -> Low Risk
A12: =Pricing_Data[[#This Row],[SKU]] -> MN-11 | B12: =Pricing_Data[[#This Row],[Current_Price]] -> 16.9 | C12: =Table3[[#This Row],[Final_Recommended_Price]] -> 19.075 | D12: =C12-B12 -> 2.175 | E12: =Pricing_Data[[#This Row],[Min_Price]] -> 19.075 | F12: =Table3[[#This Row],[Price_Increase_Potential]] -> No | G12: =Table3[[#This Row],[Primary_Pricing_Driver]] -> Minimum margin constraint | H12: =IF( G12="Minimum margin constraint", "Hold price (margin floor)", IF( C12 > B12, "Increase price", IF( C12 < B12, "Decrease price", "Hold price" ) ) ) -> Hold price (margin floor) | I12: =INDEX(Returns_Data[Return_Risk],MATCH(Table8[[#This Row],[SKU]],Returns_Data[SKU],0)) -> Low Risk
A13: =Pricing_Data[[#This Row],[SKU]] -> MN-12 | B13: =Pricing_Data[[#This Row],[Current_Price]] -> 19.9 | C13: =Table3[[#This Row],[Final_Recommended_Price]] -> 22.3375 | D13: =C13-B13 -> 2.4375 | E13: =Pricing_Data[[#This Row],[Min_Price]] -> 22.3375 | F13: =Table3[[#This Row],[Price_Increase_Potential]] -> No | G13: =Table3[[#This Row],[Primary_Pricing_Driver]] -> Minimum margin constraint | H13: =IF( G13="Minimum margin constraint", "Hold price (margin floor)", IF( C13 > B13, "Increase price", IF( C13 < B13, "Decrease price", "Hold price" ) ) ) -> Hold price (margin floor) | I13: =INDEX(Returns_Data[Return_Risk],MATCH(Table8[[#This Row],[SKU]],Returns_Data[SKU],0)) -> Low Risk
... A51: =Pricing_Data[[#This Row],[SKU]] -> MN-50 | B51: =Pricing_Data[[#This Row],[Current_Price]] -> 29.9 | C51: =Table3[[#This Row],[Final_Recommended_Price]] -> 34.5 | D51: =C51-B51 -> 4.6 | E51: =Pricing_Data[[#This Row],[Min_Price]] -> 34.5 | F51: =Table3[[#This Row],[Price_Increase_Potential]] -> No | G51: =Table3[[#This Row],[Primary_Pricing_Driver]] -> Minimum margin constraint | H51: =IF( G51="Minimum margin constraint", "Hold price (margin floor)", IF( C51 > B51, "Increase price", IF( C51 < B51, "Decrease price", "Hold price" ) ) ) -> Hold price (margin floor) | I51: =INDEX(Returns_Data[Return_Risk],MATCH(Table8[[#This Row],[SKU]],Returns_Data[SKU],0)) -> Low Risk

Sheet Dashboard
A2: Pricing Insights & Recommendations Overview
A5: =COUNTA(Table3[SKU]) -> 50 | D5: =COUNTIF(Table3[Price_Increase_Potential],"Yes") -> 13 | G5: =COUNTIF(Table3[Primary_Pricing_Driver],"*constraint*") / COUNTA(Table3[SKU]) -> 0.74 | J5: =AVERAGE(Pricing_Action_View!D2:D51) -> 4.575151
A7: Total SKU | D7: SKUs with Pricing Headroom | G7: % Margin-Constrained SKUs | J7: Avg Price Change vs Current Price
A39: SKU | B39: Current Price | C39: Recommended Price | D39: Price Change | E39: Primary Driver | F39: Action | G39: Return Risk
A40: MN-13 | B40: $22.90 | C40: 24.2 | D40: $1.30 | E40: Competitor benchmark | F40: Increase price | G40: Low Risk | H40: The majority of SKUs are still limited by margin floors.
A41: MN-24 | B41: $19.90 | C41: 19.76 | D41: -$0.14 | E41: Competitor benchmark | F41: Decrease price | G41: Low Risk
A42: MN-29 | B42: $21.90 | C42: 22.8 | D42: $0.90 | E42: Competitor benchmark | F42: Increase price | G42: High Risk | H42: The upside in pricing is selective rather than widespread.
A43: MN-33 | B43: $25.90 | C43: 33.359323 | D43: $7.46 | E43: Overstock | F43: Increase price | G43: Low Risk
A44: MN-40 | B44: $23.90 | C44: 25.647 | D44: $1.75 | E44: Competitor benchmark | F44: Increase price | G44: Medium Risk | H44: The primary cause of increases is demand signals (ROAS + conversion).
A45: MN-41 | B45: $78.90 | C45: 84.975 | D45: $6.08 | E45: Competitor benchmark | F45: Increase price | G45: Medium Risk
A46: MN-42 | B46: $73.90 | C46: 79.104 | D46: $5.20 | E46: Competitor benchmark | F46: Increase price | G46: Medium Risk | H46: Strong demand signals and advantageous inventory positions are the main driver
A47: MN-43 | B47: $13.90 | C47: 14.06 | D47: $0.16 | E47: Competitor benchmark | F47: Increase price | G47: Low Risk | H47: of the pricing headroom seen in 13 SKUs.
A48: MN-44 | B48: $11.90 | C48: 14.118462 | D48: $2.22 | E48: Overstock | F48: Increase price | G48: Low Risk
A49: MN-45 | B49: $29.90 | C49: 32.342 | D49: $2.44 | E49: Competitor benchmark | F49: Increase price | G49: Low Risk
A50: MN-46 | B50: $26.90 | C50: 27.455 | D50: $0.56 | E50: Competitor benchmark | F50: Increase price | G50: Low Risk
A51: MN-47 | B51: $76.90 | C51: 78.6714 | D51: $1.77 | E51: Competitor benchmark | F51: Increase price | G51: Low Risk
A52: MN-48 | B52: $89.90 | C52: 86.3037 | D52: -$3.60 | E52: Competitor benchmark | F52: Decrease price | G52: Low Risk

Sheet Pricing_Data
A1: SKU | B1: Product_description | C1: Product Role | D1: Country_of_Origin | E1: FBA Fee | F1: Storage Fee | G1: Handling_Cost | H1: Cost | I1: Current_Price | J1: Minimum_Acceptable_Margin_% | K1: Target_Gross_Margin_% | L1: Total_Cost | M1: Min_Price | N1: Target_Price
A2: MN-01 | B2: Rectangle Tray -14 x 10 Inch - Pk of 25 | C2: Core | D2: India | E2: 15.11 | F2: 0.44 | G2: 0.75 | H2: 16 | I2: 38.9 | J2: 0.2 | K2: 0.35 | L2: =Pricing_Data[[#This Row],[FBA Fee]]+Pricing_Data[[#This Row],[Storage Fee]]+Pricing_Data[[#This Row],[Handling_Cost]]+Pricing_Data[[#This Row],[Cost]] -> 32.3 | M2: =Pricing_Data[[#This Row],[Total_Cost]] / (1-Pricing_Data[[#This Row],[Minimum_Acceptable_Margin_%]]) -> 40.375 | N2: =Pricing_Data[[#This Row],[Total_Cost]] / (1-Pricing_Data[[#This Row],[Target_Gross_Margin_%]]) -> 49.692308
A3: MN-02 | B3: Rectangle Tray -12x10 - Pk of 25 | C3: Core | D3: India | E3: 13.55 | F3: 0.3 | G3: 0.75 | H3: 12 | I3: 33.9 | J3: 0.2 | K3: 0.35 | L3: =Pricing_Data[[#This Row],[FBA Fee]]+Pricing_Data[[#This Row],[Storage Fee]]+Pricing_Data[[#This Row],[Handling_Cost]]+Pricing_Data[[#This Row],[Cost]] -> 26.6 | M3: =Pricing_Data[[#This Row],[Total_Cost]] / (1-Pricing_Data[[#This Row],[Minimum_Acceptable_Margin_%]]) -> 33.25 | N3: =Pricing_Data[[#This Row],[Total_Cost]] / (1-Pricing_Data[[#This Row],[Target_Gross_Margin_%]]) -> 40.923077
A4: MN-03 | B4: Oval Tray -15x10 Inch - Pk of 25 | C4: Core | D4: India | E4: 13.94 | F4: 0.34 | G4: 0.75 | H4: 15 | I4: 34.9 | J4: 0.2 | K4: 0.35 | L4: =Pricing_Data[[#This Row],[FBA Fee]]+Pricing_Data[[#This Row],[Storage Fee]]+Pricing_Data[[#This Row],[Handling_Cost]]+Pricing_Data[[#This Row],[Cost]] -> 30.03 | M4: =Pricing_Data[[#This Row],[Total_Cost]] / (1-Pricing_Data[[#This Row],[Minimum_Acceptable_Margin_%]]) -> 37.5375 | N4: =Pricing_Data[[#This Row],[Total_Cost]] / (1-Pricing_Data[[#This Row],[Target_Gross_Margin_%]]) -> 46.2
A5: MN-04 | B5: Oval Tray - 13x9 Inch - pk of 25 | C5: Core | D5: India | E5: 12.89 | F5: 0.3 | G5: 0.75 | H5: 12 | I5: 29.9 | J5: 0.2 | K5: 0.35 | L5: =Pricing_Data[[#This Row],[FBA Fee]]+Pricing_Data[[#This Row],[Storage Fee]]+Pricing_Data[[#This Row],[Handling_Cost]]+Pricing_Data[[#This Row],[Cost]] -> 25.94 | M5: =Pricing_Data[[#This Row],[Total_Cost]] / (1-Pricing_Data[[#This Row],[Minimum_Acceptable_Margin_%]]) -> 32.425 | N5: =Pricing_Data[[#This Row],[Total_Cost]] / (1-Pricing_Data[[#This Row],[Target_Gross_Margin_%]]) -> 39.907692
A6: MN-05 | B6: Christmas Tray - 17x12 Inch - Pk of 5 | C6: Seasonal | D6: India | E6: 11.8 | F6: 0.22 | G6: 0.75 | H6: 13 | I6: 21.9 | J6: 0.25 | K6: 0.45 | L6: =Pricing_Data[[#This Row],[FBA Fee]]+Pricing_Data[[#This Row],[Storage Fee]]+Pricing_Data[[#This Row],[Handling_Cost]]+Pricing_Data[[#This Row],[Cost]] -> 25.77 | M6: =Pricing_Data[[#This Row],[Total_Cost]] / (1-Pricing_Data[[#This Row],[Minimum_Acceptable_Margin_%]]) -> 34.36 | N6: =Pricing_Data[[#This Row],[Total_Cost]] / (1-Pricing_Data[[#This Row],[Target_Gross_Margin_%]]) -> 46.854545
A7: MN-06 | B7: Star Tray - 14 Inch - Pk of 5 | C7: Seasonal | D7: India | E7: 8.5 | F7: 0.12 | G7: 0.75 | H7: 5 | I7: 14.95 | J7: 0.25 | K7: 0.45 | L7: =Pricing_Data[[#This Row],[FBA Fee]]+Pricing_Data[[#This Row],[Storage Fee]]+Pricing_Data[[#This Row],[Handling_Cost]]+Pricing_Data[[#This Row],[Cost]] -> 14.37 | M7: =Pricing_Data[[#This Row],[Total_Cost]] / (1-Pricing_Data[[#This Row],[Minimum_Acceptable_Margin_%]]) -> 19.16 | N7: =Pricing_Data[[#This Row],[Total_Cost]] / (1-Pricing_Data[[#This Row],[Target_Gross_Margin_%]]) -> 26.127273
A8: MN-07 | B8: 15 Round plate - pk of 10 | C8: Core | D8: India | E8: 17.85 | F8: 17.86 | G8: 17.87 | H8: 17.88 | I8: 17.89 | J8: 0.2 | K8: 0.35 | L8: =Pricing_Data[[#This Row],[FBA Fee]]+Pricing_Data[[#This Row],[Storage Fee]]+Pricing_Data[[#This Row],[Handling_Cost]]+Pricing_Data[[#This Row],[Cost]] -> 71.46 | M8: =Pricing_Data[[#This Row],[Total_Cost]] / (1-Pricing_Data[[#This Row],[Minimum_Acceptable_Margin_%]]) -> 89.325 | N8: =Pricing_Data[[#This Row],[Total_Cost]] / (1-Pricing_Data[[#This Row],[Target_Gross_Margin_%]]) -> 109.93846
A9: MN-08 | B9: 10 Inch Heart Plates - pk of 25 | C9: Seasonal | D9: India | E9: 12.11 | F9: 0.25 | G9: 0.75 | H9: 13 | I9: 29.9 | J9: 0.25 | K9: 0.45 | L9: =Pricing_Data[[#This Row],[FBA Fee]]+Pricing_Data[[#This Row],[Storage Fee]]+Pricing_Data[[#This Row],[Handling_Cost]]+Pricing_Data[[#This Row],[Cost]] -> 26.11 | M9: =Pricing_Data[[#This Row],[Total_Cost]] / (1-Pricing_Data[[#This Row],[Minimum_Acceptable_Margin_%]]) -> 34.813333 | N9: =Pricing_Data[[#This Row],[Total_Cost]] / (1-Pricing_Data[[#This Row],[Target_Gross_Margin_%]]) -> 47.472727
A10: MN-09 | B10: 6 Inch Heart Plates - pk of 25 | C10: Seasonal | D10: India | E10: 8.08 | F10: 0.09 | G10: 0.75 | H10: 6 | I10: 14.9 | J10: 0.25 | K10: 0.45 | L10: =Pricing_Data[[#This Row],[FBA Fee]]+Pricing_Data[[#This Row],[Storage Fee]]+Pricing_Data[[#This Row],[Handling_Cost]]+Pricing_Data[[#This Row],[Cost]] -> 14.92 | M10: =Pricing_Data[[#This Row],[Total_Cost]] / (1-Pricing_Data[[#This Row],[Minimum_Acceptable_Margin_%]]) -> 19.893333 | N10: =Pricing_Data[[#This Row],[Total_Cost]] / (1-Pricing_Data[[#This Row],[Target_Gross_Margin_%]]) -> 27.127273
A11: MN-10 | B11: 9x6 Rectangle - pk of 25 | C11: Core | D11: India | E11: 9.52 | F11: 0.13 | G11: 0.75 | H11: 7 | I11: 19.9 | J11: 0.2 | K11: 0.35 | L11: =Pricing_Data[[#This Row],[FBA Fee]]+Pricing_Data[[#This Row],[Storage Fee]]+Pricing_Data[[#This Row],[Handling_Cost]]+Pricing_Data[[#This Row],[Cost]] -> 17.4 | M11: =Pricing_Data[[#This Row],[Total_Cost]] / (1-Pricing_Data[[#This Row],[Minimum_Acceptable_Margin_%]]) -> 21.75 | N11: =Pricing_Data[[#This Row],[Total_Cost]] / (1-Pricing_Data[[#This Row],[Target_Gross_Margin_%]]) -> 26.769231
A12: MN-11 | B12: Oval Tray - 13x9 Inch - pk of 10 | C12: Core | D12: India | E12: 9.36 | F12: 0.15 | G12: 0.75 | H12: 5 | I12: 16.9 | J12: 0.2 | K12: 0.35 | L12: =Pricing_Data[[#This Row],[FBA Fee]]+Pricing_Data[[#This Row],[Storage Fee]]+Pricing_Data[[#This Row],[Handling_Cost]]+Pricing_Data[[#This Row],[Cost]] -> 15.26 | M12: =Pricing_Data[[#This Row],[Total_Cost]] / (1-Pricing_Data[[#This Row],[Minimum_Acceptable_Margin_%]]) -> 19.075 | N12: =Pricing_Data[[#This Row],[Total_Cost]] / (1-Pricing_Data[[#This Row],[Target_Gross_Margin_%]]) -> 23.476923
A13: MN-12 | B13: 13 inch Round DEEP plate - pk of 10 | C13: Core | D13: India | E13: 10.9 | F13: 0.22 | G13: 0.75 | H13: 6 | I13: 19.9 | J13: 0.2 | K13: 0.35 | L13: =Pricing_Data[[#This Row],[FBA Fee]]+Pricing_Data[[#This Row],[Storage Fee]]+Pricing_Data[[#This Row],[Handling_Cost]]+Pricing_Data[[#This Row],[Cost]] -> 17.87 | M13: =Pricing_Data[[#This Row],[Total_Cost]] / (1-Pricing_Data[[#This Row],[Minimum_Acceptable_Margin_%]]) -> 22.3375 | N13: =Pricing_Data[[#This Row],[Total_Cost]] / (1-Pricing_Data[[#This Row],[Target_Gross_Margin_%]]) -> 27.492308
... A51: MN-50 | B51: 9x6 Rectangle - pk of 50 | C51: Core | D51: India | E51: 12.58 | F51: 0.27 | G51: 0.75 | H51: 14 | I51: 29.9 | J51: 0.2 | K51: 0.35 | L51: =Pricing_Data[[#This Row],[FBA Fee]]+Pricing_Data[[#This Row],[Storage Fee]]+Pricing_Data[[#This Row],[Handling_Cost]]+Pricing_Data[[#This Row],[Cost]] -> 27.6 | M51: =Pricing_Data[[#This Row],[Total_Cost]] / (1-Pricing_Data[[#This Row],[Minimum_Acceptable_Margin_%]]) -> 34.5 | N51: =Pricing_Data[[#This Row],[Total_Cost]] / (1-Pricing_Data[[#This Row],[Target_Gross_Margin_%]]) -> 42.461538

Sheet Returns_Data
A1: SKU | B1: Return Quantity (Last 7 days) | C1: Return Quantity (Last 30 days) | D1: Return Quantity (Last 60 days) | E1: Return Quantity (Last 90 days) | F1: Return_Risk
A2: MN-01 | B2: 0 | C2: 9 | D2: 18 | E2: 26 | F2: =IF( E2>100, "High Risk", IF( E2>=50, "Medium Risk", "Low Risk" ) ) -> Low Risk
A3: MN-02 | B3: 0 | C3: 4 | D3: 14 | E3: 24 | F3: =IF( E3>100, "High Risk", IF( E3>=50, "Medium Risk", "Low Risk" ) ) -> Low Risk
A4: MN-03 | B4: 1 | C4: 4 | D4: 10 | E4: 13 | F4: =IF( E4>100, "High Risk", IF( E4>=50, "Medium Risk", "Low Risk" ) ) -> Low Risk
A5: MN-04 | B5: 1 | C5: 4 | D5: 6 | E5: 16 | F5: =IF( E5>100, "High Risk", IF( E5>=50, "Medium Risk", "Low Risk" ) ) -> Low Risk
A6: MN-09 | B6: 0 | C6: 2 | D6: 7 | E6: 11 | F6: =IF( E6>100, "High Risk", IF( E6>=50, "Medium Risk", "Low Risk" ) ) -> Low Risk
A7: MN-08 | B7: 0 | C7: 3 | D7: 4 | E7: 6 | F7: =IF( E7>100, "High Risk", IF( E7>=50, "Medium Risk", "Low Risk" ) ) -> Low Risk
A8: MN-10 | B8: 2 | C8: 9 | D8: 11 | E8: 19 | F8: =IF( E8>100, "High Risk", IF( E8>=50, "Medium Risk", "Low Risk" ) ) -> Low Risk
A9: MN-11 | B9: 3 | C9: 6 | D9: 8 | E9: 10 | F9: =IF( E9>100, "High Risk", IF( E9>=50, "Medium Risk", "Low Risk" ) ) -> Low Risk
A10: MN-12 | B10: 4 | C10: 13 | D10: 17 | E10: 24 | F10: =IF( E10>100, "High Risk", IF( E10>=50, "Medium Risk", "Low Risk" ) ) -> Low Risk
A11: MN-13 | B11: 2 | C11: 4 | D11: 11 | E11: 16 | F11: =IF( E11>100, "High Risk", IF( E11>=50, "Medium Risk", "Low Risk" ) ) -> Low Risk
A12: MN-14 | B12: 23 | C12: 79 | D12: 112 | E12: 145 | F12: =IF( E12>100, "High Risk", IF( E12>=50, "Medium Risk", "Low Risk" ) ) -> High Risk
A13: MN-15 | B13: 16 | C13: 44 | D13: 79 | E13: 111 | F13: =IF( E13>100, "High Risk", IF( E13>=50, "Medium Risk", "Low Risk" ) ) -> High Risk
... A51: MN-06 | B51: 1 | C51: 2 | D51: 3 | E51: 3 | F51: =IF( E51>100, "High Risk", IF( E51>=50, "Medium Risk", "Low Risk" ) ) -> Low Risk

Sheet Inventory_Health
A1: SKU | B1: condition | C1: total-inventory | D1: available | E1: inbound-shipped | F1: inbound-received | G1: reserved-quantity | H1: unfulfillable-quantity | I1: inv-age-0-to-30-days | J1: inv-age-31-to-60-days | K1: inv-age-61-to-90-days | L1: inv-age-181-to-330-days | M1: inv-age-331-to-365-days | N1: inv-age-365-plus-days | O1: currency | P1: units-shipped-t7 | Q1: units-shipped-t30 | R1: units-shipped-t60 | S1: units-shipped-t90 | T1: sell-through | U1: item-volume | V1: volume-unit-measurement | W1: storage-type | X1: storage-volume | Y1: marketplace | Z1: days-of-supply | AA1: weeks-of-cover-t30 | AB1: weeks-of-cover-t90 | AC1: Calculated_Total_Inventory
A2: MN-01 | B2: New | C2: 382 | D2: 264 | E2: 40 | F2: 9 | G2: 68 | H2: 1 | I2: 12 | J2: 261 | K2: 56 | L2: 0 | M2: 0 | N2: 0 | O2: USD | P2: 59 | Q2: 203 | R2: 386 | S2: 574 | T2: 1.33 | U2: 0.546781 | V2: cubic feet | W2: Standard | X2: 144.35018 | Y2: US | Z2: 47 | AA2: 6 | AB2: 7 | AC2: =IFERROR(Inventory_Health__2[[#This Row],[available]]+Inventory_Health__2[[#This Row],[inbound-shipped]]+Inventory_Health__2[[#This Row],[inbound-received]]+Inventory_Health__2[[#This Row],[reserved-quantity]]-Inventory_Health__2[[#This Row],[unfulfillable-quantity]],0) -> 380
A3: MN-02 | B3: New | C3: 306 | D3: 206 | E3: 80 | F3: 2 | G3: 18 | H3: 0 | I3: 127 | J3: 91 | K3: 17 | L3: 0 | M3: 0 | N3: 0 | O3: USD | P3: 29 | Q3: 155 | R3: 261 | S3: 417 | T3: 1.56 | U3: 0.373971 | V3: cubic feet | W3: Standard | X3: 77.038026 | Y3: US | Z3: 85 | AA3: 7 | AB3: 8 | AC3: =IFERROR(Inventory_Health__2[[#This Row],[available]]+Inventory_Health__2[[#This Row],[inbound-shipped]]+Inventory_Health__2[[#This Row],[inbound-received]]+Inventory_Health__2[[#This Row],[reserved-quantity]]-Inventory_Health__2[[#This Row],[unfulfillable-quantity]],0) -> 306
A4: MN-03 | B4: New | C4: 139 | D4: 95 | E4: 40 | F4: 0 | G4: 3 | H4: 1 | I4: 42 | J4: 8 | K4: 62 | L4: 0 | M4: 0 | N4: 0 | O4: USD | P4: 13 | Q4: 67 | R4: 116 | S4: 179 | T4: 1.16 | U4: 0.425846 | V4: cubic feet | W4: Standard | X4: 40.45537 | Y4: US | Z4: 83 | AA4: 8 | AB4: 9 | AC4: =IFERROR(Inventory_Health__2[[#This Row],[available]]+Inventory_Health__2[[#This Row],[inbound-shipped]]+Inventory_Health__2[[#This Row],[inbound-received]]+Inventory_Health__2[[#This Row],[reserved-quantity]]-Inventory_Health__2[[#This Row],[unfulfillable-quantity]],0) -> 137
A5: MN-04 | B5: New | C5: 171 | D5: 70 | E5: 80 | F5: 8 | G5: 13 | H5: 0 | I5: 3 | J5: 84 | K5: 0 | L5: 0 | M5: 0 | N5: 0 | O5: USD | P5: 18 | Q5: 71 | R5: 128 | S5: 187 | T5: 1.65 | U5: 0.375575 | V5: cubic feet | W5: Standard | X5: 26.29025 | Y5: US | Z5: 99 | AA5: 8 | AB5: 10 | AC5: =IFERROR(Inventory_Health__2[[#This Row],[available]]+Inventory_Health__2[[#This Row],[inbound-shipped]]+Inventory_Health__2[[#This Row],[inbound-received]]+Inventory_Health__2[[#This Row],[reserved-quantity]]-Inventory_Health__2[[#This Row],[unfulfillable-quantity]],0) -> 171
A6: MN-05 | B6: New | C6: 283 | D6: 0 | E6: 0 | F6: 49 | G6: 234 | H6: 0 | I6: 53 | J6: 141 | K6: 0 | L6: 0 | M6: 0 | N6: 0 | O6: USD | P6: 249 | Q6: 491 | R6: 543 | S6: 557 | T6: 1.47 | U6: 0.270417 | V6: cubic feet | W6: Standard | X6: 0 | Y6: US | Z6: 145 | AA6: 0 | AB6: 1 | AC6: =IFERROR(Inventory_Health__2[[#This Row],[available]]+Inventory_Health__2[[#This Row],[inbound-shipped]]+Inventory_Health__2[[#This Row],[inbound-received]]+Inventory_Health__2[[#This Row],[reserved-quantity]]-Inventory_Health__2[[#This Row],[unfulfillable-quantity]],0) -> 283
A7: MN-06 | B7: New | C7: 21 | D7: 1 | E7: 0 | F7: 0 | G7: 20 | H7: 0 | I7: 8 | J7: 40 | K7: 0 | L7: 0 | M7: 0 | N7: 0 | O7: USD | P7: 61 | Q7: 131 | R7: 150 | S7: 173 | T7: 1.23 | U7: 0.155234 | V7: cubic feet | W7: Standard | X7: 0.155234 | Y7: US | Z7: 0 | AA7: 0 | AB7: 0 | AC7: =IFERROR(Inventory_Health__2[[#This Row],[available]]+Inventory_Health__2[[#This Row],[inbound-shipped]]+Inventory_Health__2[[#This Row],[inbound-received]]+Inventory_Health__2[[#This Row],[reserved-quantity]]-Inventory_Health__2[[#This Row],[unfulfillable-quantity]],0) -> 21
A8: MN-07 | B8: New | C8: 144 | D8: 134 | E8: 0 | F8: 0 | G8: 7 | H8: 3 | I8: 51 | J8: 45 | K8: 55 | L8: 0 | M8: 0 | N8: 0 | O8: USD | P8: 15 | Q8: 95 | R8: 150 | S8: 220 | T8: 1.25 | U8: 0.336372 | V8: cubic feet | W8: Oversize | X8: 45.073848 | Y8: US | Z8: 59 | AA8: 5 | AB8: 7 | AC8: =IFERROR(Inventory_Health__2[[#This Row],[available]]+Inventory_Health__2[[#This Row],[inbound-shipped]]+Inventory_Health__2[[#This Row],[inbound-received]]+Inventory_Health__2[[#This Row],[reserved-quantity]]-Inventory_Health__2[[#This Row],[unfulfillable-quantity]],0) -> 138
A9: MN-08 | B9: New | C9: 255 | D9: 95 | E9: 152 | F9: 0 | G9: 8 | H9: 0 | I9: 4 | J9: 42 | K9: 41 | L9: 17 | M9: 0 | N9: 0 | O9: USD | P9: 2 | Q9: 10 | R9: 18 | S9: 36 | T9: 0.37 | U9: 0.315957 | V9: cubic feet | W9: Standard | X9: 30.015915 | Y9: US | Z9: 103 | AA9: 98 | AB9: 89 | AC9: =IFERROR(Inventory_Health__2[[#This Row],[available]]+Inventory_Health__2[[#This Row],[inbound-shipped]]+Inventory_Health__2[[#This Row],[inbound-received]]+Inventory_Health__2[[#This Row],[reserved-quantity]]-Inventory_Health__2[[#This Row],[unfulfillable-quantity]],0) -> 255
A10: MN-09 | B10: New | C10: 211 | D10: 207 | E10: 0 | F10: 0 | G10: 3 | H10: 1 | I10: 3 | J10: 1 | K10: 203 | L10: 0 | M10: 0 | N10: 0 | O10: USD | P10: 3 | Q10: 19 | R10: 38 | S10: 66 | T10: 0.36 | U10: 0.108386 | V10: cubic feet | W10: Standard | X10: 22.435902 | Y10: US | Z10: 57 | AA10: 43 | AB10: 40 | AC10: =IFERROR(Inventory_Health__2[[#This Row],[available]]+Inventory_Health__2[[#This Row],[inbound-shipped]]+Inventory_Health__2[[#This Row],[inbound-received]]+Inventory_Health__2[[#This Row],[reserved-quantity]]-Inventory_Health__2[[#This Row],[unfulfillable-quantity]],0) -> 209
A11: MN-10 | B11: New | C11: 363 | D11: 102 | E11: 200 | F11: 16 | G11: 45 | H11: 0 | I11: 96 | J11: 10 | K11: 43 | L11: 0 | M11: 0 | N11: 0 | O11: USD | P11: 25 | Q11: 122 | R11: 177 | S11: 231 | T11: 1.17 | U11: 0.160565 | V11: cubic feet | W11: Standard | X11: 16.37763 | Y11: US | Z11: 150 | AA11: 10 | AB11: 17 | AC11: =IFERROR(Inventory_Health__2[[#This Row],[available]]+Inventory_Health__2[[#This Row],[inbound-shipped]]+Inventory_Health__2[[#This Row],[inbound-received]]+Inventory_Health__2[[#This Row],[reserved-quantity]]-Inventory_Health__2[[#This Row],[unfulfillable-quantity]],0) -> 363
A12: MN-11 | B12: New | C12: 230 | D12: 124 | E12: 100 | F12: 0 | G12: 6 | H12: 0 | I12: 5 | J12: 133 | K12: 0 | L12: 0 | M12: 0 | N12: 0 | O12: USD | P12: 12 | Q12: 101 | R12: 141 | S12: 215 | T12: 1.43 | U12: 0.183563 | V12: cubic feet | W12: Standard | X12: 22.761812 | Y12: US | Z12: 159 | AA12: 8 | AB12: 13 | AC12: =IFERROR(Inventory_Health__2[[#This Row],[available]]+Inventory_Health__2[[#This Row],[inbound-shipped]]+Inventory_Health__2[[#This Row],[inbound-received]]+Inventory_Health__2[[#This Row],[reserved-quantity]]-Inventory_Health__2[[#This Row],[unfulfillable-quantity]],0) -> 230
A13: MN-12 | B13: New | C13: 259 | D13: 87 | E13: 100 | F13: 0 | G13: 69 | H13: 3 | I13: 93 | J13: 56 | K13: 0 | L13: 0 | M13: 0 | N13: 0 | O13: USD | P13: 48 | Q13: 194 | R13: 291 | S13: 354 | T13: 1.69 | U13: 0.279394 | V13: cubic feet | W13: Standard | X13: 24.307278 | Y13: US | Z13: 74 | AA13: 3 | AB13: 6 | AC13: =IFERROR(Inventory_Health__2[[#This Row],[available]]+Inventory_Health__2[[#This Row],[inbound-shipped]]+Inventory_Health__2[[#This Row],[inbound-received]]+Inventory_Health__2[[#This Row],[reserved-quantity]]-Inventory_Health__2[[#This Row],[unfulfillable-quantity]],0) -> 253
... A19: MN-18 | B19: New | C19: 458 | D19: 261 | E19: 160 | F19: 6 | G19: 26 | H19: 5 | I19: 108 | J19: 225 | K19: 0 | L19: 0 | M19: 0 | N19: 0 | O19: USD | P19: 21 | Q19: 273 | R19: 482 | S19: 761 | T19: 1.81 | U19: 0.457576 | V19: cubic feet | W19: Standard | X19: 119.42734 | Y19: US | Z19: 90 | AA19: 6 | AB19: 7 | AC19: =IFERROR(Inventory_Health__2[[#This Row],[available]]+Inventory_Health__2[[#This Row],[inbound-shipped]]+Inventory_Health__2[[#This Row],[inbound-received]]+Inventory_Health__2[[#This Row],[reserved-quantity]]-Inventory_Health__2[[#This Row],[unfulfillable-quantity]],0) -> 448
A20: MN-19 | B20: New | D20: 342 | E20: 0 | F20: 1 | G20: 115 | H20: 2 | I20: 70 | J20: 429 | K20: 0 | L20: 0 | M20: 0 | N20: 0 | O20: USD | P20: 122 | Q20: 565 | R20: 994 | S20: 1485 | T20: 1.83 | U20: 0.636574 | V20: cubic feet | W20: Oversize | X20: 217.70831 | Y20: US | Z20: 15 | AA20: 2 | AB20: 3 | AC20: =IFERROR(Inventory_Health__2[[#This Row],[available]]+Inventory_Health__2[[#This Row],[inbound-shipped]]+Inventory_Health__2[[#This Row],[inbound-received]]+Inventory_Health__2[[#This Row],[reserved-quantity]]-Inventory_Health__2[[#This Row],[unfulfillable-quantity]],0) -> 456
A21: MN-20 | B21: New | C21: 1039 | D21: 712 | E21: 256 | F21: 0 | G21: 68 | H21: 3 | I21: 159 | J21: 684 | K21: 0 | L21: 0 | M21: 0 | N21: 0 | O21: USD | P21: 124 | Q21: 526 | R21: 1000 | S21: 1494 | T21: 1.15 | U21: 0.039821 | V21: cubic feet | W21: Standard | X21: 28.352552 | Y21: US | Z21: 66 | AA21: 7 | AB21: 8 | AC21: =IFERROR(Inventory_Health__2[[#This Row],[available]]+Inventory_Health__2[[#This Row],[inbound-shipped]]+Inventory_Health__2[[#This Row],[inbound-received]]+Inventory_Health__2[[#This Row],[reserved-quantity]]-Inventory_Health__2[[#This Row],[unfulfillable-quantity]],0) -> 1033
A22: MN-21 | B22: New | C22: 18 | D22: 2 | E22: 0 | F22: 0 | G22: 15 | H22: 1 | I22: 23 | J22: 16 | K22: 0 | L22: 0 | M22: 0 | N22: 0 | O22: USD | P22: 41 | Q22: 235 | R22: 432 | S22: 553 | T22: 3.18 | U22: 0.234841 | V22: cubic feet | W22: Standard | X22: 0.469682 | Y22: US | Z22: 0 | AA22: 0 | AB22: 0 | AC22: =IFERROR(Inventory_Health__2[[#This Row],[available]]+Inventory_Health__2[[#This Row],[inbound-shipped]]+Inventory_Health__2[[#This Row],[inbound-received]]+Inventory_Health__2[[#This Row],[reserved-quantity]]-Inventory_Health__2[[#This Row],[unfulfillable-quantity]],0) -> 16
A23: MN-22 | B23: New | C23: 395 | D23: 252 | E23: 100 | F23: 4 | G23: 38 | H23: 1 | I23: 268 | J23: 63 | K23: 0 | L23: 0 | M23: 0 | N23: 0 | O23: USD | P23: 78 | Q23: 355 | R23: 553 | S23: 733 | T23: 1.85 | U23: 0.257323 | V23: cubic feet | W23: Standard | X23: 64.845396 | Y23: US | Z23: 51 | AA23: 4 | AB23: 6 | AC23: =IFERROR(Inventory_Health__2[[#This Row],[available]]+Inventory_Health__2[[#This Row],[inbound-shipped]]+Inventory_Health__2[[#This Row],[inbound-received]]+Inventory_Health__2[[#This Row],[reserved-quantity]]-Inventory_Health__2[[#This Row],[unfulfillable-quantity]],0) -> 393
A24: MN-23 | B24: New | C24: 547 | D24: 285 | E24: 240 | F24: 0 | G24: 20 | H24: 2 | I24: 227 | J24: 122 | K24: 0 | L24: 0 | M24: 0 | N24: 0 | O24: USD | P24: 86 | Q24: 326 | R24: 496 | S24: 691 | T24: 1.64 | U24: 0.017404 | V24: cubic feet | W24: Standard | X24: 4.96014 | Y24: US | Z24: 73 | AA24: 6 | AB24: 9 | AC24: =IFERROR(Inventory_Health__2[[#This Row],[available]]+Inventory_Health__2[[#This Row],[inbound-shipped]]+Inventory_Health__2[[#This Row],[inbound-received]]+Inventory_Health__2[[#This Row],[reserved-quantity]]-Inventory_Health__2[[#This Row],[unfulfillable-quantity]],0) -> 543
A25: MN-24 | B25: New | C25: 424 | D25: 292 | E25: 100 | F25: 2 | G25: 30 | H25: 0 | I25: 210 | J25: 48 | K25: 87 | L25: 0 | M25: 0 | N25: 0 | O25: USD | P25: 43 | Q25: 200 | R25: 310 | S25: 468 | T25: 1.37 | U25: 0.186266 | V25: cubic feet | W25: Standard | X25: 54.389672 | Y25: US | Z25: 106 | AA25: 7 | AB25: 10 | AC25: =IFERROR(Inventory_Health__2[[#This Row],[available]]+Inventory_Health__2[[#This Row],[inbound-shipped]]+Inventory_Health__2[[#This Row],[inbound-received]]+Inventory_Health__2[[#This Row],[reserved-quantity]]-Inventory_Health__2[[#This Row],[unfulfillable-quantity]],0) -> 424
A26: MN-25 | B26: New | C26: 1645 | D26: 341 | E26: 1100 | F26: 41 | G26: 138 | H26: 25 | I26: 74 | J26: 482 | K26: 0 | L26: 0 | M26: 0 | N26: 0 | O26: USD | P26: 233 | Q26: 1729 | R26: 3336 | S26: 4300 | T26: 3 | U26: 0.510138 | V26: cubic feet | W26: Standard | X26: 173.95706 | Y26: US | Z26: 41 | AA26: 3 | AB26: 4 | AC26: =IFERROR(Inventory_Health__2[[#This Row],[available]]+Inventory_Health__2[[#This Row],[inbound-shipped]]+Inventory_Health__2[[#This Row],[inbound-received]]+Inventory_Health__2[[#This Row],[reserved-quantity]]-Inventory_Health__2[[#This Row],[unfulfillable-quantity]],0) -> 1595
A27: MN-26 | B27: New | C27: 1142 | D27: 1079 | E27: 0 | F27: 5 | G27: 55 | H27: 3 | I27: 456 | J27: 756 | K27: 0 | L27: 0 | M27: 0 | N27: 0 | O27: USD | P27: 132 | Q27: 515 | R27: 1026 | S27: 1596 | T27: 1.64 | U27: 0.285126 | V27: cubic feet | W27: Standard | X27: 307.65095 | Y27: US | Z27: 80 | AA27: 8 | AB27: 8 | AC27: =IFERROR(Inventory_Health__2[[#This Row],[available]]+Inventory_Health__2[[#This Row],[inbound-shipped]]+Inventory_Health__2[[#This Row],[inbound-received]]+Inventory_Health__2[[#This Row],[reserved-quantity]]-Inventory_Health__2[[#This Row],[unfulfillable-quantity]],0) -> 1136
A28: MN-27 | B28: New | C28: 838 | D28: 772 | E28: 0 | F28: 24 | G28: 42 | H28: 0 | I28: 696 | J28: 163 | K28: 0 | L28: 0 | M28: 0 | N28: 0 | O28: USD | P28: 129 | Q28: 542 | R28: 932 | S28: 1320 | T28: 1.83 | U28: 0.287959 | V28: cubic feet | W28: Standard | X28: 222.30435 | Y28: US | Z28: 82 | AA28: 5 | AB28: 7 | AC28: =IFERROR(Inventory_Health__2[[#This Row],[available]]+Inventory_Health__2[[#This Row],[inbound-shipped]]+Inventory_Health__2[[#This Row],[inbound-received]]+Inventory_Health__2[[#This Row],[reserved-quantity]]-Inventory_Health__2[[#This Row],[unfulfillable-quantity]],0) -> 838
A29: MN-28 | B29: New | C29: 1327 | D29: 1043 | E29: 200 | F29: 7 | G29: 70 | H29: 7 | I29: 55 | J29: 1202 | K29: 0 | L29: 0 | M29: 0 | N29: 0 | O29: USD | P29: 198 | Q29: 767 | R29: 1586 | S29: 2404 | T29: 1.65 | U29: 0.199538 | V29: cubic feet | W29: Standard | X29: 208.11813 | Y29: US | Z29: 67 | AA29: 6 | AB29: 6 | AC29: =IFERROR(Inventory_Health__2[[#This Row],[available]]+Inventory_Health__2[[#This Row],[inbound-shipped]]+Inventory_Health__2[[#This Row],[inbound-received]]+Inventory_Health__2[[#This Row],[reserved-quantity]]-Inventory_Health__2[[#This Row],[unfulfillable-quantity]],0) -> 1313
A30: MN-29 | B30: New | C30: 924 | D30: 815 | E30: 0 | F30: 12 | G30: 97 | H30: 0 | I30: 260 | J30: 673 | K30: 0 | L30: 0 | M30: 0 | N30: 0 | O30: USD | P30: 132 | Q30: 545 | R30: 988 | S30: 1451 | T30: 1.6 | U30: 0.09045 | V30: cubic feet | W30: Standard | X30: 73.71675 | Y30: US | Z30: 77 | AA30: 6 | AB30: 7 | AC30: =IFERROR(Inventory_Health__2[[#This Row],[available]]+Inventory_Health__2[[#This Row],[inbound-shipped]]+Inventory_Health__2[[#This Row],[inbound-received]]+Inventory_Health__2[[#This Row],[reserved-quantity]]-Inventory_Health__2[[#This Row],[unfulfillable-quantity]],0) -> 924
A31: MN-30 | B31: New | C31: 404 | D31: 254 | E31: 100 | F31: 5 | G31: 44 | H31: 1 | I31: 139 | J31: 104 | K31: 68 | L31: 0 | M31: 0 | N31: 0 | O31: USD | P31: 29 | Q31: 245 | R31: 423 | S31: 612 | T31: 1.44 | U31: 0.474537 | V31: cubic feet | W31: Oversize | X31: 120.5324 | Y31: US | Z31: 65 | AA31: 5 | AB31: 7 | AC31: =IFERROR(Inventory_Health__2[[#This Row],[available]]+Inventory_Health__2[[#This Row],[inbound-shipped]]+Inventory_Health__2[[#This Row],[inbound-received]]+Inventory_Health__2[[#This Row],[reserved-quantity]]-Inventory_Health__2[[#This Row],[unfulfillable-quantity]],0) -> 402
A32: MN-31 | B32: New | C32: 300 | D32: 199 | E32: 80 | F32: 6 | G32: 15 | H32: 0 | I32: 15 | J32: 207 | K32: 0 | L32: 0 | M32: 0 | N32: 0 | O32: USD | P32: 24 | Q32: 120 | R32: 211 | S32: 331 | T32: 1.61 | U32: 0.304942 | V32: cubic feet | W32: Standard | X32: 60.683458 | Y32: US | Z32: 118 | AA32: 9 | AB32: 11 | AC32: =IFERROR(Inventory_Health__2[[#This Row],[available]]+Inventory_Health__2[[#This Row],[inbound-shipped]]+Inventory_Health__2[[#This Row],[inbound-received]]+Inventory_Health__2[[#This Row],[reserved-quantity]]-Inventory_Health__2[[#This Row],[unfulfillable-quantity]],0) -> 300
... A39: MN-38 | B39: New | C39: 991 | D39: 861 | E39: 0 | F39: 73 | G39: 56 | H39: 1 | I39: 587 | J39: 373 | K39: 0 | L39: 0 | M39: 0 | N39: 0 | O39: USD | P39: 114 | Q39: 429 | R39: 954 | S39: 1509 | T39: 1.8 | U39: 0.162883 | V39: cubic feet | W39: Standard | X39: 140.24226 | Y39: US | Z39: 76 | AA39: 8 | AB39: 8 | AC39: =IFERROR(Inventory_Health__2[[#This Row],[available]]+Inventory_Health__2[[#This Row],[inbound-shipped]]+Inventory_Health__2[[#This Row],[inbound-received]]+Inventory_Health__2[[#This Row],[reserved-quantity]]-Inventory_Health__2[[#This Row],[unfulfillable-quantity]],0) -> 989
A40: MN-39 | B40: New | D40: 22 | E40: 216 | F40: 0 | G40: 36 | H40: 0 | I40: 52 | J40: 2 | K40: 23 | L40: 0 | M40: 0 | N40: 0 | O40: USD | P40: 52 | Q40: 157 | R40: 218 | S40: 288 | T40: 1.56 | U40: 0.089032 | V40: cubic feet | W40: Standard | X40: 1.958704 | Y40: US | Z40: 95 | AA40: 6 | AB40: 10 | AC40: =IFERROR(Inventory_Health__2[[#This Row],[available]]+Inventory_Health__2[[#This Row],[inbound-shipped]]+Inventory_Health__2[[#This Row],[inbound-received]]+Inventory_Health__2[[#This Row],[reserved-quantity]]-Inventory_Health__2[[#This Row],[unfulfillable-quantity]],0) -> 274
A41: MN-40 | B41: New | C41: 655 | D41: 407 | E41: 0 | F41: 181 | G41: 67 | H41: 0 | I41: 356 | J41: 155 | K41: 0 | L41: 0 | M41: 0 | N41: 0 | O41: USD | P41: 85 | Q41: 337 | R41: 613 | S41: 893 | T41: 1.74 | U41: 0.132234 | V41: cubic feet | W41: Standard | X41: 53.819238 | Y41: US | Z41: 84 | AA41: 6 | AB41: 8 | AC41: =IFERROR(Inventory_Health__2[[#This Row],[available]]+Inventory_Health__2[[#This Row],[inbound-shipped]]+Inventory_Health__2[[#This Row],[inbound-received]]+Inventory_Health__2[[#This Row],[reserved-quantity]]-Inventory_Health__2[[#This Row],[unfulfillable-quantity]],0) -> 655
A42: MN-41 | B42: New | C42: 935 | D42: 694 | E42: 150 | F42: 19 | G42: 61 | H42: 11 | I42: 22 | J42: 831 | K42: 0 | L42: 0 | M42: 0 | N42: 0 | O42: USD | P42: 142 | Q42: 535 | R42: 953 | S42: 1443 | T42: 1.52 | U42: 0.643986 | V42: cubic feet | W42: Standard | X42: 446.92628 | Y42: US | Z42: 75 | AA42: 6 | AB42: 7 | AC42: =IFERROR(Inventory_Health__2[[#This Row],[available]]+Inventory_Health__2[[#This Row],[inbound-shipped]]+Inventory_Health__2[[#This Row],[inbound-received]]+Inventory_Health__2[[#This Row],[reserved-quantity]]-Inventory_Health__2[[#This Row],[unfulfillable-quantity]],0) -> 913
A43: MN-42 | B43: New | C43: 752 | D43: 673 | E43: 0 | F43: 10 | G43: 66 | H43: 3 | I43: 328 | J43: 206 | K43: 258 | L43: 0 | M43: 0 | N43: 0 | O43: USD | P43: 83 | Q43: 252 | R43: 709 | S43: 1224 | T43: 1.42 | U43: 0.372838 | V43: cubic feet | W43: Standard | X43: 250.91997 | Y43: US | Z43: 86 | AA43: 10 | AB43: 7 | AC43: =IFERROR(Inventory_Health__2[[#This Row],[available]]+Inventory_Health__2[[#This Row],[inbound-shipped]]+Inventory_Health__2[[#This Row],[inbound-received]]+Inventory_Health__2[[#This Row],[reserved-quantity]]-Inventory_Health__2[[#This Row],[unfulfillable-quantity]],0) -> 746
A44: MN-43 | B44: New | C44: 166 | D44: 123 | E44: 0 | F44: 0 | G44: 43 | H44: 0 | I44: 110 | J44: 12 | K44: 51 | L44: 0 | M44: 0 | N44: 0 | O44: USD | P44: 25 | Q44: 100 | R44: 162 | S44: 217 | T44: 1.24 | U44: 0.035586 | V44: cubic feet | W44: Standard | X44: 4.377078 | Y44: US | Z44: 74 | AA44: 4 | AB44: 7 | AC44: =IFERROR(Inventory_Health__2[[#This Row],[available]]+Inventory_Health__2[[#This Row],[inbound-shipped]]+Inventory_Health__2[[#This Row],[inbound-received]]+Inventory_Health__2[[#This Row],[reserved-quantity]]-Inventory_Health__2[[#This Row],[unfulfillable-quantity]],0) -> 166
A45: MN-44 | B45: New | C45: 130 | D45: 96 | E45: 0 | F45: 17 | G45: 16 | H45: 1 | I45: 69 | J45: 54 | K45: 0 | L45: 0 | M45: 0 | N45: 0 | O45: USD | P45: 14 | Q45: 57 | R45: 96 | S45: 133 | T45: 0.85 | U45: 0.034594 | V45: cubic feet | W45: Standard | X45: 3.321024 | Y45: US | Z45: 99 | AA45: 7 | AB45: 11 | AC45: =IFERROR(Inventory_Health__2[[#This Row],[available]]+Inventory_Health__2[[#This Row],[inbound-shipped]]+Inventory_Health__2[[#This Row],[inbound-received]]+Inventory_Health__2[[#This Row],[reserved-quantity]]-Inventory_Health__2[[#This Row],[unfulfillable-quantity]],0) -> 128
A46: MN-45 | B46: New | C46: 159 | D46: 82 | E46: 48 | F46: 17 | G46: 12 | H46: 0 | I46: 51 | J46: 55 | K46: 0 | L46: 0 | M46: 0 | N46: 0 | O46: USD | P46: 20 | Q46: 71 | R46: 204 | S46: 328 | T46: 2.02 | U46: 0.103417 | V46: cubic feet | W46: Standard | X46: 8.480194 | Y46: US | Z46: 63 | AA46: 8 | AB46: 5 | AC46: =IFERROR(Inventory_Health__2[[#This Row],[available]]+Inventory_Health__2[[#This Row],[inbound-shipped]]+Inventory_Health__2[[#This Row],[inbound-received]]+Inventory_Health__2[[#This Row],[reserved-quantity]]-Inventory_Health__2[[#This Row],[unfulfillable-quantity]],0) -> 159
A47: MN-46 | B47: New | C47: 177 | D47: 109 | E47: 48 | F47: 4 | G47: 15 | H47: 1 | I47: 77 | J47: 52 | K47: 0 | L47: 0 | M47: 0 | N47: 0 | O47: USD | P47: 19 | Q47: 78 | R47: 117 | S47: 173 | T47: 1.4 | U47: 0.082992 | V47: cubic feet | W47: Standard | X47: 9.046128 | Y47: US | Z47: 103 | AA47: 8 | AB47: 12 | AC47: =IFERROR(Inventory_Health__2[[#This Row],[available]]+Inventory_Health__2[[#This Row],[inbound-shipped]]+Inventory_Health__2[[#This Row],[inbound-received]]+Inventory_Health__2[[#This Row],[reserved-quantity]]-Inventory_Health__2[[#This Row],[unfulfillable-quantity]],0) -> 175
A48: MN-47 | B48: New | C48: 256 | D48: 241 | E48: 0 | F48: 0 | G48: 15 | H48: 0 | I48: 11 | J48: 82 | K48: 169 | L48: 0 | M48: 0 | N48: 0 | O48: USD | P48: 12 | Q48: 54 | R48: 158 | S48: 271 | T48: 0.96 | U48: 0.474597 | V48: cubic feet | W48: Standard | X48: 114.37788 | Y48: US | Z48: 89 | AA48: 17 | AB48: 11 | AC48: =IFERROR(Inventory_Health__2[[#This Row],[available]]+Inventory_Health__2[[#This Row],[inbound-shipped]]+Inventory_Health__2[[#This Row],[inbound-received]]+Inventory_Health__2[[#This Row],[reserved-quantity]]-Inventory_Health__2[[#This Row],[unfulfillable-quantity]],0) -> 256
A49: MN-48 | B49: New | C49: 210 | D49: 196 | E49: 0 | F49: 1 | G49: 13 | H49: 0 | I49: 1 | J49: 163 | K49: 45 | L49: 0 | M49: 0 | N49: 0 | O49: USD | P49: 26 | Q49: 67 | R49: 158 | S49: 265 | T49: 1.19 | U49: 0.91242 | V49: cubic feet | W49: Standard | X49: 178.83432 | Y49: US | Z49: 84 | AA49: 11 | AB49: 9 | AC49: =IFERROR(Inventory_Health__2[[#This Row],[available]]+Inventory_Health__2[[#This Row],[inbound-shipped]]+Inventory_Health__2[[#This Row],[inbound-received]]+Inventory_Health__2[[#This Row],[reserved-quantity]]-Inventory_Health__2[[#This Row],[unfulfillable-quantity]],0) -> 210
A50: MN-49 | B50: New | C50: 196 | D50: 156 | E50: 0 | F50: 21 | G50: 18 | H50: 1 | I50: 10 | J50: 182 | K50: 0 | L50: 0 | M50: 0 | N50: 0 | O50: USD | P50: 30 | Q50: 129 | R50: 277 | S50: 404 | T50: 1.89 | U50: 0.37674 | V50: cubic feet | W50: Standard | X50: 58.77144 | Y50: US | Z50: 40 | AA50: 5 | AB50: 5 | AC50: =IFERROR(Inventory_Health__2[[#This Row],[available]]+Inventory_Health__2[[#This Row],[inbound-shipped]]+Inventory_Health__2[[#This Row],[inbound-received]]+Inventory_Health__2[[#This Row],[reserved-quantity]]-Inventory_Health__2[[#This Row],[unfulfillable-quantity]],0) -> 194
A51: MN-50 | B51: New | C51: 217 | D51: 76 | E51: 60 | F51: 7 | G51: 73 | H51: 1 | I51: 89 | J51: 86 | K51: 0 | L51: 0 | M51: 0 | N51: 0 | O51: USD | P51: 49 | Q51: 148 | R51: 254 | S51: 378 | T51: 1.92 | U51: 0.336525 | V51: cubic feet | W51: Standard | X51: 25.5759 | Y51: US | Z51: 49 | AA51: 3 | AB51: 4 | AC51: =IFERROR(Inventory_Health__2[[#This Row],[available]]+Inventory_Health__2[[#This Row],[inbound-shipped]]+Inventory_Health__2[[#This Row],[inbound-received]]+Inventory_Health__2[[#This Row],[reserved-quantity]]-Inventory_Health__2[[#This Row],[unfulfillable-quantity]],0) -> 215

Sheet Historical_Sales
A1: Date | B1: SKU | C1: Sessions - Total | D1: Page Views - Total | E1: Units Ordered | F1: Ordered Product Sales | G1: Total Order Items | H1: Conversion_Rate
A2: 45901 | B2: MN-01 | C2: 22 | D2: 32 | E2: 6 | F2: 228.1 | G2: 5 | H2: =IF(Historical_Sales[[#This Row],[Sessions - Total]]=0,0,Historical_Sales[[#This Row],[Units Ordered]]/Historical_Sales[[#This Row],[Sessions - Total]]) -> 0.27272727
A3: 45901 | B3: MN-02 | C3: 28 | D3: 33 | E3: 5 | F3: 158.96 | G3: 5 | H3: =IF(Historical_Sales[[#This Row],[Sessions - Total]]=0,0,Historical_Sales[[#This Row],[Units Ordered]]/Historical_Sales[[#This Row],[Sessions - Total]]) -> 0.17857143
A4: 45901 | B4: MN-03 | C4: 9 | D4: 12 | E4: 2 | F4: 81.35 | G4: 2 | H4: =IF(Historical_Sales[[#This Row],[Sessions - Total]]=0,0,Historical_Sales[[#This Row],[Units Ordered]]/Historical_Sales[[#This Row],[Sessions - Total]]) -> 0.22222222
A5: 45901 | B5: MN-07 | C5: 31 | D5: 41 | E5: 2 | F5: 70.11 | G5: 2 | H5: =IF(Historical_Sales[[#This Row],[Sessions - Total]]=0,0,Historical_Sales[[#This Row],[Units Ordered]]/Historical_Sales[[#This Row],[Sessions - Total]]) -> 0.064516129 | L5: Sales Summary
A6: 45901 | B6: MN-09 | C6: 24 | D6: 32 | E6: 2 | F6: 32.26 | G6: 1 | H6: =IF(Historical_Sales[[#This Row],[Sessions - Total]]=0,0,Historical_Sales[[#This Row],[Units Ordered]]/Historical_Sales[[#This Row],[Sessions - Total]]) -> 0.083333333
A7: 45901 | B7: MN-10 | C7: 10 | D7: 11 | E7: 1 | F7: 23.15 | G7: 1 | H7: =IF(Historical_Sales[[#This Row],[Sessions - Total]]=0,0,Historical_Sales[[#This Row],[Units Ordered]]/Historical_Sales[[#This Row],[Sessions - Total]]) -> 0.1 | L7: Row Labels | M7: Sum of Sessions - Total | N7: Sum of Units Ordered | O7: Conversion_rate
A8: 45901 | B8: MN-13 | C8: 27 | D8: 44 | E8: 5 | F8: 106.44 | G8: 5 | H8: =IF(Historical_Sales[[#This Row],[Sessions - Total]]=0,0,Historical_Sales[[#This Row],[Units Ordered]]/Historical_Sales[[#This Row],[Sessions - Total]]) -> 0.18518519 | L8: MN-01 | M8: 1921 | N8: 587 | O8: =IF(M8=0,0,N8/M8) -> 0.30557002
A9: 45901 | B9: MN-14 | C9: 28 | D9: 49 | E9: 5 | F9: 152.47 | G9: 5 | H9: =IF(Historical_Sales[[#This Row],[Sessions - Total]]=0,0,Historical_Sales[[#This Row],[Units Ordered]]/Historical_Sales[[#This Row],[Sessions - Total]]) -> 0.17857143 | L9: MN-02 | M9: 1842 | N9: 431 | O9: =IF(M9=0,0,N9/M9) -> 0.2339848
A10: 45901 | B10: MN-15 | C10: 88 | D10: 107 | E10: 21 | F10: 466.71 | G10: 18 | H10: =IF(Historical_Sales[[#This Row],[Sessions - Total]]=0,0,Historical_Sales[[#This Row],[Units Ordered]]/Historical_Sales[[#This Row],[Sessions - Total]]) -> 0.23863636 | L10: MN-03 | M10: 859 | N10: 196 | O10: =IF(M10=0,0,N10/M10) -> 0.22817229
A11: 45901 | B11: MN-16 | C11: 27 | D11: 39 | E11: 4 | F11: 70.67 | G11: 4 | H11: =IF(Historical_Sales[[#This Row],[Sessions - Total]]=0,0,Historical_Sales[[#This Row],[Units Ordered]]/Historical_Sales[[#This Row],[Sessions - Total]]) -> 0.14814815 | L11: MN-04 | M11: 604 | N11: 191 | O11: =IF(M11=0,0,N11/M11) -> 0.31622517
A12: 45901 | B12: MN-17 | C12: 14 | D12: 28 | E12: 14 | F12: 413.4 | G12: 3 | H12: =IF(Historical_Sales[[#This Row],[Sessions - Total]]=0,0,Historical_Sales[[#This Row],[Units Ordered]]/Historical_Sales[[#This Row],[Sessions - Total]]) -> 1 | L12: MN-05 | M12: 1917 | N12: 341 | O12: =IF(M12=0,0,N12/M12) -> 0.17788211
A13: 45901 | B13: MN-18 | C13: 17 | D13: 27 | E13: 4 | F13: 117.84 | G13: 3 | H13: =IF(Historical_Sales[[#This Row],[Sessions - Total]]=0,0,Historical_Sales[[#This Row],[Units Ordered]]/Historical_Sales[[#This Row],[Sessions - Total]]) -> 0.23529412 | L13: MN-06 | M13: 562 | N13: 124 | O13: =IF(M13=0,0,N13/M13) -> 0.22064057
A14: 45901 | B14: MN-19 | C14: 60 | D14: 90 | E14: 7 | F14: 280.27 | G14: 7 | H14: =IF(Historical_Sales[[#This Row],[Sessions - Total]]=0,0,Historical_Sales[[#This Row],[Units Ordered]]/Historical_Sales[[#This Row],[Sessions - Total]]) -> 0.11666667 | L14: MN-07 | M14: 1815 | N14: 236 | O14: =IF(M14=0,0,N14/M14) -> 0.13002755
A15: 45901 | B15: MN-19 | C15: 4 | D15: 7 | E15: 1 | F15: 49.01 | G15: 1 | H15: =IF(Historical_Sales[[#This Row],[Sessions - Total]]=0,0,Historical_Sales[[#This Row],[Units Ordered]]/Historical_Sales[[#This Row],[Sessions - Total]]) -> 0.25 | L15: MN-08 | M15: 168 | N15: 43 | O15: =IF(M15=0,0,N15/M15) -> 0.25595238
A16: 45901 | B16: MN-20 | C16: 82 | D16: 112 | E16: 16 | F16: 205.87 | G16: 14 | H16: =IF(Historical_Sales[[#This Row],[Sessions - Total]]=0,0,Historical_Sales[[#This Row],[Units Ordered]]/Historical_Sales[[#This Row],[Sessions - Total]]) -> 0.19512195 | L16: MN-09 | M16: 515 | N16: 81 | O16: =IF(M16=0,0,N16/M16) -> 0.15728155
A17: 45901 | B17: MN-21 | C17: 68 | D17: 96 | E17: 8 | F17: 173.7 | G17: 6 | H17: =IF(Historical_Sales[[#This Row],[Sessions - Total]]=0,0,Historical_Sales[[#This Row],[Units Ordered]]/Historical_Sales[[#This Row],[Sessions - Total]]) -> 0.11764706 | L17: MN-10 | M17: 1292 | N17: 230 | O17: =IF(M17=0,0,N17/M17) -> 0.17801858
A18: 45901 | B18: MN-22 | C18: 33 | D18: 47 | E18: 8 | F18: 177.72 | G18: 6 | H18: =IF(Historical_Sales[[#This Row],[Sessions - Total]]=0,0,Historical_Sales[[#This Row],[Units Ordered]]/Historical_Sales[[#This Row],[Sessions - Total]]) -> 0.24242424 | L18: MN-11 | M18: 1762 | N18: 236 | O18: =IF(M18=0,0,N18/M18) -> 0.13393871
A19: 45901 | B19: MN-23 | C19: 19 | D19: 20 | E19: 5 | F19: 55.1 | G19: 5 | H19: =IF(Historical_Sales[[#This Row],[Sessions - Total]]=0,0,Historical_Sales[[#This Row],[Units Ordered]]/Historical_Sales[[#This Row],[Sessions - Total]]) -> 0.26315789 | L19: MN-12 | M19: 2040 | N19: 352 | O19: =IF(M19=0,0,N19/M19) -> 0.17254902
... A58: 45902 | B58: MN-20 | C58: 64 | D58: 78 | E58: 18 | F58: 237 | G58: 17 | H58: =IF(Historical_Sales[[#This Row],[Sessions - Total]]=0,0,Historical_Sales[[#This Row],[Units Ordered]]/Historical_Sales[[#This Row],[Sessions - Total]]) -> 0.28125 | L58: Grand Total | M58: 136799 | N58: 40234 | O58: =IF(M58=0,0,N58/M58) -> 0.29411034
A59: 45902 | B59: MN-20 | C59: 4 | D59: 5 | E59: 1 | F59: 19.45 | G59: 1 | H59: =IF(Historical_Sales[[#This Row],[Sessions - Total]]=0,0,Historical_Sales[[#This Row],[Units Ordered]]/Historical_Sales[[#This Row],[Sessions - Total]]) -> 0.25
A60: 45902 | B60: MN-21 | C60: 52 | D60: 67 | E60: 3 | F60: 62.65 | G60: 3 | H60: =IF(Historical_Sales[[#This Row],[Sessions - Total]]=0,0,Historical_Sales[[#This Row],[Units Ordered]]/Historical_Sales[[#This Row],[Sessions - Total]]) -> 0.057692308
A61: 45902 | B61: MN-22 | C61: 31 | D61: 43 | E61: 7 | F61: 156.95 | G61: 3 | H61: =IF(Historical_Sales[[#This Row],[Sessions - Total]]=0,0,Historical_Sales[[#This Row],[Units Ordered]]/Historical_Sales[[#This Row],[Sessions - Total]]) -> 0.22580645
A62: 45902 | B62: MN-23 | C62: 9 | D62: 10 | E62: 3 | F62: 37.83 | G62: 3 | H62: =IF(Historical_Sales[[#This Row],[Sessions - Total]]=0,0,Historical_Sales[[#This Row],[Units Ordered]]/Historical_Sales[[#This Row],[Sessions - Total]]) -> 0.33333333
A63: 45902 | B63: MN-24 | C63: 21 | D63: 23 | E63: 4 | F63: 80.14 | G63: 4 | H63: =IF(Historical_Sales[[#This Row],[Sessions - Total]]=0,0,Historical_Sales[[#This Row],[Units Ordered]]/Historical_Sales[[#This Row],[Sessions - Total]]) -> 0.19047619
A64: 45902 | B64: MN-25 | C64: 81 | D64: 120 | E64: 24 | F64: 877.98 | G64: 19 | H64: =IF(Historical_Sales[[#This Row],[Sessions - Total]]=0,0,Historical_Sales[[#This Row],[Units Ordered]]/Historical_Sales[[#This Row],[Sessions - Total]]) -> 0.2962963
A65: 45902 | B65: MN-26 | C65: 29 | D65: 41 | E65: 25 | F65: 780.99 | G65: 10 | H65: =IF(Historical_Sales[[#This Row],[Sessions - Total]]=0,0,Historical_Sales[[#This Row],[Units Ordered]]/Historical_Sales[[#This Row],[Sessions - Total]]) -> 0.86206897
A66: 45902 | B66: MN-27 | C66: 22 | D66: 28 | E66: 11 | F66: 346.83 | G66: 9 | H66: =IF(Historical_Sales[[#This Row],[Sessions - Total]]=0,0,Historical_Sales[[#This Row],[Units Ordered]]/Historical_Sales[[#This Row],[Sessions - Total]]) -> 0.5
A67: 45902 | B67: MN-28 | C67: 44 | D67: 58 | E67: 17 | F67: 447.41 | G67: 10 | H67: =IF(Historical_Sales[[#This Row],[Sessions - Total]]=0,0,Historical_Sales[[#This Row],[Units Ordered]]/Historical_Sales[[#This Row],[Sessions - Total]]) -> 0.38636364
A68: 45902 | B68: MN-29 | C68: 61 | D68: 83 | E68: 30 | F68: 682.68 | G68: 22 | H68: =IF(Historical_Sales[[#This Row],[Sessions - Total]]=0,0,Historical_Sales[[#This Row],[Units Ordered]]/Historical_Sales[[#This Row],[Sessions - Total]]) -> 0.49180328
A69: 45902 | B69: MN-30 | C69: 29 | D69: 45 | E69: 12 | F69: 435.22 | G69: 8 | H69: =IF(Historical_Sales[[#This Row],[Sessions - Total]]=0,0,Historical_Sales[[#This Row],[Units Ordered]]/Historical_Sales[[#This Row],[Sessions - Total]]) -> 0.4137931
A70: 45902 | B70: MN-31 | C70: 6 | D70: 9 | E70: 4 | F70: 124.09 | G70: 2 | H70: =IF(Historical_Sales[[#This Row],[Sessions - Total]]=0,0,Historical_Sales[[#This Row],[Units Ordered]]/Historical_Sales[[#This Row],[Sessions - Total]]) -> 0.66666667
... A109: 45903 | B109: MN-26 | C109: 17 | D109: 22 | E109: 46 | F109: 1431 | G109: 8 | H109: =IF(Historical_Sales[[#This Row],[Sessions - Total]]=0,0,Historical_Sales[[#This Row],[Units Ordered]]/Historical_Sales[[#This Row],[Sessions - Total]]) -> 2.7058824
A110: 45903 | B110: MN-27 | H110: =IF(Historical_Sales[[#This Row],[Sessions - Total]]=0,0,Historical_Sales[[#This Row],[Units Ordered]]/Historical_Sales[[#This Row],[Sessions - Total]]) -> 0
A111: 45903 | B111: MN-28 | C111: 50 | D111: 66 | E111: 38 | F111: 989.74 | G111: 22 | H111: =IF(Historical_Sales[[#This Row],[Sessions - Total]]=0,0,Historical_Sales[[#This Row],[Units Ordered]]/Historical_Sales[[#This Row],[Sessions - Total]]) -> 0.76
A112: 45903 | B112: MN-29 | C112: 46 | D112: 61 | E112: 20 | F112: 445.44 | G112: 12 | H112: =IF(Historical_Sales[[#This Row],[Sessions - Total]]=0,0,Historical_Sales[[#This Row],[Units Ordered]]/Historical_Sales[[#This Row],[Sessions - Total]]) -> 0.43478261
A113: 45903 | B113: MN-30 | C113: 36 | D113: 43 | E113: 18 | F113: 643.76 | G113: 8 | H113: =IF(Historical_Sales[[#This Row],[Sessions - Total]]=0,0,Historical_Sales[[#This Row],[Units Ordered]]/Historical_Sales[[#This Row],[Sessions - Total]]) -> 0.5
A114: 45903 | B114: MN-31 | C114: 15 | D114: 23 | E114: 11 | F114: 333.47 | G114: 6 | H114: =IF(Historical_Sales[[#This Row],[Sessions - Total]]=0,0,Historical_Sales[[#This Row],[Units Ordered]]/Historical_Sales[[#This Row],[Sessions - Total]]) -> 0.73333333
A115: 45903 | B115: MN-32 | C115: 11 | D115: 15 | E115: 9 | F115: 255.32 | G115: 3 | H115: =IF(Historical_Sales[[#This Row],[Sessions - Total]]=0,0,Historical_Sales[[#This Row],[Units Ordered]]/Historical_Sales[[#This Row],[Sessions - Total]]) -> 0.81818182
A116: 45903 | B116: MN-33 | C116: 8 | D116: 9 | E116: 10 | F116: 262.66 | G116: 5 | H116: =IF(Historical_Sales[[#This Row],[Sessions - Total]]=0,0,Historical_Sales[[#This Row],[Units Ordered]]/Historical_Sales[[#This Row],[Sessions - Total]]) -> 1.25
A117: 45903 | B117: MN-34 | C117: 23 | D117: 39 | E117: 10 | F117: 341.12 | G117: 7 | H117: =IF(Historical_Sales[[#This Row],[Sessions - Total]]=0,0,Historical_Sales[[#This Row],[Units Ordered]]/Historical_Sales[[#This Row],[Sessions - Total]]) -> 0.43478261
A118: 45903 | B118: MN-35 | C118: 11 | D118: 16 | E118: 7 | F118: 241.18 | G118: 4 | H118: =IF(Historical_Sales[[#This Row],[Sessions - Total]]=0,0,Historical_Sales[[#This Row],[Units Ordered]]/Historical_Sales[[#This Row],[Sessions - Total]]) -> 0.63636364
A119: 45903 | B119: MN-36 | C119: 86 | D119: 117 | E119: 15 | F119: 477.43 | G119: 15 | H119: =IF(Historical_Sales[[#This Row],[Sessions - Total]]=0,0,Historical_Sales[[#This Row],[Units Ordered]]/Historical_Sales[[#This Row],[Sessions - Total]]) -> 0.1744186
A120: 45903 | B120: MN-37 | C120: 11 | D120: 15 | E120: 1 | F120: 34.82 | G120: 1 | H120: =IF(Historical_Sales[[#This Row],[Sessions - Total]]=0,0,Historical_Sales[[#This Row],[Units Ordered]]/Historical_Sales[[#This Row],[Sessions - Total]]) -> 0.090909091
A121: 45903 | B121: MN-38 | C121: 23 | D121: 31 | E121: 10 | F121: 299.22 | G121: 8 | H121: =IF(Historical_Sales[[#This Row],[Sessions - Total]]=0,0,Historical_Sales[[#This Row],[Units Ordered]]/Historical_Sales[[#This Row],[Sessions - Total]]) -> 0.43478261
A122: 45903 | B122: MN-40 | C122: 13 | D122: 23 | E122: 10 | F122: 250.69 | G122: 7 | H122: =IF(Historical_Sales[[#This Row],[Sessions - Total]]=0,0,Historical_Sales[[#This Row],[Units Ordered]]/Historical_Sales[[#This Row],[Sessions - Total]]) -> 0.76923077
... A1359: 45930 | B1359: MN-44 | C1359: 13 | D1359: 17 | E1359: 2 | F1359: 26.27 | G1359: 2 | H1359: =IF(Historical_Sales[[#This Row],[Sessions - Total]]=0,0,Historical_Sales[[#This Row],[Units Ordered]]/Historical_Sales[[#This Row],[Sessions - Total]]) -> 0.15384615
B1360: MN-45 | C1360: 10 | D1360: 11 | E1360: 1 | F1360: 37.44 | G1360: 1 | H1360: =IF(Historical_Sales[[#This Row],[Sessions - Total]]=0,0,Historical_Sales[[#This Row],[Units Ordered]]/Historical_Sales[[#This Row],[Sessions - Total]]) -> 0.1
B1361: MN-47 | C1361: 6 | D1361: 11 | E1361: 6 | F1361: 470.16 | G1361: 4 | H1361: =IF(Historical_Sales[[#This Row],[Sessions - Total]]=0,0,Historical_Sales[[#This Row],[Units Ordered]]/Historical_Sales[[#This Row],[Sessions - Total]]) -> 1
B1362: MN-50 | C1362: 28 | D1362: 44 | E1362: 3 | F1362: 107.47 | G1362: 3 | H1362: =IF(Historical_Sales[[#This Row],[Sessions - Total]]=0,0,Historical_Sales[[#This Row],[Units Ordered]]/Historical_Sales[[#This Row],[Sessions - Total]]) -> 0.10714286
A1363: 45667 | B1363: MN-01 | C1363: 17 | D1363: 19 | E1363: 6 | F1363: 228.85 | G1363: 6 | H1363: =IF(Historical_Sales[[#This Row],[Sessions - Total]]=0,0,Historical_Sales[[#This Row],[Units Ordered]]/Historical_Sales[[#This Row],[Sessions - Total]]) -> 0.35294118
A1364: 45931 | B1364: MN-02 | C1364: 23 | D1364: 32 | E1364: 5 | F1364: 197.57 | G1364: 4 | H1364: =IF(Historical_Sales[[#This Row],[Sessions - Total]]=0,0,Historical_Sales[[#This Row],[Units Ordered]]/Historical_Sales[[#This Row],[Sessions - Total]]) -> 0.2173913
A1365: 45931 | B1365: MN-06 | C1365: 6 | D1365: 9 | E1365: 2 | F1365: 37.78 | G1365: 2 | H1365: =IF(Historical_Sales[[#This Row],[Sessions - Total]]=0,0,Historical_Sales[[#This Row],[Units Ordered]]/Historical_Sales[[#This Row],[Sessions - Total]]) -> 0.33333333
A1366: 45931 | B1366: MN-07 | C1366: 15 | D1366: 22 | E1366: 5 | F1366: 172.98 | G1366: 4 | H1366: =IF(Historical_Sales[[#This Row],[Sessions - Total]]=0,0,Historical_Sales[[#This Row],[Units Ordered]]/Historical_Sales[[#This Row],[Sessions - Total]]) -> 0.33333333
A1367: 45931 | B1367: MN-08 | C1367: 5 | D1367: 7 | E1367: 1 | F1367: 34.5 | G1367: 1 | H1367: =IF(Historical_Sales[[#This Row],[Sessions - Total]]=0,0,Historical_Sales[[#This Row],[Units Ordered]]/Historical_Sales[[#This Row],[Sessions - Total]]) -> 0.2
A1368: 45931 | B1368: MN-10 | C1368: 17 | D1368: 33 | E1368: 3 | F1368: 74.06 | G1368: 3 | H1368: =IF(Historical_Sales[[#This Row],[Sessions - Total]]=0,0,Historical_Sales[[#This Row],[Units Ordered]]/Historical_Sales[[#This Row],[Sessions - Total]]) -> 0.17647059
A1369: 45931 | B1369: MN-11 | C1369: 19 | D1369: 22 | E1369: 3 | F1369: 60.39 | G1369: 3 | H1369: =IF(Historical_Sales[[#This Row],[Sessions - Total]]=0,0,Historical_Sales[[#This Row],[Units Ordered]]/Historical_Sales[[#This Row],[Sessions - Total]]) -> 0.15789474
A1370: 45931 | B1370: MN-11 | C1370: 3 | D1370: 5 | E1370: 2 | F1370: 50.38 | G1370: 1 | H1370: =IF(Historical_Sales[[#This Row],[Sessions - Total]]=0,0,Historical_Sales[[#This Row],[Units Ordered]]/Historical_Sales[[#This Row],[Sessions - Total]]) -> 0.66666667
A1371: 45931 | B1371: MN-12 | C1371: 17 | D1371: 28 | E1371: 4 | F1371: 94.79 | G1371: 4 | H1371: =IF(Historical_Sales[[#This Row],[Sessions - Total]]=0,0,Historical_Sales[[#This Row],[Units Ordered]]/Historical_Sales[[#This Row],[Sessions - Total]]) -> 0.23529412
A1372: 45931 | B1372: MN-13 | C1372: 30 | D1372: 34 | E1372: 7 | F1372: 176.17 | G1372: 7 | H1372: =IF(Historical_Sales[[#This Row],[Sessions - Total]]=0,0,Historical_Sales[[#This Row],[Units Ordered]]/Historical_Sales[[#This Row],[Sessions - Total]]) -> 0.23333333
A1373: 45931 | B1373: MN-14 | C1373: 38 | D1373: 50 | E1373: 7 | F1373: 207.56 | G1373: 6 | H1373: =IF(Historical_Sales[[#This Row],[Sessions - Total]]=0,0,Historical_Sales[[#This Row],[Units Ordered]]/Historical_Sales[[#This Row],[Sessions - Total]]) -> 0.18421053
A1374: 45931 | B1374: MN-15 | C1374: 118 | D1374: 173 | E1374: 32 | F1374: 800.08 | G1374: 31 | H1374: =IF(Historical_Sales[[#This Row],[Sessions - Total]]=0,0,Historical_Sales[[#This Row],[Units Ordered]]/Historical_Sales[[#This Row],[Sessions - Total]]) -> 0.27118644
... A2327: 45951 | B2327: MN-47 | C2327: 11 | D2327: 23 | E2327: 1 | F2327: 72.15 | G2327: 1 | H2327: =IF(Historical_Sales[[#This Row],[Sessions - Total]]=0,0,Historical_Sales[[#This Row],[Units Ordered]]/Historical_Sales[[#This Row],[Sessions - Total]]) -> 0.090909091
B2328: MN-48 | C2328: 9 | D2328: 13 | E2328: 3 | F2328: 230.14 | G2328: 3 | H2328: =IF(Historical_Sales[[#This Row],[Sessions - Total]]=0,0,Historical_Sales[[#This Row],[Units Ordered]]/Historical_Sales[[#This Row],[Sessions - Total]]) -> 0.33333333
B2329: MN-49 | C2329: 55 | D2329: 81 | E2329: 3 | F2329: 116.81 | G2329: 2 | H2329: =IF(Historical_Sales[[#This Row],[Sessions - Total]]=0,0,Historical_Sales[[#This Row],[Units Ordered]]/Historical_Sales[[#This Row],[Sessions - Total]]) -> 0.054545455
B2330: MN-50 | C2330: 21 | D2330: 27 | E2330: 1 | F2330: 28.07 | G2330: 1 | H2330: =IF(Historical_Sales[[#This Row],[Sessions - Total]]=0,0,Historical_Sales[[#This Row],[Units Ordered]]/Historical_Sales[[#This Row],[Sessions - Total]]) -> 0.047619048
B2331: MN-01 | C2331: 25 | D2331: 30 | E2331: 8 | F2331: 354.6 | G2331: 7 | H2331: =IF(Historical_Sales[[#This Row],[Sessions - Total]]=0,0,Historical_Sales[[#This Row],[Units Ordered]]/Historical_Sales[[#This Row],[Sessions - Total]]) -> 0.32
B2332: MN-02 | C2332: 18 | D2332: 21 | E2332: 4 | F2332: 149.16 | G2332: 3 | H2332: =IF(Historical_Sales[[#This Row],[Sessions - Total]]=0,0,Historical_Sales[[#This Row],[Units Ordered]]/Historical_Sales[[#This Row],[Sessions - Total]]) -> 0.22222222
A2333: 45952 | B2333: MN-03 | C2333: 8 | D2333: 11 | E2333: 1 | F2333: 33.22 | G2333: 1 | H2333: =IF(Historical_Sales[[#This Row],[Sessions - Total]]=0,0,Historical_Sales[[#This Row],[Units Ordered]]/Historical_Sales[[#This Row],[Sessions - Total]]) -> 0.125
A2334: 45952 | B2334: MN-04 | C2334: 11 | D2334: 17 | E2334: 3 | F2334: 97.49 | G2334: 2 | H2334: =IF(Historical_Sales[[#This Row],[Sessions - Total]]=0,0,Historical_Sales[[#This Row],[Units Ordered]]/Historical_Sales[[#This Row],[Sessions - Total]]) -> 0.27272727
A2335: 45952 | B2335: MN-05 | C2335: 9 | D2335: 15 | E2335: 2 | F2335: 41.26 | G2335: 2 | H2335: =IF(Historical_Sales[[#This Row],[Sessions - Total]]=0,0,Historical_Sales[[#This Row],[Units Ordered]]/Historical_Sales[[#This Row],[Sessions - Total]]) -> 0.22222222
A2336: 45952 | B2336: MN-06 | C2336: 11 | D2336: 12 | E2336: 1 | F2336: 16.31 | G2336: 1 | H2336: =IF(Historical_Sales[[#This Row],[Sessions - Total]]=0,0,Historical_Sales[[#This Row],[Units Ordered]]/Historical_Sales[[#This Row],[Sessions - Total]]) -> 0.090909091
A2337: 45952 | B2337: MN-07 | C2337: 24 | D2337: 34 | E2337: 4 | F2337: 143.6 | G2337: 4 | H2337: =IF(Historical_Sales[[#This Row],[Sessions - Total]]=0,0,Historical_Sales[[#This Row],[Units Ordered]]/Historical_Sales[[#This Row],[Sessions - Total]]) -> 0.16666667
A2338: 45952 | B2338: MN-08 | C2338: 5 | D2338: 8 | E2338: 1 | F2338: 30.36 | G2338: 1 | H2338: =IF(Historical_Sales[[#This Row],[Sessions - Total]]=0,0,Historical_Sales[[#This Row],[Units Ordered]]/Historical_Sales[[#This Row],[Sessions - Total]]) -> 0.2
A2339: 45952 | B2339: MN-09 | C2339: 2 | D2339: 3 | E2339: 1 | F2339: 18.24 | G2339: 1 | H2339: =IF(Historical_Sales[[#This Row],[Sessions - Total]]=0,0,Historical_Sales[[#This Row],[Units Ordered]]/Historical_Sales[[#This Row],[Sessions - Total]]) -> 0.5
A2340: 45952 | B2340: MN-10 | C2340: 24 | D2340: 38 | E2340: 7 | F2340: 149.99 | G2340: 7 | H2340: =IF(Historical_Sales[[#This Row],[Sessions - Total]]=0,0,Historical_Sales[[#This Row],[Units Ordered]]/Historical_Sales[[#This Row],[Sessions - Total]]) -> 0.29166667
A2341: 45952 | B2341: MN-11 | C2341: 23 | D2341: 42 | E2341: 5 | F2341: 92.11 | G2341: 5 | H2341: =IF(Historical_Sales[[#This Row],[Sessions - Total]]=0,0,Historical_Sales[[#This Row],[Units Ordered]]/Historical_Sales[[#This Row],[Sessions - Total]]) -> 0.2173913
A2342: 45952 | B2342: MN-12 | C2342: 30 | D2342: 42 | E2342: 3 | F2342: 72.27 | G2342: 3 | H2342: =IF(Historical_Sales[[#This Row],[Sessions - Total]]=0,0,Historical_Sales[[#This Row],[Units Ordered]]/Historical_Sales[[#This Row],[Sessions - Total]]) -> 0.1
A2343: 45952 | B2343: MN-12 | C2343: 2 | D2343: 3 | E2343: 1 | F2343: 44.87 | G2343: 1 | H2343: =IF(Historical_Sales[[#This Row],[Sessions - Total]]=0,0,Historical_Sales[[#This Row],[Units Ordered]]/Historical_Sales[[#This Row],[Sessions - Total]]) -> 0.5
A2344: 45952 | B2344: MN-13 | C2344: 38 | D2344: 51 | E2344: 3 | F2344: 82.78 | G2344: 3 | H2344: =IF(Historical_Sales[[#This Row],[Sessions - Total]]=0,0,Historical_Sales[[#This Row],[Units Ordered]]/Historical_Sales[[#This Row],[Sessions - Total]]) -> 0.078947368
... A2367: 45952 | B2367: MN-33 | C2367: 12 | D2367: 22 | E2367: 5 | F2367: 120.98 | G2367: 4 | H2367: =IF(Historical_Sales[[#This Row],[Sessions - Total]]=0,0,Historical_Sales[[#This Row],[Units Ordered]]/Historical_Sales[[#This Row],[Sessions - Total]]) -> 0.41666667
A2368: 45952 | B2368: MN-34 | H2368: =IF(Historical_Sales[[#This Row],[Sessions - Total]]=0,0,Historical_Sales[[#This Row],[Units Ordered]]/Historical_Sales[[#This Row],[Sessions - Total]]) -> 0
A2369: 45952 | B2369: MN-35 | C2369: 7 | D2369: 8 | E2369: 4 | F2369: 141.02 | G2369: 4 | H2369: =IF(Historical_Sales[[#This Row],[Sessions - Total]]=0,0,Historical_Sales[[#This Row],[Units Ordered]]/Historical_Sales[[#This Row],[Sessions - Total]]) -> 0.57142857
A2370: 45952 | B2370: MN-36 | C2370: 114 | D2370: 167 | E2370: 26 | F2370: 905.16 | G2370: 26 | H2370: =IF(Historical_Sales[[#This Row],[Sessions - Total]]=0,0,Historical_Sales[[#This Row],[Units Ordered]]/Historical_Sales[[#This Row],[Sessions - Total]]) -> 0.22807018
A2371: 45952 | B2371: MN-37 | C2371: 3 | D2371: 4 | E2371: 1 | F2371: 30.09 | G2371: 1 | H2371: =IF(Historical_Sales[[#This Row],[Sessions - Total]]=0,0,Historical_Sales[[#This Row],[Units Ordered]]/Historical_Sales[[#This Row],[Sessions - Total]]) -> 0.33333333
A2372: 45952 | B2372: MN-38 | C2372: 58 | D2372: 69 | E2372: 16 | F2372: 553.05 | G2372: 11 | H2372: =IF(Historical_Sales[[#This Row],[Sessions - Total]]=0,0,Historical_Sales[[#This Row],[Units Ordered]]/Historical_Sales[[#This Row],[Sessions - Total]]) -> 0.27586207
A2373: 45952 | B2373: MN-40 | C2373: 24 | D2373: 35 | E2373: 7 | F2373: 190.52 | G2373: 6 | H2373: =IF(Historical_Sales[[#This Row],[Sessions - Total]]=0,0,Historical_Sales[[#This Row],[Units Ordered]]/Historical_Sales[[#This Row],[Sessions - Total]]) -> 0.29166667
A2374: 45952 | B2374: MN-41 | C2374: 19 | D2374: 30 | E2374: 33 | F2374: 2485.98 | G2374: 7 | H2374: =IF(Historical_Sales[[#This Row],[Sessions - Total]]=0,0,Historical_Sales[[#This Row],[Units Ordered]]/Historical_Sales[[#This Row],[Sessions - Total]]) -> 1.7368421
A2375: 45952 | B2375: MN-42 | C2375: 29 | D2375: 36 | E2375: 21 | F2375: 1491.42 | G2375: 12 | H2375: =IF(Historical_Sales[[#This Row],[Sessions - Total]]=0,0,Historical_Sales[[#This Row],[Units Ordered]]/Historical_Sales[[#This Row],[Sessions - Total]]) -> 0.72413793
A2376: 45952 | B2376: MN-43 | C2376: 27 | D2376: 30 | E2376: 5 | F2376: 61.4 | G2376: 5 | H2376: =IF(Historical_Sales[[#This Row],[Sessions - Total]]=0,0,Historical_Sales[[#This Row],[Units Ordered]]/Historical_Sales[[#This Row],[Sessions - Total]]) -> 0.18518519
A2377: 45952 | B2377: MN-44 | C2377: 15 | D2377: 19 | E2377: 2 | F2377: 21.04 | G2377: 2 | H2377: =IF(Historical_Sales[[#This Row],[Sessions - Total]]=0,0,Historical_Sales[[#This Row],[Units Ordered]]/Historical_Sales[[#This Row],[Sessions - Total]]) -> 0.13333333
A2378: 45952 | B2378: MN-45 | C2378: 17 | D2378: 22 | E2378: 3 | F2378: 118.68 | G2378: 2 | H2378: =IF(Historical_Sales[[#This Row],[Sessions - Total]]=0,0,Historical_Sales[[#This Row],[Units Ordered]]/Historical_Sales[[#This Row],[Sessions - Total]]) -> 0.17647059
A2379: 45952 | B2379: MN-46 | C2379: 6 | D2379: 8 | E2379: 1 | F2379: 33.89 | G2379: 1 | H2379: =IF(Historical_Sales[[#This Row],[Sessions - Total]]=0,0,Historical_Sales[[#This Row],[Units Ordered]]/Historical_Sales[[#This Row],[Sessions - Total]]) -> 0.16666667
A2380: 45952 | B2380: MN-47 | C2380: 13 | D2380: 14 | E2380: 5 | F2380: 353.13 | G2380: 3 | H2380: =IF(Historical_Sales[[#This Row],[Sessions - Total]]=0,0,Historical_Sales[[#This Row],[Units Ordered]]/Historical_Sales[[#This Row],[Sessions - Total]]) -> 0.38461538
... A3590: 45978 | B3590: MN-26 | C3590: 34 | D3590: 48 | E3590: 26 | F3590: 860.75 | G3590: 16 | H3590: =IF(Historical_Sales[[#This Row],[Sessions - Total]]=0,0,Historical_Sales[[#This Row],[Units Ordered]]/Historical_Sales[[#This Row],[Sessions - Total]]) -> 0.76470588
A3591: 45978 | B3591: MN-27 | H3591: =IF(Historical_Sales[[#This Row],[Sessions - Total]]=0,0,Historical_Sales[[#This Row],[Units Ordered]]/Historical_Sales[[#This Row],[Sessions - Total]]) -> 0
A3592: 45978 | B3592: MN-28 | C3592: 55 | D3592: 75 | E3592: 29 | F3592: 806.98 | G3592: 27 | H3592: =IF(Historical_Sales[[#This Row],[Sessions - Total]]=0,0,Historical_Sales[[#This Row],[Units Ordered]]/Historical_Sales[[#This Row],[Sessions - Total]]) -> 0.52727273
A3593: 45978 | B3593: MN-29 | C3593: 62 | D3593: 84 | E3593: 28 | F3593: 661.17 | G3593: 18 | H3593: =IF(Historical_Sales[[#This Row],[Sessions - Total]]=0,0,Historical_Sales[[#This Row],[Units Ordered]]/Historical_Sales[[#This Row],[Sessions - Total]]) -> 0.4516129
A3594: 45978 | B3594: MN-30 | C3594: 64 | D3594: 86 | E3594: 17 | F3594: 634.42 | G3594: 15 | H3594: =IF(Historical_Sales[[#This Row],[Sessions - Total]]=0,0,Historical_Sales[[#This Row],[Units Ordered]]/Historical_Sales[[#This Row],[Sessions - Total]]) -> 0.265625
A3595: 45978 | B3595: MN-31 | C3595: 19 | D3595: 19 | E3595: 2 | F3595: 70.48 | G3595: 2 | H3595: =IF(Historical_Sales[[#This Row],[Sessions - Total]]=0,0,Historical_Sales[[#This Row],[Units Ordered]]/Historical_Sales[[#This Row],[Sessions - Total]]) -> 0.10526316
...

Sheet Competitor_Data
A1: SKU-Original | B1: SKU | C1: Avg_Comp_Price | D1: Lowest_Competitor_Price | E1: Highest_Competitor_Price | F1: Competitor_Count | G1: Effective_Competitor_Price | H1: Avg_Competitor_Price
A2: MN01 | B2: =LEFT(A2,2)&"-"&RIGHT(A2,2) -> MN-01 | C2: 36.9 | D2: 31.95 | E2: 44.9 | F2: 9 | G2: =IF( AND(Competitor_Data[[#This Row],[Lowest_Competitor_Price]]>0, Competitor_Data[[#This Row],[Highest_Competitor_Price]]>0), (Competitor_Data[[#This Row],[Lowest_Competitor_Price]] + Competitor_Data[[#This Row],[Highest_Competitor_Price]]) / 2, IF(Competitor_Data[[#This Row],[Lowest_Competitor_Price]]>0,Competitor_Data[[#This Row],[Lowest_Competitor_Price]],"") ) -> 38.425 | H2: =IF(Competitor_Data[[#This Row],[Avg_Comp_Price]]>0,Competitor_Data[[#This Row],[Avg_Comp_Price]],"") -> 36.9
A3: MN02 | B3: =LEFT(A3,2)&"-"&RIGHT(A3,2) -> MN-02 | C3: 32.5 | D3: 27.9 | E3: 39.95 | F3: 8 | G3: =IF( AND(Competitor_Data[[#This Row],[Lowest_Competitor_Price]]>0, Competitor_Data[[#This Row],[Highest_Competitor_Price]]>0), (Competitor_Data[[#This Row],[Lowest_Competitor_Price]] + Competitor_Data[[#This Row],[Highest_Competitor_Price]]) / 2, IF(Competitor_Data[[#This Row],[Lowest_Competitor_Price]]>0,Competitor_Data[[#This Row],[Lowest_Competitor_Price]],"") ) -> 33.925 | H3: =IF(Competitor_Data[[#This Row],[Avg_Comp_Price]]>0,Competitor_Data[[#This Row],[Avg_Comp_Price]],"") -> 32.5
A4: MN03 | B4: =LEFT(A4,2)&"-"&RIGHT(A4,2) -> MN-03 | C4: 35.2 | D4: 29.99 | E4: 42.5 | F4: 7 | G4: =IF( AND(Competitor_Data[[#This Row],[Lowest_Competitor_Price]]>0, Competitor_Data[[#This Row],[Highest_Competitor_Price]]>0), (Competitor_Data[[#This Row],[Lowest_Competitor_Price]] + Competitor_Data[[#This Row],[Highest_Competitor_Price]]) / 2, IF(Competitor_Data[[#This Row],[Lowest_Competitor_Price]]>0,Competitor_Data[[#This Row],[Lowest_Competitor_Price]],"") ) -> 36.245 | H4: =IF(Competitor_Data[[#This Row],[Avg_Comp_Price]]>0,Competitor_Data[[#This Row],[Avg_Comp_Price]],"") -> 35.2
A5: MN04 | B5: =LEFT(A5,2)&"-"&RIGHT(A5,2) -> MN-04 | C5: 28.4 | D5: 24.5 | E5: 35.9 | F5: 6 | G5: =IF( AND(Competitor_Data[[#This Row],[Lowest_Competitor_Price]]>0, Competitor_Data[[#This Row],[Highest_Competitor_Price]]>0), (Competitor_Data[[#This Row],[Lowest_Competitor_Price]] + Competitor_Data[[#This Row],[Highest_Competitor_Price]]) / 2, IF(Competitor_Data[[#This Row],[Lowest_Competitor_Price]]>0,Competitor_Data[[#This Row],[Lowest_Competitor_Price]],"") ) -> 30.2 | H5: =IF(Competitor_Data[[#This Row],[Avg_Comp_Price]]>0,Competitor_Data[[#This Row],[Avg_Comp_Price]],"") -> 28.4
A6: MN05 | B6: =LEFT(A6,2)&"-"&RIGHT(A6,2) -> MN-05 | C6: 23.9 | D6: 18.95 | F6: 3 | G6: =IF( AND(Competitor_Data[[#This Row],[Lowest_Competitor_Price]]>0, Competitor_Data[[#This Row],[Highest_Competitor_Price]]>0), (Competitor_Data[[#This Row],[Lowest_Competitor_Price]] + Competitor_Data[[#This Row],[Highest_Competitor_Price]]) / 2, IF(Competitor_Data[[#This Row],[Lowest_Competitor_Price]]>0,Competitor_Data[[#This Row],[Lowest_Competitor_Price]],"") ) -> 18.95 | H6: =IF(Competitor_Data[[#This Row],[Avg_Comp_Price]]>0,Competitor_Data[[#This Row],[Avg_Comp_Price]],"") -> 23.9
A7: MN06 | B7: =LEFT(A7,2)&"-"&RIGHT(A7,2) -> MN-06 | C7: 15.8 | D7: 12.99 | E7: 21.5 | F7: 4 | G7: =IF( AND(Competitor_Data[[#This Row],[Lowest_Competitor_Price]]>0, Competitor_Data[[#This Row],[Highest_Competitor_Price]]>0), (Competitor_Data[[#This Row],[Lowest_Competitor_Price]] + Competitor_Data[[#This Row],[Highest_Competitor_Price]]) / 2, IF(Competitor_Data[[#This Row],[Lowest_Competitor_Price]]>0,Competitor_Data[[#This Row],[Lowest_Competitor_Price]],"") ) -> 17.245 | H7: =IF(Competitor_Data[[#This Row],[Avg_Comp_Price]]>0,Competitor_Data[[#This Row],[Avg_Comp_Price]],"") -> 15.8
A8: MN07 | B8: =LEFT(A8,2)&"-"&RIGHT(A8,2) -> MN-07 | C8: 33.5 | D8: 28.9 | E8: 41.95 | F8: 10 | G8: =IF( AND(Competitor_Data[[#This Row],[Lowest_Competitor_Price]]>0, Competitor_Data[[#This Row],[Highest_Competitor_Price]]>0), (Competitor_Data[[#This Row],[Lowest_Competitor_Price]] + Competitor_Data[[#This Row],[Highest_Competitor_Price]]) / 2, IF(Competitor_Data[[#This Row],[Lowest_Competitor_Price]]>0,Competitor_Data[[#This Row],[Lowest_Competitor_Price]],"") ) -> 35.425 | H8: =IF(Competitor_Data[[#This Row],[Avg_Comp_Price]]>0,Competitor_Data[[#This Row],[Avg_Comp_Price]],"") -> 33.5
A9: MN08 | B9: =LEFT(A9,2)&"-"&RIGHT(A9,2) -> MN-08 | C9: 31.2 | D9: 25.95 | E9: 39.9 | F9: 6 | G9: =IF( AND(Competitor_Data[[#This Row],[Lowest_Competitor_Price]]>0, Competitor_Data[[#This Row],[Highest_Competitor_Price]]>0), (Competitor_Data[[#This Row],[Lowest_Competitor_Price]] + Competitor_Data[[#This Row],[Highest_Competitor_Price]]) / 2, IF(Competitor_Data[[#This Row],[Lowest_Competitor_Price]]>0,Competitor_Data[[#This Row],[Lowest_Competitor_Price]],"") ) -> 32.925 | H9: =IF(Competitor_Data[[#This Row],[Avg_Comp_Price]]>0,Competitor_Data[[#This Row],[Avg_Comp_Price]],"") -> 31.2
A10: MN09 | B10: =LEFT(A10,2)&"-"&RIGHT(A10,2) -> MN-09 | C10: 15.6 | D10: 11.99 | E10: 22.9 | F10: 5 | G10: =IF( AND(Competitor_Data[[#This Row],[Lowest_Competitor_Price]]>0, Competitor_Data[[#This Row],[Highest_Competitor_Price]]>0), (Competitor_Data[[#This Row],[Lowest_Competitor_Price]] + Competitor_Data[[#This Row],[Highest_Competitor_Price]]) / 2, IF(Competitor_Data[[#This Row],[Lowest_Competitor_Price]]>0,Competitor_Data[[#This Row],[Lowest_Competitor_Price]],"") ) -> 17.445 | H10: =IF(Competitor_Data[[#This Row],[Avg_Comp_Price]]>0,Competitor_Data[[#This Row],[Avg_Comp_Price]],"") -> 15.6
A11: MN10 | B11: =LEFT(A11,2)&"-"&RIGHT(A11,2) -> MN-10 | C11: 20.5 | D11: 16.95 | E11: 26.9 | F11: 9 | G11: =IF( AND(Competitor_Data[[#This Row],[Lowest_Competitor_Price]]>0, Competitor_Data[[#This Row],[Highest_Competitor_Price]]>0), (Competitor_Data[[#This Row],[Lowest_Competitor_Price]] + Competitor_Data[[#This Row],[Highest_Competitor_Price]]) / 2, IF(Competitor_Data[[#This Row],[Lowest_Competitor_Price]]>0,Competitor_Data[[#This Row],[Lowest_Competitor_Price]],"") ) -> 21.925 | H11: =IF(Competitor_Data[[#This Row],[Avg_Comp_Price]]>0,Competitor_Data[[#This Row],[Avg_Comp_Price]],"") -> 20.5
A12: MN11 | B12: =LEFT(A12,2)&"-"&RIGHT(A12,2) -> MN-11 | C12: 17.8 | D12: 14.99 | E12: 23.5 | F12: 8 | G12: =IF( AND(Competitor_Data[[#This Row],[Lowest_Competitor_Price]]>0, Competitor_Data[[#This Row],[Highest_Competitor_Price]]>0), (Competitor_Data[[#This Row],[Lowest_Competitor_Price]] + Competitor_Data[[#This Row],[Highest_Competitor_Price]]) / 2, IF(Competitor_Data[[#This Row],[Lowest_Competitor_Price]]>0,Competitor_Data[[#This Row],[Lowest_Competitor_Price]],"") ) -> 19.245 | H12: =IF(Competitor_Data[[#This Row],[Avg_Comp_Price]]>0,Competitor_Data[[#This Row],[Avg_Comp_Price]],"") -> 17.8
A13: MN12 | B13: =LEFT(A13,2)&"-"&RIGHT(A13,2) -> MN-12 | C13: 21.4 | D13: 17.95 | E13: 27.9 | F13: 9 | G13: =IF( AND(Competitor_Data[[#This Row],[Lowest_Competitor_Price]]>0, Competitor_Data[[#This Row],[Highest_Competitor_Price]]>0), (Competitor_Data[[#This Row],[Lowest_Competitor_Price]] + Competitor_Data[[#This Row],[Highest_Competitor_Price]]) / 2, IF(Competitor_Data[[#This Row],[Lowest_Competitor_Price]]>0,Competitor_Data[[#This Row],[Lowest_Competitor_Price]],"") ) -> 22.925 | H13: =IF(Competitor_Data[[#This Row],[Avg_Comp_Price]]>0,Competitor_Data[[#This Row],[Avg_Comp_Price]],"") -> 21.4
A14: MN13 | B14: =LEFT(A14,2)&"-"&RIGHT(A14,2) -> MN-13 | C14: 24.2 | D14: 19.99 | E14: 31.5 | F14: 8 | G14: =IF( AND(Competitor_Data[[#This Row],[Lowest_Competitor_Price]]>0, Competitor_Data[[#This Row],[Highest_Competitor_Price]]>0), (Competitor_Data[[#This Row],[Lowest_Competitor_Price]] + Competitor_Data[[#This Row],[Highest_Competitor_Price]]) / 2, IF(Competitor_Data[[#This Row],[Lowest_Competitor_Price]]>0,Competitor_Data[[#This Row],[Lowest_Competitor_Price]],"") ) -> 25.745 | H14: =IF(Competitor_Data[[#This Row],[Avg_Comp_Price]]>0,Competitor_Data[[#This Row],[Avg_Comp_Price]],"") -> 24.2
A15: MN14 | B15: =LEFT(A15,2)&"-"&RIGHT(A15,2) -> MN-14 | C15: 27.8 | D15: 23.95 | E15: 35.9 | F15: 7 | G15: =IF( AND(Competitor_Data[[#This Row],[Lowest_Competitor_Price]]>0, Competitor_Data[[#This Row],[Highest_Competitor_Price]]>0), (Competitor_Data[[#This Row],[Lowest_Competitor_Price]] + Competitor_Data[[#This Row],[Highest_Competitor_Price]]) / 2, IF(Competitor_Data[[#This Row],[Lowest_Competitor_Price]]>0,Competitor_Data[[#This Row],[Lowest_Competitor_Price]],"") ) -> 29.925 | H15: =IF(Competitor_Data[[#This Row],[Avg_Comp_Price]]>0,Competitor_Data[[#This Row],[Avg_Comp_Price]],"") -> 27.8
A16: MN15 | B16: =LEFT(A16,2)&"-"&RIGHT(A16,2) -> MN-15 | C16: 22.4 | D16: 18.99 | E16: 29.9 | F16: 9 | G16: =IF( AND(Competitor_Data[[#This Row],[Lowest_Competitor_Price]]>0, Competitor_Data[[#This Row],[Highest_Competitor_Price]]>0), (Competitor_Data[[#This Row],[Lowest_Competitor_Price]] + Competitor_Data[[#This Row],[Highest_Competitor_Price]]) / 2, IF(Competitor_Data[[#This Row],[Lowest_Competitor_Price]]>0,Competitor_Data[[#This Row],[Lowest_Competitor_Price]],"") ) -> 24.445 | H16: =IF(Competitor_Data[[#This Row],[Avg_Comp_Price]]>0,Competitor_Data[[#This Row],[Avg_Comp_Price]],"") -> 22.4
A17: MN16 | B17: =LEFT(A17,2)&"-"&RIGHT(A17,2) -> MN-16 | C17: 20.1 | D17: 16.95 | E17: 26.5 | F17: 8 | G17: =IF( AND(Competitor_Data[[#This Row],[Lowest_Competitor_Price]]>0, Competitor_Data[[#This Row],[Highest_Competitor_Price]]>0), (Competitor_Data[[#This Row],[Lowest_Competitor_Price]] + Competitor_Data[[#This Row],[Highest_Competitor_Price]]) / 2, IF(Competitor_Data[[#This Row],[Lowest_Competitor_Price]]>0,Competitor_Data[[#This Row],[Lowest_Competitor_Price]],"") ) -> 21.725 | H17: =IF(Competitor_Data[[#This Row],[Avg_Comp_Price]]>0,Competitor_Data[[#This Row],[Avg_Comp_Price]],"") -> 20.1
A18: MN17 | B18: =LEFT(A18,2)&"-"&RIGHT(A18,2) -> MN-17 | C18: 31.5 | D18: 26.99 | E18: 39.9 | F18: 9 | G18: =IF( AND(Competitor_Data[[#This Row],[Lowest_Competitor_Price]]>0, Competitor_Data[[#This Row],[Highest_Competitor_Price]]>0), (Competitor_Data[[#This Row],[Lowest_Competitor_Price]] + Competitor_Data[[#This Row],[Highest_Competitor_Price]]) / 2, IF(Competitor_Data[[#This Row],[Lowest_Competitor_Price]]>0,Competitor_Data[[#This Row],[Lowest_Competitor_Price]],"") ) -> 33.445 | H18: =IF(Competitor_Data[[#This Row],[Avg_Comp_Price]]>0,Competitor_Data[[#This Row],[Avg_Comp_Price]],"") -> 31.5
... A51: MN50 | B51: =LEFT(A51,2)&"-"&RIGHT(A51,2) -> MN-50 | C51: 30.2 | D51: 24.95 | E51: 38.9 | F51: 8 | G51: =IF( AND(Competitor_Data[[#This Row],[Lowest_Competitor_Price]]>0, Competitor_Data[[#This Row],[Highest_Competitor_Price]]>0), (Competitor_Data[[#This Row],[Lowest_Competitor_Price]] + Competitor_Data[[#This Row],[Highest_Competitor_Price]]) / 2, IF(Competitor_Data[[#This Row],[Lowest_Competitor_Price]]>0,Competitor_Data[[#This Row],[Lowest_Competitor_Price]],"") ) -> 31.925 | H51: =IF(Competitor_Data[[#This Row],[Avg_Comp_Price]]>0,Competitor_Data[[#This Row],[Avg_Comp_Price]],"") -> 30.2

Sheet Ads_Performance
A1: date | B1: SKU | C1: impressions | D1: clicks | E1: costPerClick | F1: clickThroughRate | G1: cost | H1: spend | I1: currency-code | J1: purchases1d | K1: purchases7d | L1: purchases14d | M1: purchases30d | N1: unitsSoldClicks1d | O1: unitsSoldClicks7d | P1: unitsSoldClicks14d | Q1: unitsSoldClicks30d | R1: sales1d | S1: sales7d | T1: sales14d | U1: sales30d | V1: acosClicks7d | W1: acosClicks14d | X1: roasClicks7d | Y1: roasClicks14d
A2: 45901 | B2: MN-16 | C2: 2016 | D2: 14 | E2: 1.998 | F2: 0.694 | G2: 27.97 | H2: 27.97 | I2: USD | J2: 1 | K2: 1 | L2: 1 | M2: 1 | N2: 1 | O2: 1 | P2: 1 | Q2: 1 | R2: 18.89 | S2: 18.89 | T2: 18.89 | U2: 18.89 | V2: 148.06776 | W2: 148.06776 | X2: 0.67536646 | Y2: 0.67536646
A3: 45901 | B3: MN-15 | C3: 1810 | D3: 33 | E3: 2.062 | F3: 1.823 | G3: 68.06 | H3: 68.06 | I3: USD | J3: 4 | K3: 6 | L3: 6 | M3: 6 | N3: 4 | O3: 6 | P3: 6 | Q3: 6 | R3: 107.45 | S3: 161.31 | T3: 161.31 | U3: 161.31 | V3: 42.192053 | W3: 42.192053 | X3: 2.3701146 | Y3: 2.3701146
A4: 45901 | B4: MN-14 | C4: 613 | D4: 9 | E4: 2.85 | F4: 1.468 | G4: 25.65 | H4: 25.65 | I4: USD | J4: 0 | K4: 1 | L4: 1 | M4: 1 | N4: 0 | O4: 1 | P4: 1 | Q4: 1 | R4: 0 | S4: 90.98 | T4: 90.98 | U4: 90.98 | V4: 28.193009 | W4: 28.193009 | X4: 3.5469786 | Y4: 3.5469786
A5: 45901 | B5: MN-17 | C5: 1271 | D5: 3 | E5: 5.62 | F5: 0.236 | G5: 16.86 | H5: 16.86 | I5: USD | J5: 2 | K5: 2 | L5: 2 | M5: 2 | N5: 9 | O5: 9 | P5: 9 | Q5: 9 | R5: 274.41 | S5: 274.41 | T5: 274.41 | U5: 274.41 | V5: 6.144091 | W5: 6.144091 | X5: 16.275801 | Y5: 16.275801
A6: 45901 | B6: MN-25 | C6: 1036 | D6: 10 | E6: 4.34 | F6: 0.965 | G6: 43.4 | H6: 43.4 | I6: USD | J6: 1 | K6: 3 | L6: 3 | M6: 3 | N6: 2 | O6: 8 | P6: 8 | Q6: 8 | R6: 218.3 | S6: 851.24 | T6: 851.24 | U6: 851.24 | V6: 5.0984446 | W6: 5.0984446 | X6: 19.613825 | Y6: 19.613825
A7: 45901 | B7: MN-13 | C7: 598 | D7: 6 | E7: 1.735 | F7: 1.003 | G7: 10.41 | H7: 10.41 | I7: USD | J7: 1 | K7: 1 | L7: 1 | M7: 1 | N7: 1 | O7: 1 | P7: 1 | Q7: 1 | R7: 21.49 | S7: 21.49 | T7: 21.49 | U7: 21.49 | V7: 48.441135 | W7: 48.441135 | X7: 2.0643612 | Y7: 2.0643612
A8: 45901 | B8: MN-22 | C8: 340 | D8: 10 | E8: 1.155 | F8: 2.941 | G8: 11.55 | H8: 11.55 | I8: USD | J8: 1 | K8: 1 | L8: 1 | M8: 1 | N8: 1 | O8: 1 | P8: 1 | Q8: 1 | R8: 22.49 | S8: 22.49 | T8: 22.49 | U8: 22.49 | V8: 51.356158 | W8: 51.356158 | X8: 1.9471861 | Y8: 1.9471861
A9: 45901 | B9: MN-19 | C9: 679 | D9: 5 | E9: 2.276 | F9: 0.736 | G9: 11.38 | H9: 11.38 | I9: USD | J9: 1 | K9: 1 | L9: 1 | M9: 1 | N9: 1 | O9: 1 | P9: 1 | Q9: 1 | R9: 30.49 | S9: 30.49 | T9: 30.49 | U9: 30.49 | V9: 37.323713 | W9: 37.323713 | X9: 2.6792619 | Y9: 2.6792619 | AE9: Ads Summary
A10: 45901 | B10: MN-37 | C10: 23 | D10: 0 | F10: 0 | G10: 0 | H10: 0 | I10: USD | J10: 0 | K10: 0 | L10: 0 | M10: 0 | N10: 0 | O10: 0 | P10: 0 | Q10: 0 | R10: 0 | S10: 0 | T10: 0 | U10: 0
A11: 45901 | B11: MN-12 | C11: 1495 | D11: 7 | E11: 1.316 | F11: 0.468 | G11: 9.21 | H11: 9.21 | I11: USD | J11: 1 | K11: 1 | L11: 1 | M11: 1 | N11: 1 | O11: 1 | P11: 1 | Q11: 1 | R11: 22.49 | S11: 22.49 | T11: 22.49 | U11: 22.49 | V11: 40.951534 | W11: 40.951534 | X11: 2.441911 | Y11: 2.441911 | AE11: Row Labels | AF11: Average of acosClicks14d | AG11: Average of roasClicks14d
A12: 45901 | B12: MN-25 | C12: 4486 | D12: 46 | E12: 4.791 | F12: 1.025 | G12: 220.37 | H12: 220.37 | I12: USD | J12: 15 | K12: 19 | L12: 19 | M12: 19 | N12: 16 | O12: 20 | P12: 20 | Q12: 20 | R12: 663.84 | S12: 811.29 | T12: 811.29 | U12: 811.29 | V12: 27.162913 | W12: 27.162913 | X12: 3.6814902 | Y12: 3.6814902 | AE12: MN-01 | AF12: 31.486923 | AG12: 6.0015491
A13: 45901 | B13: MN-26 | C13: 1251 | D13: 9 | E13: 4.401 | F13: 0.719 | G13: 39.61 | H13: 39.61 | I13: USD | J13: 3 | K13: 3 | L13: 3 | M13: 3 | N13: 5 | O13: 5 | P13: 5 | Q13: 5 | R13: 147.68 | S13: 147.68 | T13: 147.68 | U13: 147.68 | V13: 26.821506 | W13: 26.821506 | X13: 3.7283514 | Y13: 3.7283514 | AE13: MN-02 | AF13: 17.429955 | AG13: 11.141498
A14: 45901 | B14: MN-27 | C14: 497 | D14: 4 | E14: 5.113 | F14: 0.805 | G14: 20.45 | H14: 20.45 | I14: USD | J14: 2 | K14: 2 | L14: 2 | M14: 2 | N14: 2 | O14: 2 | P14: 2 | Q14: 2 | R14: 65.98 | S14: 65.98 | T14: 65.98 | U14: 65.98 | V14: 30.994241 | W14: 30.994241 | X14: 3.2264059 | Y14: 3.2264059 | AE14: MN-03 | AF14: 14.183546 | AG14: 10.859895
A15: 45901 | B15: MN-28 | C15: 1651 | D15: 15 | E15: 4.923 | F15: 0.909 | G15: 73.84 | H15: 73.84 | I15: USD | J15: 2 | K15: 4 | L15: 4 | M15: 4 | N15: 3 | O15: 5 | P15: 5 | Q15: 5 | R15: 76.47 | S15: 133.45 | T15: 133.45 | U15: 133.45 | V15: 55.331585 | W15: 55.331585 | X15: 1.807286 | Y15: 1.807286 | AE15: MN-04 | AF15: 40.747658 | AG15: 5.490357
A16: 45901 | B16: MN-29 | C16: 5392 | D16: 35 | E16: 3.765 | F16: 0.649 | G16: 131.79 | H16: 131.79 | I16: USD | J16: 16 | K16: 18 | L16: 18 | M16: 18 | N16: 24 | O16: 26 | P16: 26 | Q16: 26 | R16: 728.36 | S16: 777.34 | T16: 777.34 | U16: 777.34 | V16: 16.953971 | W16: 16.953971 | X16: 5.8983231 | Y16: 5.8983231 | AE16: MN-05 | AF16: 25.843374 | AG16: 2.5731512
A17: 45901 | B17: MN-30 | C17: 1232 | D17: 22 | E17: 3.333 | F17: 1.786 | G17: 73.32 | H17: 73.32 | I17: USD | J17: 4 | K17: 6 | L17: 6 | M17: 6 | N17: 5 | O17: 11 | P17: 11 | Q17: 11 | R17: 379.27 | S17: 946.42 | T17: 946.42 | U17: 946.42 | V17: 7.747089 | W17: 7.747089 | X17: 12.908074 | Y17: 12.908074 | AE17: MN-06 | AF17: 49.906491 | AG17: 1.8697301
A18: 45901 | B18: MN-32 | C18: 1185 | D18: 9 | E18: 4.152 | F18: 0.759 | G18: 37.37 | H18: 37.37 | I18: USD | J18: 6 | K18: 6 | L18: 6 | M18: 6 | N18: 19 | O18: 19 | P18: 19 | Q18: 19 | R18: 699.68 | S18: 699.68 | T18: 699.68 | U18: 699.68 | V18: 5.341013 | W18: 5.341013 | X18: 18.72304 | Y18: 18.72304 | AE18: MN-07 | AF18: 10.698216 | AG18: 8.6299209
A19: 45901 | B19: MN-33 | C19: 638 | D19: 8 | E19: 3.774 | F19: 1.254 | G19: 30.19 | H19: 30.19 | I19: USD | J19: 1 | K19: 2 | L19: 2 | M19: 2 | N19: 8 | O19: 9 | P19: 9 | Q19: 9 | R19: 231.04 | S19: 265.53 | T19: 265.53 | U19: 265.53 | V19: 11.369713 | W19: 11.369713 | X19: 8.7952965 | Y19: 8.7952965 | AE19: MN-08 | AF19: 4.6143725 | AG19: 9.9317801
A20: 45901 | B20: MN-34 | C20: 116 | D20: 4 | E20: 2.41 | F20: 3.448 | G20: 9.64 | H20: 9.64 | I20: USD | J20: 0 | K20: 0 | L20: 0 | M20: 0 | N20: 0 | O20: 0 | P20: 0 | Q20: 0 | R20: 0 | S20: 0 | T20: 0 | U20: 0 | X20: 0 | Y20: 0 | AE20: MN-09 | AF20: 13.280875 | AG20: 3.982438
A21: 45901 | B21: MN-35 | C21: 830 | D21: 12 | E21: 2.275 | F21: 1.446 | G21: 27.3 | H21: 27.3 | I21: USD | J21: 0 | K21: 0 | L21: 0 | M21: 0 | N21: 0 | O21: 0 | P21: 0 | Q21: 0 | R21: 0 | S21: 0 | T21: 0 | U21: 0 | X21: 0 | Y21: 0 | AE21: MN-10 | AF21: 18.167006 | AG21: 5.7078558
A22: 45901 | B22: MN-41 | C22: 572 | D22: 3 | E22: 6.83 | F22: 0.524 | G22: 20.49 | H22: 20.49 | I22: USD | J22: 1 | K22: 1 | L22: 1 | M22: 1 | N22: 1 | O22: 1 | P22: 1 | Q22: 1 | R22: 79.49 | S22: 79.49 | T22: 79.49 | U22: 79.49 | V22: 25.776827 | W22: 25.776827 | X22: 3.8794534 | Y22: 3.8794534 | AE22: MN-11 | AF22: 19.915199 | AG22: 5.6579079
A23: 45901 | B23: MN-42 | C23: 2288 | D23: 3 | E23: 2.787 | F23: 0.131 | G23: 8.36 | H23: 8.36 | I23: USD | J23: 1 | K23: 1 | L23: 1 | M23: 1 | N23: 6 | O23: 6 | P23: 6 | Q23: 6 | R23: 415.56 | S23: 415.56 | T23: 415.56 | U23: 415.56 | V23: 2.0117432 | W23: 2.0117432 | X23: 49.708134 | Y23: 49.708134 | AE23: MN-12 | AF23: 37.854601 | AG23: 3.7928957
A24: 45901 | B24: MN-01 | C24: 2325 | D24: 10 | E24: 2.914 | F24: 0.43 | G24: 29.14 | H24: 29.14 | I24: USD | J24: 1 | K24: 3 | L24: 3 | M24: 3 | N24: 2 | O24: 4 | P24: 4 | Q24: 4 | R24: 79.96 | S24: 105.76 | T24: 105.76 | U24: 105.76 | V24: 27.55295 | W24: 27.55295 | X24: 3.6293754 | Y24: 3.6293754 | AE24: MN-13 | AF24: 21.889256 | AG24: 4.7278648
A25: 45901 | B25: MN-40 | C25: 272 | D25: 3 | E25: 2.513 | F25: 1.103 | G25: 7.54 | H25: 7.54 | I25: USD | J25: 2 | K25: 2 | L25: 2 | M25: 2 | N25: 2 | O25: 2 | P25: 2 | Q25: 2 | R25: 53.98 | S25: 53.98 | T25: 53.98 | U25: 53.98 | V25: 13.968136 | W25: 13.968136 | X25: 7.1591512 | Y25: 7.1591512 | AE25: MN-14 | AF25: 39.26697 | AG25: 2.6835368
A26: 45901 | B26: MN-26 | C26: 429 | D26: 6 | E26: 4.317 | F26: 1.399 | G26: 25.9 | H26: 25.9 | I26: USD | J26: 1 | K26: 1 | L26: 1 | M26: 1 | N26: 1 | O26: 1 | P26: 1 | Q26: 1 | R26: 97.49 | S26: 97.49 | T26: 97.49 | U26: 97.49 | V26: 26.566827 | W26: 26.566827 | X26: 3.7640927 | Y26: 3.7640927 | AE26: MN-15 | AF26: 36.504738 | AG26: 2.9124937
A27: 45901 | B27: MN-30 | C27: 131 | D27: 1 | E27: 3.26 | F27: 0.763 | G27: 3.26 | H27: 3.26 | I27: USD | J27: 2 | K27: 2 | L27: 2 | M27: 2 | N27: 4 | O27: 4 | P27: 4 | Q27: 4 | R27: 368.74 | S27: 368.74 | T27: 368.74 | U27: 368.74 | V27: 0.88409177 | W27: 0.88409177 | X27: 113.11043 | Y27: 113.11043 | AE27: MN-16 | AF27: 36.226361 | AG27: 4.5109568
A28: 45901 | B28: MN-47 | C28: 49 | D28: 0 | F28: 0 | G28: 0 | H28: 0 | I28: USD | J28: 0 | K28: 0 | L28: 0 | M28: 0 | N28: 0 | O28: 0 | P28: 0 | Q28: 0 | R28: 0 | S28: 0 | T28: 0 | U28: 0 | AE28: MN-17 | AF28: 33.921212 | AG28: 3.2953448
A29: 45901 | B29: MN-35 | C29: 232 | D29: 2 | E29: 1.29 | F29: 0.862 | G29: 2.58 | H29: 2.58 | I29: USD | J29: 0 | K29: 0 | L29: 0 | M29: 0 | N29: 0 | O29: 0 | P29: 0 | Q29: 0 | R29: 0 | S29: 0 | T29: 0 | U29: 0 | X29: 0 | Y29: 0 | AE29: MN-18 | AF29: 17.877862 | AG29: 5.4322749
A30: 45901 | B30: MN-16 | C30: 67 | D30: 0 | F30: 0 | G30: 0 | H30: 0 | I30: USD | J30: 0 | K30: 0 | L30: 0 | M30: 0 | N30: 0 | O30: 0 | P30: 0 | Q30: 0 | R30: 0 | S30: 0 | T30: 0 | U30: 0 | AE30: MN-19 | AF30: 21.259657 | AG30: 6.9902913
A31: 45901 | B31: MN-14 | C31: 219 | D31: 2 | E31: 4.97 | F31: 0.913 | G31: 9.94 | H31: 9.94 | I31: USD | J31: 0 | K31: 0 | L31: 0 | M31: 0 | N31: 0 | O31: 0 | P31: 0 | Q31: 0 | R31: 0 | S31: 0 | T31: 0 | U31: 0 | X31: 0 | Y31: 0 | AE31: MN-20 | AF31: 27.650197 | AG31: 6.7823503
A32: 45901 | B32: MN-48 | C32: 108 | D32: 0 | F32: 0 | G32: 0 | H32: 0 | I32: USD | J32: 0 | K32: 0 | L32: 0 | M32: 0 | N32: 0 | O32: 0 | P32: 0 | Q32: 0 | R32: 0 | S32: 0 | T32: 0 | U32: 0 | AE32: MN-21 | AF32: 20.261531 | AG32: 6.1221186
A33: 45901 | B33: MN-25 | C33: 275 | D33: 2 | E33: 3.035 | F33: 0.727 | G33: 6.07 | H33: 6.07 | I33: USD | J33: 1 | K33: 1 | L33: 1 | M33: 1 | N33: 1 | O33: 1 | P33: 1 | Q33: 1 | R33: 114.49 | S33: 114.49 | T33: 114.49 | U33: 114.49 | V33: 5.3017731 | W33: 5.3017731 | X33: 18.861615 | Y33: 18.861615 | AE33: MN-22 | AF33: 29.912885 | AG33: 4.243145
A34: 45901 | B34: MN-15 | C34: 11 | D34: 0 | F34: 0 | G34: 0 | H34: 0 | I34: USD | J34: 0 | K34: 0 | L34: 0 | M34: 0 | N34: 0 | O34: 0 | P34: 0 | Q34: 0 | R34: 0 | S34: 0 | T34: 0 | U34: 0 | AE34: MN-23 | AF34: 20.877112 | AG34: 7.1217664
A35: 45901 | B35: MN-01 | C35: 115 | D35: 1 | E35: 2.41 | F35: 0.87 | G35: 2.41 | H35: 2.41 | I35: USD | J35: 1 | K35: 1 | L35: 1 | M35: 1 | N35: 1 | O35: 1 | P35: 1 | Q35: 1 | R35: 22.49 | S35: 22.49 | T35: 22.49 | U35: 22.49 | V35: 10.715874 | W35: 10.715874 | X35: 9.3319502 | Y35: 9.3319502 | AE35: MN-24 | AF35: 24.151847 | AG35: 4.0039273
A36: 45901 | B36: MN-45 | C36: 404 | D36: 2 | E36: 2.7 | F36: 0.495 | G36: 5.4 | H36: 5.4 | I36: USD | J36: 1 | K36: 1 | L36: 1 | M36: 1 | N36: 1 | O36: 1 | P36: 1 | Q36: 1 | R36: 28.89 | S36: 28.89 | T36: 28.89 | U36: 28.89 | V36: 18.691589 | W36: 18.691589 | X36: 5.35 | Y36: 5.35 | AE36: MN-25 | AF36: 23.889 | AG36: 6.1283927
A37: 45901 | B37: MN-43 | C37: 1569 | D37: 11 | E37: 2.304 | F37: 0.701 | G37: 25.34 | H37: 25.34 | I37: USD | J37: 1 | K37: 2 | L37: 2 | M37: 2 | N37: 1 | O37: 2 | P37: 2 | Q37: 2 | R37: 12.49 | S37: 25.38 | T37: 25.38 | U37: 25.38 | V37: 99.842396 | W37: 99.842396 | X37: 1.0015785 | Y37: 1.0015785 | AE37: MN-26 | AF37: 23.756626 | AG37: 5.3889616
A38: 45901 | B38: MN-46 | C38: 351 | D38: 1 | E38: 1.41 | F38: 0.285 | G38: 1.41 | H38: 1.41 | I38: USD | J38: 0 | K38: 0 | L38: 0 | M38: 0 | N38: 0 | O38: 0 | P38: 0 | Q38: 0 | R38: 0 | S38: 0 | T38: 0 | U38: 0 | X38: 0 | Y38: 0 | AE38: MN-27 | AF38: 26.476689 | AG38: 4.9770903
A39: 45901 | B39: MN-13 | C39: 2 | D39: 0 | F39: 0 | G39: 0 | H39: 0 | I39: USD | J39: 0 | K39: 0 | L39: 0 | M39: 0 | N39: 0 | O39: 0 | P39: 0 | Q39: 0 | R39: 0 | S39: 0 | T39: 0 | U39: 0 | AE39: MN-28 | AF39: 31.794818 | AG39: 4.3521146
A40: 45901 | B40: MN-15 | C40: 53 | D40: 2 | E40: 2.065 | F40: 3.774 | G40: 4.13 | H40: 4.13 | I40: USD | J40: 0 | K40: 0 | L40: 0 | M40: 0 | N40: 0 | O40: 0 | P40: 0 | Q40: 0 | R40: 0 | S40: 0 | T40: 0 | U40: 0 | X40: 0 | Y40: 0 | AE40: MN-29 | AF40: 30.863715 | AG40: 4.0026435
A41: 45901 | B41: MN-19 | C41: 6 | D41: 1 | E41: 1.44 | F41: 16.667 | G41: 1.44 | H41: 1.44 | I41: USD | J41: 0 | K41: 0 | L41: 0 | M41: 0 | N41: 0 | O41: 0 | P41: 0 | Q41: 0 | R41: 0 | S41: 0 | T41: 0 | U41: 0 | X41: 0 | Y41: 0 | AE41: MN-30 | AF41: 41.399948 | AG41: 4.7316132
A42: 45901 | B42: MN-30 | C42: 51 | D42: 1 | E42: 5.23 | F42: 1.961 | G42: 5.23 | H42: 5.23 | I42: USD | J42: 1 | K42: 1 | L42: 1 | M42: 1 | N42: 1 | O42: 1 | P42: 1 | Q42: 1 | R42: 35.49 | S42: 35.49 | T42: 35.49 | U42: 35.49 | V42: 14.736546 | W42: 14.736546 | X42: 6.7858509 | Y42: 6.7858509 | AE42: MN-31 | AF42: 30.909478 | AG42: 3.2006217
A43: 45901 | B43: MN-28 | C43: 552 | D43: 6 | E43: 4.363 | F43: 1.087 | G43: 26.18 | H43: 26.18 | I43: USD | J43: 1 | K43: 1 | L43: 1 | M43: 1 | N43: 1 | O43: 1 | P43: 1 | Q43: 1 | R43: 25.49 | S43: 25.49 | T43: 25.49 | U43: 25.49 | V43: 102.70694 | W43: 102.70694 | X43: 0.973644 | Y43: 0.973644 | AE43: MN-32 | AF43: 34.329271 | AG43: 11.633899
A44: 45901 | B44: MN-26 | C44: 322 | D44: 4 | E44: 4.923 | F44: 1.242 | G44: 19.69 | H44: 19.69 | I44: USD | J44: 0 | K44: 0 | L44: 0 | M44: 0 | N44: 0 | O44: 0 | P44: 0 | Q44: 0 | R44: 0 | S44: 0 | T44: 0 | U44: 0 | X44: 0 | Y44: 0 | AE44: MN-33 | AF44: 20.649876 | AG44: 7.1173458
A45: 45901 | B45: MN-07 | C45: 49 | D45: 0 | F45: 0 | G45: 0 | H45: 0 | I45: USD | J45: 0 | K45: 0 | L45: 0 | M45: 0 | N45: 0 | O45: 0 | P45: 0 | Q45: 0 | R45: 0 | S45: 0 | T45: 0 | U45: 0 | AE45: MN-34 | AF45: 27.686315 | AG45: 6.1022726
A46: 45901 | B46: MN-12 | C46: 26 | D46: 0 | F46: 0 | G46: 0 | H46: 0 | I46: USD | J46: 0 | K46: 0 | L46: 0 | M46: 0 | N46: 0 | O46: 0 | P46: 0 | Q46: 0 | R46: 0 | S46: 0 | T46: 0 | U46: 0 | AE46: MN-35 | AF46: 28.0262 | AG46: 4.4338583
A47: 45901 | B47: MN-33 | C47: 251 | D47: 2 | E47: 3.78 | F47: 0.797 | G47: 7.56 | H47: 7.56 | I47: USD | J47: 0 | K47: 0 | L47: 0 | M47: 0 | N47: 0 | O47: 0 | P47: 0 | Q47: 0 | R47: 0 | S47: 0 | T47: 0 | U47: 0 | X47: 0 | Y47: 0 | AE47: MN-36 | AF47: 30.369378 | AG47: 3.991366
A48: 45901 | B48: MN-41 | C48: 240 | D48: 3 | E48: 3.793 | F48: 1.25 | G48: 11.38 | H48: 11.38 | I48: USD | J48: 0 | K48: 0 | L48: 0 | M48: 0 | N48: 0 | O48: 0 | P48: 0 | Q48: 0 | R48: 0 | S48: 0 | T48: 0 | U48: 0 | X48: 0 | Y48: 0 | AE48: MN-37 | AF48: 20.675543 | AG48: 5.8465883
A49: 45901 | B49: MN-03 | C49: 40 | D49: 0 | F49: 0 | G49: 0 | H49: 0 | I49: USD | J49: 0 | K49: 0 | L49: 0 | M49: 0 | N49: 0 | O49: 0 | P49: 0 | Q49: 0 | R49: 0 | S49: 0 | T49: 0 | U49: 0 | AE49: MN-38 | AF49: 38.64259 | AG49: 3.7971713
A50: 45901 | B50: MN-03 | C50: 27 | D50: 1 | E50: 0.6 | F50: 3.704 | G50: 0.6 | H50: 0.6 | I50: USD | J50: 0 | K50: 0 | L50: 0 | M50: 0 | N50: 0 | O50: 0 | P50: 0 | Q50: 0 | R50: 0 | S50: 0 | T50: 0 | U50: 0 | X50: 0 | Y50: 0 | AE50: MN-39 | AF50: 35.948862 | AG50: 15.752303
A51: 45901 | B51: MN-03 | C51: 32 | D51: 0 | F51: 0 | G51: 0 | H51: 0 | I51: USD | J51: 0 | K51: 0 | L51: 0 | M51: 0 | N51: 0 | O51: 0 | P51: 0 | Q51: 0 | R51: 0 | S51: 0 | T51: 0 | U51: 0 | AE51: MN-40 | AF51: 22.002956 | AG51: 7.6587567
A52: 45901 | B52: MN-03 | C52: 41 | D52: 0 | F52: 0 | G52: 0 | H52: 0 | I52: USD | J52: 0 | K52: 0 | L52: 0 | M52: 0 | N52: 0 | O52: 0 | P52: 0 | Q52: 0 | R52: 0 | S52: 0 | T52: 0 | U52: 0 | AE52: MN-41 | AF52: 11.908474 | AG52: 13.133451
A53: 45901 | B53: MN-20 | C53: 519 | D53: 9 | E53: 0.528 | F53: 1.734 | G53: 4.75 | H53: 4.75 | I53: USD | J53: 0 | K53: 1 | L53: 1 | M53: 1 | N53: 0 | O53: 1 | P53: 1 | Q53: 1 | R53: 0 | S53: 12.9 | T53: 12.9 | U53: 12.9 | V53: 36.821705 | W53: 36.821705 | X53: 2.7157895 | Y53: 2.7157895 | AE53: MN-42 | AF53: 20.984806 | AG53: 9.5312154
A54: 45901 | B54: MN-20 | C54: 564 | D54: 7 | E54: 0.51 | F54: 1.241 | G54: 3.57 | H54: 3.57 | I54: USD | J54: 1 | K54: 1 | L54: 1 | M54: 1 | N54: 1 | O54: 1 | P54: 1 | Q54: 1 | R54: 12.49 | S54: 12.49 | T54: 12.49 | U54: 12.49 | V54: 28.582866 | W54: 28.582866 | X54: 3.4985994 | Y54: 3.4985994 | AE54: MN-43 | AF54: 76.702818 | AG54: 1.6074905
A55: 45901 | B55: MN-20 | C55: 431 | D55: 4 | E55: 0.495 | F55: 0.928 | G55: 1.98 | H55: 1.98 | I55: USD | J55: 0 | K55: 0 | L55: 0 | M55: 0 | N55: 0 | O55: 0 | P55: 0 | Q55: 0 | R55: 0 | S55: 0 | T55: 0 | U55: 0 | X55: 0 | Y55: 0 | AE55: MN-44 | AF55: 25.937288 | AG55: 5.8762181
A56: 45901 | B56: MN-20 | C56: 1225 | D56: 22 | E56: 0.351 | F56: 1.796 | G56: 7.73 | H56: 7.73 | I56: USD | J56: 3 | K56: 3 | L56: 3 | M56: 3 | N56: 3 | O56: 3 | P56: 3 | Q56: 3 | R56: 33.47 | S56: 33.47 | T56: 33.47 | U56: 33.47 | V56: 23.095309 | W56: 23.095309 | X56: 4.3298836 | Y56: 4.3298836 | AE56: MN-45 | AF56: 15.221962 | AG56: 16.043456
A57: 45901 | B57: MN-50 | C57: 113 | D57: 1 | E57: 1.92 | F57: 0.885 | G57: 1.92 | H57: 1.92 | I57: USD | J57: 0 | K57: 0 | L57: 0 | M57: 0 | N57: 0 | O57: 0 | P57: 0 | Q57: 0 | R57: 0 | S57: 0 | T57: 0 | U57: 0 | X57: 0 | Y57: 0 | AE57: MN-46 | AF57: 18.265842 | AG57: 3.6313231
A58: 45901 | B58: MN-02 | C58: 281 | D58: 3 | E58: 1.34 | F58: 1.068 | G58: 4.02 | H58: 4.02 | I58: USD | J58: 1 | K58: 1 | L58: 1 | M58: 1 | N58: 1 | O58: 1 | P58: 1 | Q58: 1 | R58: 34.49 | S58: 34.49 | T58: 34.49 | U58: 34.49 | V58: 11.655552 | W58: 11.655552 | X58: 8.579602 | Y58: 8.579602 | AE58: MN-47 | AF58: 9.8930438 | AG58: 11.574952
A59: 45901 | B59: MN-50 | C59: 221 | D59: 4 | E59: 1.043 | F59: 1.81 | G59: 4.17 | H59: 4.17 | I59: USD | J59: 0 | K59: 0 | L59: 0 | M59: 0 | N59: 0 | O59: 0 | P59: 0 | Q59: 0 | R59: 0 | S59: 0 | T59: 0 | U59: 0 | X59: 0 | Y59: 0 | AE59: MN-48 | AF59: 14.015364 | AG59: 9.3063031
A60: 45901 | B60: MN-02 | C60: 480 | D60: 2 | E60: 0.945 | F60: 0.417 | G60: 1.89 | H60: 1.89 | I60: USD | J60: 1 | K60: 1 | L60: 1 | M60: 1 | N60: 1 | O60: 1 | P60: 1 | Q60: 1 | R60: 30.49 | S60: 30.49 | T60: 30.49 | U60: 30.49 | V60: 6.1987537 | W60: 6.1987537 | X60: 16.132275 | Y60: 16.132275 | AE60: MN-49 | AF60: 13.67693 | AG60: 5.4294372
A61: 45901 | B61: MN-02 | C61: 218 | D61: 1 | E61: 0.37 | F61: 0.459 | G61: 0.37 | H61: 0.37 | I61: USD | J61: 0 | K61: 0 | L61: 0 | M61: 0 | N61: 0 | O61: 0 | P61: 0 | Q61: 0 | R61: 0 | S61: 0 | T61: 0 | U61: 0 | X61: 0 | Y61: 0 | AE61: MN-50 | AF61: 12.42124 | AG61: 6.89907
A62: 45901 | B62: MN-50 | C62: 59 | D62: 0 | F62: 0 | G62: 0 | H62: 0 | I62: USD | J62: 0 | K62: 0 | L62: 0 | M62: 0 | N62: 0 | O62: 0 | P62: 0 | Q62: 0 | R62: 0 | S62: 0 | T62: 0 | U62: 0 | AE62: Grand Total | AF62: 25.483196 | AG62: 6.198352
A63: 45901 | B63: MN-02 | C63: 902 | D63: 10 | E63: 0.678 | F63: 1.109 | G63: 6.78 | H63: 6.78 | I63: USD | J63: 1 | K63: 1 | L63: 1 | M63: 1 | N63: 1 | O63: 1 | P63: 1 | Q63: 1 | R63: 35.88 | S63: 35.88 | T63: 35.88 | U63: 35.88 | V63: 18.896321 | W63: 18.896321 | X63: 5.2920354 | Y63: 5.2920354
A64: 45901 | B64: MN-50 | C64: 385 | D64: 0 | F64: 0 | G64: 0 | H64: 0 | I64: USD | J64: 0 | K64: 0 | L64: 0 | M64: 0 | N64: 0 | O64: 0 | P64: 0 | Q64: 0 | R64: 0 | S64: 0 | T64: 0 | U64: 0
A65: 45901 | B65: MN-44 | C65: 11 | D65: 0 | F65: 0 | G65: 0 | H65: 0 | I65: USD | J65: 0 | K65: 0 | L65: 0 | M65: 0 | N65: 0 | O65: 0 | P65: 0 | Q65: 0 | R65: 0 | S65: 0 | T65: 0 | U65: 0
A66: 45901 | B66: MN-21 | C66: 1157 | D66: 15 | E66: 1.325 | F66: 1.296 | G66: 19.87 | H66: 19.87 | I66: USD | J66: 2 | K66: 2 | L66: 2 | M66: 2 | N66: 2 | O66: 2 | P66: 2 | Q66: 2 | R66: 44.98 | S66: 44.98 | T66: 44.98 | U66: 44.98 | V66: 44.175189 | W66: 44.175189 | X66: 2.2637141 | Y66: 2.2637141
A67: 45901 | B67: MN-24 | C67: 272 | D67: 1 | E67: 1.44 | F67: 0.368 | G67: 1.44 | H67: 1.44 | I67: USD | J67: 0 | K67: 0 | L67: 0 | M67: 0 | N67: 0 | O67: 0 | P67: 0 | Q67: 0 | R67: 0 | S67: 0 | T67: 0 | U67: 0 | X67: 0 | Y67: 0
A68: 45901 | B68: MN-24 | C68: 909 | D68: 7 | E68: 0.916 | F68: 0.77 | G68: 6.41 | H68: 6.41 | I68: USD | J68: 2 | K68: 2 | L68: 2 | M68: 2 | N68: 2 | O68: 2 | P68: 2 | Q68: 2 | R68: 55.98 | S68: 55.98 | T68: 55.98 | U68: 55.98 | V68: 11.450518 | W68: 11.450518 | X68: 8.7332293 | Y68: 8.7332293
A69: 45901 | B69: MN-44 | C69: 26 | D69: 0 | F69: 0 | G69: 0 | H69: 0 | I69: USD | J69: 0 | K69: 0 | L69: 0 | M69: 0 | N69: 0 | O69: 0 | P69: 0 | Q69: 0 | R69: 0 | S69: 0 | T69: 0 | U69: 0
A70: 45901 | B70: MN-21 | C70: 3459 | D70: 22 | E70: 1.171 | F70: 0.636 | G70: 25.77 | H70: 25.77 | I70: USD | J70: 2 | K70: 2 | L70: 2 | M70: 2 | N70: 2 | O70: 2 | P70: 2 | Q70: 2 | R70: 45.39 | S70: 45.39 | T70: 45.39 | U70: 45.39 | V70: 56.77462 | W70: 56.77462 | X70: 1.7613504 | Y70: 1.7613504
A71: 45901 | B71: MN-44 | C71: 107 | D71: 0 | F71: 0 | G71: 0 | H71: 0 | I71: USD | J71: 0 | K71: 0 | L71: 0 | M71: 0 | N71: 0 | O71: 0 | P71: 0 | Q71: 0 | R71: 0 | S71: 0 | T71: 0 | U71: 0
A72: 45901 | B72: MN-21 | C72: 771 | D72: 5 | E72: 1.292 | F72: 0.649 | G72: 6.46 | H72: 6.46 | I72: USD | J72: 1 | K72: 1 | L72: 1 | M72: 1 | N72: 1 | O72: 1 | P72: 1 | Q72: 1 | R72: 18.89 | S72: 18.89 | T72: 18.89 | U72: 18.89 | V72: 34.197988 | W72: 34.197988 | X72: 2.9241486 | Y72: 2.9241486
A73: 45901 | B73: MN-24 | C73: 736 | D73: 7 | E73: 1.436 | F73: 0.951 | G73: 10.05 | H73: 10.05 | I73: USD | J73: 1 | K73: 1 | L73: 1 | M73: 1 | N73: 1 | O73: 1 | P73: 1 | Q73: 1 | R73: 20.49 | S73: 20.49 | T73: 20.49 | U73: 20.49 | V73: 49.048316 | W73: 49.048316 | X73: 2.038806 | Y73: 2.038806
A74: 45901 | B74: MN-21 | C74: 2708 | D74: 21 | E74: 0.868 | F74: 0.775 | G74: 18.23 | H74: 18.23 | I74: USD | J74: 1 | K74: 3 | L74: 3 | M74: 3 | N74: 1 | O74: 3 | P74: 3 | Q74: 3 | R74: 20.49 | S74: 79.25 | T74: 79.25 | U74: 79.25 | V74: 23.003155 | W74: 23.003155 | X74: 4.3472298 | Y74: 4.3472298
A75: 45901 | B75: MN-44 | C75: 99 | D75: 0 | F75: 0 | G75: 0 | H75: 0 | I75: USD | J75: 0 | K75: 0 | L75: 0 | M75: 0 | N75: 0 | O75: 0 | P75: 0 | Q75: 0 | R75: 0 | S75: 0 | T75: 0 | U75: 0
A76: 45901 | B76: MN-24 | C76: 867 | D76: 6 | E76: 0.707 | F76: 0.692 | G76: 4.24 | H76: 4.24 | I76: USD | J76: 0 | K76: 0 | L76: 0 | M76: 0 | N76: 0 | O76: 0 | P76: 0 | Q76: 0 | R76: 0 | S76: 0 | T76: 0 | U76: 0 | X76: 0 | Y76: 0
A77: 45901 | B77: MN-18 | C77: 313 | D77: 3 | E77: 2.27 | F77: 0.958 | G77: 6.81 | H77: 6.81 | I77: USD | J77: 0 | K77: 0 | L77: 0 | M77: 0 | N77: 0 | O77: 0 | P77: 0 | Q77: 0 | R77: 0 | S77: 0 | T77: 0 | U77: 0 | X77: 0 | Y77: 0
A78: 45901 | B78: MN-18 | C78: 740 | D78: 5 | E78: 1.5 | F78: 0.676 | G78: 7.5 | H78: 7.5 | I78: USD | J78: 0 | K78: 0 | L78: 0 | M78: 0 | N78: 0 | O78: 0 | P78: 0 | Q78: 0 | R78: 0 | S78: 0 | T78: 0 | U78: 0 | X78: 0 | Y78: 0
A79: 45901 | B79: MN-18 | C79: 688 | D79: 4 | E79: 1.548 | F79: 0.581 | G79: 6.19 | H79: 6.19 | I79: USD | J79: 1 | K79: 1 | L79: 1 | M79: 1 | N79: 1 | O79: 1 | P79: 1 | Q79: 1 | R79: 27.49 | S79: 27.49 | T79: 27.49 | U79: 27.49 | V79: 22.517279 | W79: 22.517279 | X79: 4.4410339 | Y79: 4.4410339
A80: 45901 | B80: MN-18 | C80: 1128 | D80: 5 | E80: 1.32 | F80: 0.443 | G80: 6.6 | H80: 6.6 | I80: USD | J80: 1 | K80: 2 | L80: 2 | M80: 2 | N80: 3 | O80: 7 | P80: 7 | Q80: 7 | R80: 82.47 | S80: 194.07 | T80: 194.07 | U80: 194.07 | V80: 3.4008348 | W80: 3.4008348 | X80: 29.404545 | Y80: 29.404545
A81: 45901 | B81: MN-04 | C81: 13 | D81: 0 | F81: 0 | G81: 0 | H81: 0 | I81: USD | J81: 0 | K81: 0 | L81: 0 | M81: 0 | N81: 0 | O81: 0 | P81: 0 | Q81: 0 | R81: 0 | S81: 0 | T81: 0 | U81: 0
A82: 45901 | B82: MN-39 | C82: 13 | D82: 0 | F82: 0 | G82: 0 | H82: 0 | I82: USD | J82: 0 | K82: 0 | L82: 0 | M82: 0 | N82: 0 | O82: 0 | P82: 0 | Q82: 0 | R82: 0 | S82: 0 | T82: 0 | U82: 0
A83: 45901 | B83: MN-04 | C83: 25 | D83: 0 | F83: 0 | G83: 0 | H83: 0 | I83: USD | J83: 0 | K83: 0 | L83: 0 | M83: 0 | N83: 0 | O83: 0 | P83: 0 | Q83: 0 | R83: 0 | S83: 0 | T83: 0 | U83: 0
A84: 45901 | B84: MN-39 | C84: 23 | D84: 0 | F84: 0 | G84: 0 | H84: 0 | I84: USD | J84: 0 | K84: 0 | L84: 0 | M84: 0 | N84: 0 | O84: 0 | P84: 0 | Q84: 0 | R84: 0 | S84: 0 | T84: 0 | U84: 0
A85: 45901 | B85: MN-04 | C85: 88 | D85: 0 | F85: 0 | G85: 0 | H85: 0 | I85: USD | J85: 0 | K85: 0 | L85: 0 | M85: 0 | N85: 0 | O85: 0 | P85: 0 | Q85: 0 | R85: 0 | S85: 0 | T85: 0 | U85: 0
A86: 45901 | B86: MN-39 | C86: 16 | D86: 0 | F86: 0 | G86: 0 | H86: 0 | I86: USD | J86: 0 | K86: 0 | L86: 0 | M86: 0 | N86: 0 | O86: 0 | P86: 0 | Q86: 0 | R86: 0 | S86: 0 | T86: 0 | U86: 0
A87: 45901 | B87: MN-04 | C87: 124 | D87: 0 | F87: 0 | G87: 0 | H87: 0 | I87: USD | J87: 0 | K87: 0 | L87: 0 | M87: 0 | N87: 0 | O87: 0 | P87: 0 | Q87: 0 | R87: 0 | S87: 0 | T87: 0 | U87: 0
A88: 45901 | B88: MN-39 | C88: 18 | D88: 0 | F88: 0 | G88: 0 | H88: 0 | I88: USD | J88: 0 | K88: 0 | L88: 0 | M88: 0 | N88: 0 | O88: 0 | P88: 0 | Q88: 0 | R88: 0 | S88: 0 | T88: 0 | U88: 0
A89: 45901 | B89: MN-23 | C89: 224 | D89: 3 | E89: 0.883 | F89: 1.339 | G89: 2.65 | H89: 2.65 | I89: USD | J89: 1 | K89: 1 | L89: 1 | M89: 1 | N89: 1 | O89: 1 | P89: 1 | Q89: 1 | R89: 10.49 | S89: 10.49 | T89: 10.49 | U89: 10.49 | V89: 25.262154 | W89: 25.262154 | X89: 3.9584906 | Y89: 3.9584906
A90: 45901 | B90: MN-49 | C90: 165 | D90: 3 | E90: 1.85 | F90: 1.818 | G90: 5.55 | H90: 5.55 | I90: USD | J90: 0 | K90: 0 | L90: 0 | M90: 0 | N90: 0 | O90: 0 | P90: 0 | Q90: 0 | R90: 0 | S90: 0 | T90: 0 | U90: 0 | X90: 0 | Y90: 0
A91: 45901 | B91: MN-11 | C91: 583 | D91: 1 | E91: 2.07 | F91: 0.172 | G91: 2.07 | H91: 2.07 | I91: USD | J91: 0 | K91: 0 | L91: 0 | M91: 0 | N91: 0 | O91: 0 | P91: 0 | Q91: 0 | R91: 0 | S91: 0 | T91: 0 | U91: 0 | X91: 0 | Y91: 0
A92: 45901 | B92: MN-08 | C92: 28 | D92: 0 | F92: 0 | G92: 0 | H92: 0 | I92: USD | J92: 0 | K92: 0 | L92: 0 | M92: 0 | N92: 0 | O92: 0 | P92: 0 | Q92: 0 | R92: 0 | S92: 0 | T92: 0 | U92: 0
A93: 45901 | B93: MN-23 | C93: 245 | D93: 4 | E93: 0.78 | F93: 1.633 | G93: 3.12 | H93: 3.12 | I93: USD | J93: 3 | K93: 3 | L93: 3 | M93: 3 | N93: 3 | O93: 3 | P93: 3 | Q93: 3 | R93: 69.47 | S93: 69.47 | T93: 69.47 | U93: 69.47 | V93: 4.4911473 | W93: 4.4911473 | X93: 22.266026 | Y93: 22.266026
A94: 45901 | B94: MN-49 | C94: 247 | D94: 0 | F94: 0 | G94: 0 | H94: 0 | I94: USD | J94: 0 | K94: 0 | L94: 0 | M94: 0 | N94: 0 | O94: 0 | P94: 0 | Q94: 0 | R94: 0 | S94: 0 | T94: 0 | U94: 0
A95: 45901 | B95: MN-11 | C95: 1465 | D95: 3 | E95: 1.07 | F95: 0.205 | G95: 3.21 | H95: 3.21 | I95: USD | J95: 1 | K95: 1 | L95: 1 | M95: 1 | N95: 1 | O95: 1 | P95: 1 | Q95: 1 | R95: 20.49 | S95: 20.49 | T95: 20.49 | U95: 20.49 | V95: 15.666179 | W95: 15.666179 | X95: 6.3831776 | Y95: 6.3831776
A96: 45901 | B96: MN-08 | C96: 81 | D96: 0 | F96: 0 | G96: 0 | H96: 0 | I96: USD | J96: 0 | K96: 0 | L96: 0 | M96: 0 | N96: 0 | O96: 0 | P96: 0 | Q96: 0 | R96: 0 | S96: 0 | T96: 0 | U96: 0
A97: 45901 | B97: MN-08 | C97: 73 | D97: 0 | F97: 0 | G97: 0 | H97: 0 | I97: USD | J97: 0 | K97: 0 | L97: 0 | M97: 0 | N97: 0 | O97: 0 | P97: 0 | Q97: 0 | R97: 0 | S97: 0 | T97: 0 | U97: 0
A98: 45901 | B98: MN-23 | C98: 297 | D98: 3 | E98: 0.88 | F98: 1.01 | G98: 2.64 | H98: 2.64 | I98: USD | J98: 1 | K98: 1 | L98: 1 | M98: 1 | N98: 1 | O98: 1 | P98: 1 | Q98: 1 | R98: 10.98 | S98: 10.98 | T98: 10.98 | U98: 10.98 | V98: 24.043716 | W98: 24.043716 | X98: 4.1590909 | Y98: 4.1590909
A99: 45901 | B99: MN-49 | C99: 293 | D99: 3 | E99: 0.86 | F99: 1.024 | G99: 2.58 | H99: 2.58 | I99: USD | J99: 0 | K99: 0 | L99: 0 | M99: 0 | N99: 0 | O99: 0 | P99: 0 | Q99: 0 | R99: 0 | S99: 0 | T99: 0 | U99: 0 | X99: 0 | Y99: 0
A100: 45901 | B100: MN-11 | C100: 760 | D100: 4 | E100: 1.095 | F100: 0.526 | G100: 4.38 | H100: 4.38 | I100: USD | J100: 0 | K100: 0 | L100: 0 | M100: 0 | N100: 0 | O100: 0 | P100: 0 | Q100: 0 | R100: 0 | S100: 0 | T100: 0 | U100: 0 | X100: 0 | Y100: 0
...

Sheet Extra Sheet
D2: Pivot Tables for Charts
B4: Row Labels | C4: Count of SKU | E4: SKU | F4: Price Change
B5: No | C5: 37 | E5: MN-13 | F5: 1.3
B6: Yes | C6: 13 | E6: MN-24 | F6: -0.14
B7: Grand Total | C7: 50 | E7: MN-29 | F7: 0.9
E8: MN-33 | F8: 7.4593231
E9: MN-40 | F9: 1.747
B10: Row Labels | C10: Count of SKU | E10: MN-41 | F10: 6.075
B11: Competitor benchmark | C11: 11 | E11: MN-42 | F11: 5.204
B12: Minimum margin constraint | C12: 37 | E12: MN-43 | F12: 0.16
B13: Overstock | C13: 2 | E13: MN-44 | F13: 2.2184615
B14: Grand Total | C14: 50 | E14: MN-45 | F14: 2.442
E15: MN-46 | F15: 0.555
E16: MN-47 | F16: 1.7714
E17: MN-48 | F17: -3.5963
